Workbook

Sheet Rates
A1: Price List Data 17-07-21 | C1: Price june 2025 | D1: Previous Price
A3: 1 | B3: C.I. Gills | C3: 170 | D3: 170 | J3: Bought Out Items | P3: ENCON PURCHASE PRICE
A4: 2 | B4: C.I. Hub | C4: 375 | D4: 375 | K4: Price 2025 | M4: Previous price | P4: ITEM | S4: PRICE (Rs.) 2025 | U4: previous price
A5: 3 | B5: Coupling | C5: 350 | D5: 250 | J5: Casting Burner Parts | K5: 100 | L5: Per Kg | M5: 90 | P5: SEQUENCE CONTROLLER | T5: 10640 | U5: 5935.4
A6: 4 | B6: Hardware Bolt | C6: 150 | D6: 150 | J6: SS Assly 2A/3A | K6: 2500 | M6: 2300 | P6: VACUUM SWITCH | T6: 1200 | U6: 882
A7: 5 | B7: M.S. Angle 100,100 | C7: 71 | D7: 71 | J7: SS Assly 4A | K7: 2600 | M7: 2400 | P7: ARE-13 Burner Alone | T7: 30000 | U7: 21550
A8: 6 | B8: M.S. Angle 50*6 | C8: 71 | D8: 71 | J8: SS Assly 5A/6A | K8: 5000 | M8: 4500 | P8: ARE-22 Burner Alone | T8: 34400 | U8: 32623
A9: 7 | B9: M.S. Angle 65,50 | C9: 71 | D9: 71 | J9: SS Assly 7A | K9: 26000 | M9: 23000 | P9: ARE-35 Burner Alone | T9: 49000 | U9: =(27497/76.9)*79*1.4
A10: 8 | B10: M.S. Chanel | C10: 71 | D10: 71 | J10: Micro Valve 2A/3A | K10: 2300 | M10: 2075 | P10: ARE-50 Burner Alone | T10: 50000 | U10: 38000 | X10: 35000
A11: 9 | B11: M.S. Flat | C11: 71 | D11: 71 | J11: Micro Valve 4A | K11: 2300 | M11: 2075 | P11: ID FAN (ARE 13 & ARE 22) | T11: 14000 | U11: 10278.46
A12: 10 | B12: M.S. Plate 16mm* 5mm | C12: 72 | D12: 72 | J12: Micro Valve 5A/6A | K12: 2300 | M12: 2075 | P12: ID FAN (ARE 35) | T12: 15247 | U12: 10877.7
A13: 11 | B13: M.S. Plate 16mm*10mm | C13: 72 | D13: 72 | J13: Micro Valve 7A | K13: 2500 | M13: 2125 | P13: ID FAN (HEAVY DUTY) | T13: 25550 | U13: 19254
A14: 12 | B14: M.S. Plate 5mm | C14: 72 | D14: 72 | J14: FLEXIBLE HOSE-15NB*750MM (OIL ) | K14: 590 | M14: 590 | P14: ID FAN (TYPE O FAN) | T14: 45000 | U14: 41236 | V14: Check this fig
A15: 13 | B15: M.S. Plate 8mm | C15: 72 | D15: 72 | J15: FLEXIBLE HOSE-15NB*1000MM (OIL ) | K15: 750 | M15: 750 | P15: SOLENOID VALVE UNIT | T15: 8000 | U15: 4744 | X15: =3389*1.4
A16: 14 | B16: M.S. Round | C16: 72 | D16: 72 | J16: FLEXIBLE HOSE-20NB*1000MM (OIL ) | K16: 800 | M16: 800 | P16: ELECTRODE ASSEMBLY | T16: 2200 | U16: 560
A17: 15 | B17: M.S. Sheet 2mm | C17: 77 | D17: 77 | J17: FLEXIBLE HOSE-25NB*1000MM (AIR ) | K17: 1100 | M17: 1100 | P17: NOISE FILTER | T17: 400 | U17: 250
A18: 16 | B18: M.S. Sheet 3mm | C18: 77 | D18: 77 | J18: ADOPTER 15NB*20NB (OIL) | K18: 30 | M18: 30 | P18: INPUT SOCKET | T18: 1070 | U18: 280
A19: 17 | B19: M.S. Sheet 4mm | C19: 72 | D19: 72 | J19: ADOPTER 15NB*15NB (AIR) | K19: 30 | M19: 30
A20: 18 | B20: M.S. Sheet 5mm | C20: 72 | D20: 72
A21: 19 | B21: M.S. Sheet 8mm | C21: 72 | D21: 72 | J21: Butterfly Valve 2.5" | K21: 1500 | M21: 1500
A22: 20 | B22: M.S. Tube "B" Class 1.5 in | C22: 135 | D22: 135 | J22: Butterfly Valve 4" | K22: 1650 | M22: 1650
A23: 21 | B23: M.S. Tube "C" Class 1.5 in | C23: 135 | D23: 135 | J23: Butterfly Valve 6" | K23: 4500 | M23: 4500
A24: 22 | B24: M.S.Chanel | C24: 71 | D24: 71 | J24: ENCON-Y-STRAINER 20NB | K24: 450 | M24: 360
A25: 23 | B25: Plumber block with Bearing | C25: 13000 | D25: 11000 | J25: Whyteheat K | K25: 70 | M25: 50
A26: 24 | B26: Pulley with V belt | C26: 5000 | D26: 3000 | J26: Ball valve 25 NB | K26: 2500 | M26: 2500
A27: 25 | B27: S.S. Sheet 3mm | C27: 270 | D27: 270 | J27: ='Gas Burner'!B9 | K27: 1500 | M27: 1500
A28: 26 | B28: SS Pipe | J28: Ball valve 20 NB | K28: 1718 | M28: 1718
A29: 27 | B29: Ceramic Fiber | C29: 2000 | D29: 1450 | G29: Pipe Kg/Mtr | J29: Ball valve 32 NB | K29: 2929 | M29: 2929
A30: 28 | B30: SS Pipe 304 60 X 3mm | C30: 330 | D30: 330 | E30: =C30*G30 | G30: =PI()*60*60*7850*1/(4*1000*1000)-PI()*54*54*7850*1/(4*1000*1000) | J30: Ball valve 40 NB | K30: 5000 | M30: 5000
A31: 29 | B31: SS Pipe 304 76 X 3mm | C31: 330 | D31: 330 | E31: =C31*G31 | G31: =PI()*76*76*7850*1/(4*1000*1000)- PI()*70*70*7850*1/(4*1000*1000)
A32: 30 | B32: SS Pipe 304 100 X 3mm | C32: 330 | D32: 330 | E32: =C32*G32 | G32: =PI()*100*100*7850*1/(4*1000*1000)- PI()*94*94*7850*1/(4*1000*1000) | J32: DEMBLA CONTROL VALVES | N32: Make: DEMBLA
A33: 31 | B33: M.S. Elbow 60 OD | C33: 200 | D33: 200 | J33: Control Valve 050NB | K33: 172892 | N33: DEMBLA
A34: 32 | B34: M.S. Elbow 76 OD | C34: 300 | D34: 300 | J34: Control Valve 065NB | K34: 176475 | N34: DEMBLA
A35: 33 | B35: M.S. Elbow 100 OD | C35: 400 | D35: 400 | J35: Control Valve 080NB | K35: 183291 | N35: DEMBLA
A36: 34 | B36: SS Elbow 60 OD | C36: 600 | D36: 500 | J36: Control Valve 100NB | K36: 187598 | N36: DEMBLA
A37: 35 | B37: SS Elbow 76 OD | C37: 700 | D37: 600 | J37: Control Valve 125NB | K37: 201687 | N37: DEMBLA
A38: 36 | B38: SS Elbow 100 OD | C38: 1000 | D38: 900 | J38: Control Valve 150NB | K38: 205736 | N38: DEMBLA
J39: Control Valve 200NB | K39: 242404 | N39: DEMBLA
J40: Control Valve 250NB | K40: 305228 | N40: DEMBLA
J41: Control Valve 300NB | K41: 344828 | N41: DEMBLA
J42: Control Valve 350NB | K42: 455577 | N42: DEMBLA
J43: Control Valve 400NB | K43: 495831 | N43: DEMBLA
J44: Control Valve 450NB | K44: 594311 | N44: DEMBLA
J45: Control Valve 500NB | K45: 810100 | N45: DEMBLA
J46: Control Valve 600NB | K46: 1293131 | N46: DEMBLA
J47: Control Valve 650NB | K47: 1821680 | N47: DEMBLA
J48: Control Valve 700NB | K48: 2096854 | N48: DEMBLA
J50: DEMBLA SHUT OFF VALVES | N50: Make: DEMBLA
J51: Shut Off Valve 050NB | K51: 71626 | N51: DEMBLA
J52: Shut Off Valve 065NB | K52: 63722 | N52: DEMBLA
J53: Shut Off Valve 080NB | K53: 70539 | N53: DEMBLA
J54: Shut Off Valve 100NB | K54: 74846 | N54: DEMBLA
J55: Shut Off Valve 125NB | K55: 88935 | N55: DEMBLA
J56: Shut Off Valve 150NB | K56: 92984 | N56: DEMBLA
J57: Shut Off Valve 200NB | K57: 129651 | N57: DEMBLA
J58: Shut Off Valve 250NB | K58: 192475 | N58: DEMBLA
J59: Shut Off Valve 300NB | K59: 232075 | N59: DEMBLA
J60: Shut Off Valve 350NB | K60: 342825 | N60: DEMBLA
J61: Shut Off Valve 400NB | K61: 383078 | N61: DEMBLA
J62: Shut Off Valve 450NB | K62: 481559 | N62: DEMBLA
... J66: Shut Off Valve 700NB | K66: 1984102 | N66: DEMBLA
J68: CAIR MOTORIZED CONTROL VALVES | N68: Make: CAIR
J69: Motorized Control Valve 025NB (Globe) | K69: 28688 | N69: CAIR
J70: Motorized Control Valve 040NB | K70: 43529 | N70: CAIR
J71: Motorized Control Valve 050NB | K71: 43778 | N71: CAIR
J72: Motorized Control Valve 065NB | K72: 44173 | N72: CAIR
J73: Motorized Control Valve 080NB | K73: 44360 | N73: CAIR
J74: Motorized Control Valve 100NB | K74: 45330 | N74: CAIR
J75: Motorized Control Valve 125NB | K75: 46430 | N75: CAIR
J76: Motorized Control Valve 150NB | K76: 57770 | N76: CAIR
J77: Motorized Control Valve 200NB | K77: 67402 | N77: CAIR
J78: Motorized Control Valve 250NB | K78: 76433 | N78: CAIR
J79: Motorized Control Valve 300NB | K79: 80479 | N79: CAIR
J80: Motorized Control Valve 350NB | K80: 85167 | N80: CAIR
J82: CAIR SHUT OFF VALVES | N82: Make: CAIR
J83: Shut Off Valve 025NB (Ball) | K83: 22210 | N83: CAIR
J84: Shut Off Valve 032NB (Ball) | K84: 23000 | N84: CAIR
J85: Shut Off Valve 040NB (Ball) | K85: 23200 | N85: CAIR
J86: Shut Off Valve 040NB (Butterfly) | K86: 20746 | N86: CAIR
J87: Shut Off Valve 050NB (Butterfly) | K87: 20995 | N87: CAIR
J88: Shut Off Valve 065NB (Butterfly) | K88: 21390 | N88: CAIR
J89: Shut Off Valve 080NB (Butterfly) | K89: 21577 | N89: CAIR
J90: Shut Off Valve 100NB (Butterfly) | K90: 22547 | N90: CAIR
J91: Shut Off Valve 125NB (Butterfly) | K91: 23647 | N91: CAIR
J92: Shut Off Valve 150NB (Butterfly) | K92: 34986 | N92: CAIR
J93: Shut Off Valve 200NB (Butterfly) | K93: 44619 | N93: CAIR
J94: Shut Off Valve 250NB (Butterfly) | K94: 55260 | N94: CAIR
... J99: PRESSURE SWITCH LOW | K99: 3000 | N99: MADAS
J101: ORIFICE PLATE (incl. Flanges + Fasteners) | N101: ES
J102: Orifice Plate 025NB | K102: 2350 | N102: ES
J103: Orifice Plate 040NB | K103: 2950 | N103: ES
J104: Orifice Plate 050NB | K104: 3650 | N104: ES
J105: Orifice Plate 065NB | K105: 4100 | N105: ES
J106: Orifice Plate 080NB | K106: 4700 | N106: ES
J107: Orifice Plate 100NB | K107: 5500 | N107: ES
J108: Orifice Plate 150NB | K108: 7700 | N108: ES
J109: Orifice Plate 200NB | K109: 13200 | N109: ES
J110: Orifice Plate 250NB | K110: 16200 | N110: ES
J111: Orifice Plate 300NB | K111: 18200 | N111: ES
J112: Orifice Plate 350NB | K112: 24200 | N112: ES
...

Sheet  Oil Burner
A1: BURNER PARTS-2A/3A | J1: BURNER PARTS-4A | S1: BURNER PARTS-5A/6A | AB1: BURNER PARTS-7A
A2: S.NO. | B2: PARTICULARS | C2: QTY | D2: UNIT | E2: RATE | F2: AMOUNT | G2: M/C COST | H2: TOTAL AMOUNT | J2: S.NO. | K2: PARTICULARS | L2: QTY | M2: UNIT | N2: RATE | O2: AMOUNT | P2: M/C COST | Q2: TOTAL AMOUNT | S2: S.NO. | T2: PARTICULARS | U2: QTY | V2: UNIT | W2: RATE | X2: AMOUNT | Y2: M/C COST | Z2: TOTAL AMOUNT | AB2: S.NO. | AC2: PARTICULARS | AD2: QTY | AE2: UNIT | AF2: RATE | AG2: AMOUNT | AH2: M/C COST | AI2: TOTAL AMOUNT
A4: 1 | B4: ENCON-2A/3A BASE PLATE | C4: 10.5 | D4: Kgs | E4: =Rates!$K$5 | F4: =C4*E4 | G4: 500 | H4: =F4+G4 | J4: 1 | K4: ENCON-4A BASE PLATE | L4: 13.5 | M4: Kgs | N4: =Rates!$K$5 | O4: =L4*N4 | P4: 500 | Q4: =O4+P4 | S4: 1 | T4: ENCON-5A/6A BASE PLATE | U4: 24 | V4: Kgs | W4: =Rates!$K$5 | X4: =U4*W4 | Y4: 550 | Z4: =X4+Y4 | AB4: 1 | AC4: ENCON-7A AIR TUBE-205(dia)*180(I.D)*375(Lenth) | AD4: 22.24 | AE4: Kgs | AF4: 80 | AG4: =AD4*AF4 | AI4: =AG4+AH4
A5: 2 | B5: ENCON-2A/3AAIR TUBE | C5: 3.9 | D5: Kgs | E5: =Rates!$K$5 | F5: =C5*E5 | G5: 500 | H5: =F5+G5 | J5: 2 | K5: ENCON-4A AIR TUBE | L5: 6.8 | M5: Kgs | N5: =Rates!$K$5 | O5: =L5*N5 | P5: 500 | Q5: =O5+P5 | S5: 2 | T5: ENCON-5A/6AAIR TUBE | U5: 16.8 | V5: Kgs | W5: =Rates!$K$5 | X5: =U5*W5 | Y5: 500 | Z5: =X5+Y5 | AB5: 2 | AC5: M.S.FLANGE-300 (dia)* 195 (I.D)*12MM Thick | AD5: 7.68 | AE5: Kgs | AF5: 72 | AG5: =AD5*AF5 | AH5: 1500 | AI5: =AG5+AH5
A6: 3 | B6: ENCON-2A/3AS.G.HOLDER | C6: 2.6 | D6: Kgs | E6: =Rates!$K$5 | F6: =C6*E6 | G6: 200 | H6: =F6+G6 | J6: 3 | K6: ENCON-4AS.G.HOLDER | L6: 4.3 | M6: Kgs | N6: =Rates!$K$5 | O6: =L6*N6 | P6: 200 | Q6: =O6+P6 | S6: 3 | T6: ENCON-5A/6AS.G.HOLDER | U6: 8.4 | V6: Kgs | W6: =Rates!$K$5 | X6: =U6*W6 | Y6: 300 | Z6: =X6+Y6 | AB6: 3 | AC6: M.S. PIPE-100NB*125MM | AD6: 1 | AE6: NO | AF6: =Rates!C22 | AG6: =AD6*AF6 | AI6: =AG6+AH6
A7: 4 | B7: ENCON-2A/3A AIR ADJUSTER | C7: 3 | D7: Kgs | E7: =Rates!$K$5 | F7: =C7*E7 | G7: 100 | H7: =F7+G7 | J7: 4 | K7: ENCON-4A AIR ADJUSTER | L7: 3.8 | M7: Kgs | N7: =Rates!$K$5 | O7: =L7*N7 | P7: 100 | Q7: =O7+P7 | S7: 4 | T7: ENCON-5A/6A AIR ADJUSTER | U7: 4.7 | V7: Kgs | W7: =Rates!$K$5 | X7: =U7*W7 | Y7: 100 | Z7: =X7+Y7 | AB7: 4 | AC7: ENCON-7A AIR MIXER-86(dia)*72(I.D)*385(Lenth) | AD7: 5.24 | AE7: Kgs | AF7: 80 | AG7: =AD7*AF7 | AI7: =AG7+AH7
A8: 5 | B8: ENCON-2A/3A S.S.ASSY. | C8: 1 | D8: SET | E8: =Rates!K6 | F8: =C8*E8 | H8: =F8+G8 | J8: 5 | K8: ENCON-4A S.S.ASSY. | L8: 1 | M8: SET | N8: =Rates!K7 | O8: =L8*N8 | Q8: =O8+P8 | S8: 5 | T8: ENCON-5A/6A S.S.ASSY. | U8: 1 | V8: SET | W8: =Rates!K8 | X8: =U8*W8 | Z8: =X8+Y8 | AB8: 5 | AC8: M.S.TIKKY-300(dia)*80(I.D)*40MM Thick | AD8: 20.6 | AE8: Kgs | AF8: 72 | AG8: =AD8*AF8 | AI8: =AG8+AH8
A9: 6 | B9: ENCON-2A/3A BUTTERFLY VALVE-2.5 (INCH ) | C9: 1 | D9: NO | E9: =Rates!K21 | F9: =C9*E9 | H9: =F9+G9 | J9: 6 | K9: ENCON-4A BUTTERFLY VALVE-4 (INCH ) | L9: 1 | M9: NO | N9: =Rates!K22 | O9: =L9*N9 | Q9: =O9+P9 | S9: 6 | T9: ENCON-5A/6A BUTTERFLY VALVE-4 (INCH ) | U9: 1 | V9: NO | W9: =Rates!K22 | X9: =U9*W9 | Z9: =X9+Y9 | AB9: 6 | AC9: ENCON-7A AIR TUBE-88(dia)*72(I.D)*135MM(Lenth) | AD9: 2.12 | AE9: Kgs | AF9: 80 | AG9: =AD9*AF9 | AI9: =AG9+AH9
A10: 7 | B10: ENCON-2A/3A Y-STRAINER 20NB | C10: 1 | D10: NO | E10: =Rates!K24 | F10: =C10*E10 | H10: =F10+G10 | J10: 7 | K10: ENCON-4A Y-STRAINER 20NB | L10: 1 | M10: NO | N10: =Rates!K24 | O10: =L10*N10 | Q10: =O10+P10 | S10: 7 | T10: ENCON-5A/6AY-STRAINER 20NB | U10: 1 | V10: NO | W10: =N10 | X10: =U10*W10 | Z10: =X10+Y10 | AB10: 7 | AC10: M.S.TIKKY- 175(dia)*80(I.D)*16MM Thick | AD10: 2.38 | AE10: Kgs | AF10: 72 | AG10: =AD10*AF10 | AI10: =AG10+AH10
A11: 8 | B11: FLEXIBLE HOSE-15NB*750MM (OIL ) | C11: 1 | D11: NO | E11: =Rates!K14 | F11: =C11*E11 | H11: =F11+G11 | J11: 8 | K11: FLEXIBLE HOSE-15NB*750MM (OIL ) | L11: 1 | M11: NO | N11: =E11 | O11: =L11*N11 | Q11: =O11+P11 | S11: 8 | T11: FLEXIBLE HOSE-15NB*1000MM(OIL ) | U11: 1 | V11: NO | W11: =Rates!K15 | X11: =U11*W11 | Z11: =X11+Y11 | AB11: 8 | AC11: M.S. TIKKY-90(dia)*40(I.D)*40MM Thick | AD11: 1.6 | AE11: Kgs | AF11: 72 | AG11: =AD11*AF11 | AI11: =AG11+AH11
A12: 9 | B12: FLEXIBLE HOSE-15NB*750MM (AIR ) | C12: 1 | D12: NO | E12: =E11 | F12: =C12*E12 | H12: =F12+G12 | J12: 9 | K12: FLEXIBLE HOSE-15NB*750MM (AIR ) | L12: 1 | M12: NO | N12: =N11 | O12: =L12*N12 | Q12: =O12+P12 | S12: 9 | T12: FLEXIBLE HOSE-20NB*1000MM (AIR ) | U12: 1 | V12: NO | W12: =Rates!K16 | X12: =U12*W12 | Z12: =X12+Y12 | AB12: 9 | AC12: ENCON-7A SPACER-80(dia)*40(I.D)*35MM(Lenth) | AD12: 1 | AE12: Kgs | AF12: 72 | AG12: =AD12*AF12 | AI12: =AG12+AH12
A13: 10 | B13: GUN METAL MICRO VALVE -2A/3A | C13: 1 | D13: NO | E13: =Rates!K10 | F13: 2500 | H13: =F13+G13 | J13: 10 | K13: GUN METAL MICRO VALVE -4A | L13: 1 | M13: NO | N13: =Rates!K11 | O13: =L13*N13 | Q13: =O13+P13 | S13: 10 | T13: GUN METAL MICRO VALVE -5A/6A | U13: 1 | V13: NO | W13: =Rates!K12 | X13: =U13*W13 | Z13: =X13+Y13 | AB13: 10 | AC13: ENCON-7A S.S ASSY. | AD13: 1 | AE13: Set | AF13: =Rates!K9 | AG13: =AD13*AF13 | AI13: =AG13+AH13
A14: 11 | B14: ADOPTER 15NB*20NB (OIL) | C14: 1 | D14: NO | E14: 30 | F14: =C14*E14 | H14: =F14+G14 | J14: 11 | K14: ADOPTER 15NB*20NB (OIL) | L14: 1 | M14: NO | N14: 30 | O14: =L14*N14 | Q14: =O14+P14 | S14: 11 | T14: ADOPTER 15NB*20NB (OIL) | U14: 1 | V14: NO | W14: 30 | X14: =U14*W14 | Z14: =X14+Y14 | AB14: 11 | AC14: ENCON-7A MICRO VALVE | AD14: 1 | AE14: NO | AF14: =Rates!K13 | AG14: =AD14*AF14 | AI14: =AG14+AH14
A15: 12 | B15: ADOPTER 15NB*15NB (AIR) | C15: 2 | D15: Nos | E15: 30 | F15: =C15*E15 | H15: =F15+G15 | J15: 12 | K15: ADOPTER 20NB*20NB (AIR) | L15: 2 | M15: Nos | N15: 30 | O15: =L15*N15 | Q15: =O15+P15 | S15: 12 | T15: ADOPTER 20NB*20NB (AIR) | U15: 2 | V15: Nos | W15: 30 | X15: =U15*W15 | Z15: =X15+Y15 | AB15: 12 | AC15: FLEXIBLE HOSE-20NB*1000MM (OIL ) | AD15: 1 | AE15: set | AF15: =Rates!K16 | AG15: =AD15*AF15 | AI15: =AG15+AH15
A16: 13 | B16: ENCON-2A/3ABURNER PLATE | C16: 30.1 | D16: Kgs | E16: =Rates!$K$5 | F16: =C16*E16 | H16: =F16+G16 | J16: 13 | K16: ENCON-4ABURNER PLATE | L16: 41.4 | M16: Kgs | N16: =Rates!$K$5 | O16: =L16*N16 | Q16: =O16+P16 | S16: 13 | T16: ENCON-5A/6ABURNER PLATE | U16: 50 | V16: Kgs | W16: =Rates!$K$5 | X16: =U16*W16 | Z16: =X16+Y16 | AB16: 13 | AC16: FLEXIBLE HOSE-25NB*1000MM (AIR ) | AD16: 1 | AE16: No | AF16: =Rates!K17 | AG16: =AD16*AF16 | AI16: =AG16+AH16
A17: 14 | B17: ENCON-2A/3A BURNER BLOCK | C17: 50 | D17: Kgs | E17: =Rates!K25 | F17: =C17*E17 | G17: 100 | H17: =F17+G17 | J17: 14 | K17: ENCON-4A BURNER BLOCK | L17: 65 | M17: Kgs | N17: =E17 | O17: =L17*N17 | P17: 100 | Q17: =O17+P17 | S17: 14 | T17: ENCON-5A/6A BURNER BLOCK | U17: 110 | V17: Kgs | W17: =N17 | X17: =U17*W17 | Y17: 250 | Z17: =X17+Y17 | AB17: 14 | AC17: Butterfly valve | AD17: 1 | AE17: No | AF17: =Rates!K23 | AG17: =AD17*AF17 | AI17: =AG17+AH17
A18: 15 | B18: PAINT PRIMER,BOLT | H18: 250 | K18: labour charge | Q18: 500 | T18: labour charge | Z18: 500 | AB18: 15 | AC18: Y-STRAINER 25NB | AD18: 1 | AE18: No | AF18: =Rates!K24 | AG18: =AD18*AF18 | AI18: =AG18+AH18
B19: labour charge | H19: 400 | K19: PAINT PRIMER,BOLT | O19: 300 | Q19: 300 | S19: 15 | T19: PAINT PRIMER,BOLT | X19: 350 | Z19: 400 | AB19: 16 | AC19: ENCON-7A BURNER BLOCK | AD19: 150 | AE19: Kgs | AF19: =W17 | AG19: =AD19*AF19 | AH19: 300 | AI19: =AG19+AH19
G20: TOTAL | H20: =SUM(H4:H19) | N20: TOTAL | Q20: =SUM(Q4:Q19) | W20: TOTAL | Z20: =SUM(Z4:Z19) | AB20: 17 | AC20: Burner plate | AD20: 50 | AE20: Kgs | AF20: =Rates!K5 | AG20: =AD20*AF20 | AI20: =AG20+AH20
J21: 1 | K21: H.V. BURNER-4A | L21: 1 | M21: NO | Q21: 17311 | S21: 1 | T21: H.V. BURNER -5A/6A | U21: 1 | V21: NO | Z21: 25968 | AB21: 18 | AC21: M.S.PIPE-50NB*100MM | AD21: 1 | AE21: NO | AF21: 80 | AG21: =AD21*AF21 | AI21: =AG21+AH21
A22: 1 | B22: H.V. BURNER-2A/3A | C22: 1 | D22: NO | H22: 14800 | AB22: 19 | AC22: Labour charge | AI22: 5000
AC23: PAINT PRIMER,BOLT | AG23: 500 | AI23: =AG23+AH23
AF24: TOTAL | AI24: =SUM(AI4:AI23)
B37: Burner Size | C37: S.G. Assembly | D37: S.G. Holder | E37: Inner Tube | F37: Outer Tube | G37: Lock Nut | H37: Check Nut | I37: Swirler | J37: Base Plate | K37: Air Tube | L37: Air Adjuster
B38: ENCON-2A | C38: 2282 | D38: 382 | E38: 850 | F38: 600 | G38: 200 | H38: 125 | I38: 125 | J38: 1235 | K38: 573 | L38: 310
B39: ENCON-3A | C39: 2282 | D39: 382 | E39: 850 | F39: 600 | G39: 200 | H39: 125 | I39: 125 | J39: 1235 | K39: 573 | L39: 310
B40: ENCON-4A | C40: 2551 | D40: 501 | E40: 950 | F40: 650 | G40: 200 | H40: 125 | I40: 125 | J40: 1445 | K40: 776 | L40: 366
B41: ENCON-5A | C41: 4788 | D41: 888 | E41: 2100 | F41: 1200 | G41: 250 | H41: 150 | I41: 200 | J41: 2230 | K41: 1576 | L41: 429
B42: ENCON-6A | C42: 4388 | D42: 888 | E42: 2100 | F42: 1200 | G42: 250 | H42: 150 | I42: 200 | J42: 2230 | K42: 1576 | L42: 429
B43: ENCON-7A | C43: 17000 | E43: 10800 | F43: 5800 | H43: 250 | I43: 150 | J43: 3500

Sheet HV  Oil Burner
A1: HV BURNER PARTS-2A/3A | J1: HV BURNER PARTS-4A | S1: HV BURNER PARTS-5A/6A | AB1: HV BURNER PARTS-7A
A2: S.NO. | B2: PARTICULARS | C2: QTY | D2: UNIT | E2: RATE | F2: AMOUNT | G2: M/C COST | H2: TOTAL AMOUNT | J2: S.NO. | K2: PARTICULARS | L2: QTY | M2: UNIT | N2: RATE | O2: AMOUNT | P2: M/C COST | Q2: TOTAL AMOUNT | S2: S.NO. | T2: PARTICULARS | U2: QTY | V2: UNIT | W2: RATE | X2: AMOUNT | Y2: M/C COST | Z2: TOTAL AMOUNT | AB2: S.NO. | AC2: PARTICULARS | AD2: QTY | AE2: UNIT | AF2: RATE | AG2: AMOUNT | AH2: M/C COST | AI2: TOTAL AMOUNT
A3: 1 | B3: H.V. BURNER-2A/3A | H3: =SUM(' Oil Burner'!H5:H6,' Oil Burner'!H8) | J3: 1 | K3: H.V. BURNER-4A | Q3: =SUM(' Oil Burner'!Q5:Q6,' Oil Burner'!Q8) | S3: 1 | T3: H.V. BURNER-5A/6A | Z3: =SUM(' Oil Burner'!Z5,' Oil Burner'!Z6,' Oil Burner'!Z8) | AB3: 1 | AC3: ENCON-7A AIR TUBE-205(dia)*180(I.D)*375(Lenth) | AD3: 22.24 | AE3: Kgs | AF3: =' Oil Burner'!AF4 | AG3: =AD3*AF3 | AI3: =AG3+AH3
A4: 2 | B4: H.V. BURNER block -2A/3A | H4: 9102 | J4: 2 | K4: H.V. BURNER block -4A | Q4: 11454 | S4: 2 | T4: H.V. BURNER block -5A/6A | Z4: 16654 | AB4: 2 | AC4: M.S.FLANGE-300 (dia)* 195 (I.D)*12MM Thick | AD4: 7.68 | AE4: Kgs | AF4: =' Oil Burner'!AF5 | AG4: =AD4*AF4 | AH4: 1500 | AI4: =AG4+AH4
A5: 3 | B5: ENCON-2A/3A BUTTERFLY VALVE-2.5 (INCH ) | C5: 1 | D5: NO | E5: =Rates!K21 | F5: =C5*E5 | H5: =F5+G5 | J5: 3 | K5: ENCON-4A BUTTERFLY VALVE-4 (INCH ) | L5: 1 | M5: NO | N5: =Rates!K22 | O5: =L5*N5 | Q5: =O5+P5 | S5: 3 | T5: ENCON-5A/6A BUTTERFLY VALVE-4 (INCH ) | U5: 1 | V5: NO | W5: =Rates!K22 | X5: =U5*W5 | Z5: =X5+Y5 | AB5: 3 | AC5: M.S. PIPE-100NB*125MM | AD5: 1 | AE5: NO | AF5: =' Oil Burner'!AF6 | AG5: =AD5*AF5 | AI5: =AG5+AH5
A6: 4 | B6: ENCON-2A/3A Y-STRAINER 20NB | C6: 1 | D6: NO | E6: =Rates!K24 | F6: =C6*E6 | H6: =F6+G6 | J6: 4 | K6: ENCON-4A Y-STRAINER 20NB | L6: 1 | M6: NO | N6: =E6 | O6: =L6*N6 | Q6: =O6+P6 | S6: 4 | T6: ENCON-5A/6AY-STRAINER 20NB | U6: 1 | V6: NO | W6: =Rates!K24 | X6: =U6*W6 | Z6: =X6+Y6 | AB6: 4 | AC6: ENCON-7A AIR MIXER-86(dia)*72(I.D)*385(Lenth) | AD6: 5.24 | AE6: Kgs | AF6: =' Oil Burner'!AF7 | AG6: =AD6*AF6 | AI6: =AG6+AH6
A7: 5 | B7: FLEXIBLE HOSE-15NB*750MM (OIL ) | C7: 2 | D7: NO | E7: =Rates!K14 | F7: =C7*E7 | H7: =F7+G7 | J7: 5 | K7: FLEXIBLE HOSE-15NB*750MM (OIL ) | L7: 2 | M7: NO | N7: =E7 | O7: =L7*N7 | Q7: =O7+P7 | S7: 5 | T7: FLEXIBLE HOSE-15NB*1000MM(OIL ) | U7: 1 | V7: NO | W7: =Rates!K15 | X7: =U7*W7 | Z7: =X7+Y7 | AB7: 5 | AC7: M.S.TIKKY-300(dia)*80(I.D)*40MM Thick | AD7: 20.6 | AE7: Kgs | AF7: =' Oil Burner'!AF8 | AG7: =AD7*AF7 | AI7: =AG7+AH7
A8: 6 | B8: FLEXIBLE HOSE-15NB*750MM (AIR ) | C8: 2 | D8: NO | E8: =E7 | F8: =C8*E8 | H8: =F8+G8 | J8: 6 | K8: FLEXIBLE HOSE-15NB*750MM (AIR ) | L8: 2 | M8: NO | N8: =E8 | O8: =L8*N8 | Q8: =O8+P8 | S8: 6 | T8: FLEXIBLE HOSE-20NB*1000MM (AIR ) | U8: 1 | V8: NO | W8: =Rates!K16 | X8: =U8*W8 | Z8: =X8+Y8 | AB8: 6 | AC8: ENCON-7A AIR TUBE-88(dia)*72(I.D)*135MM(Lenth) | AD8: 2.12 | AE8: Kgs | AF8: =' Oil Burner'!AF9 | AG8: =AD8*AF8 | AI8: =AG8+AH8
A9: 7 | B9: GUN METAL MICRO VALVE -2A/3A | C9: 1 | D9: NO | E9: =Rates!K10 | F9: =C9*E9 | H9: =F9+G9 | J9: 7 | K9: GUN METAL MICRO VALVE -4A | L9: 1 | M9: NO | N9: =Rates!K11 | O9: =L9*N9 | Q9: =O9+P9 | S9: 7 | T9: FLEXIBLE HOSE-15NB*750MM with adopter | U9: 2 | V9: set | W9: =Rates!K14 | X9: =U9*W9 | Z9: =X9+Y9 | AB9: 7 | AC9: M.S.TIKKY- 175(dia)*80(I.D)*16MM Thick | AD9: 2.38 | AE9: Kgs | AF9: =' Oil Burner'!AF10 | AG9: =AD9*AF9 | AI9: =AG9+AH9
A10: 8 | B10: ADOPTER 15NB*20NB (OIL) | C10: 3 | D10: NO | E10: 30 | F10: =C10*E10 | H10: =F10+G10 | J10: 8 | K10: ADOPTER 15NB*20NB (OIL) | L10: 3 | M10: NO | N10: 30 | O10: =L10*N10 | Q10: =O10+P10 | S10: 8 | T10: GUN METAL MICRO VALVE -5A/6A | U10: 1 | V10: NO | W10: =Rates!K12 | X10: =U10*W10 | Z10: =X10+Y10 | AB10: 8 | AC10: M.S. TIKKY-90(dia)*40(I.D)*40MM Thick | AD10: 1.6 | AE10: Kgs | AF10: =' Oil Burner'!AF11 | AG10: =AD10*AF10 | AI10: =AG10+AH10
A11: 9 | B11: ADOPTER 15NB*15NB (AIR) | C11: 4 | D11: Nos | E11: 30 | F11: =C11*E11 | H11: =F11+G11 | J11: 9 | K11: ADOPTER 20NB*20NB (AIR) | L11: 4 | M11: Nos | N11: 30 | O11: =L11*N11 | Q11: =O11+P11 | S11: 9 | T11: ADOPTER 15NB*20NB (OIL) | U11: 1 | V11: NO | W11: 30 | X11: =U11*W11 | Z11: =X11+Y11 | AB11: 9 | AC11: ENCON-7A SPACER-80(dia)*40(I.D)*35MM(Lenth) | AD11: 1 | AE11: Kgs | AF11: =' Oil Burner'!AF12 | AG11: =AD11*AF11 | AI11: =AG11+AH11
A12: 10 | B12: Labour charge | H12: 2100 | J12: 10 | K12: labour charge | Q12: 2400 | S12: 10 | T12: ADOPTER 20NB*20NB (AIR) | U12: 2 | V12: Nos | W12: 30 | X12: =U12*W12 | Z12: =X12+Y12 | AB12: 10 | AC12: ENCON-7A S.S ASSY. | AD12: 1 | AE12: Set | AF12: =' Oil Burner'!AF13 | AG12: =AD12*AF12 | AI12: =AG12+AH12
A13: 11 | B13: PAINT PRIMER,BOLT | H13: 400 | J13: 11 | K13: PAINT PRIMER,BOLT | O13: 300 | Q13: 400 | S13: 11 | T13: labour charge | Z13: 2900 | AB13: 11 | AC13: ENCON-7A MICRO VALVE | AD13: 1 | AE13: NO | AF13: =' Oil Burner'!AF14 | AG13: =AD13*AF13 | AI13: =AG13+AH13
G14: Total | H14: =SUM(H3:H13) | N14: TOTAL | Q14: =SUM(Q3:Q13) | S14: 12 | T14: PAINT PRIMER,BOLT | X14: 350 | Z14: 400 | AB14: 12 | AC14: FLEXIBLE HOSE-20NB*1000MM (OIL ) | AD14: 3 | AE14: set | AF14: =' Oil Burner'!AF15 | AG14: =AD14*AF14 | AI14: =AG14+AH14
W15: TOTAL | Z15: =SUM(Z3:Z14) | AB15: 13 | AC15: FLEXIBLE HOSE-25NB*1000MM (AIR ) | AD15: 1 | AE15: No | AF15: =' Oil Burner'!AF16 | AG15: =AD15*AF15 | AI15: =AG15+AH15
AB16: 14 | AC16: Butterfly valve | AD16: 1 | AE16: No | AF16: =' Oil Burner'!AF17 | AG16: =AD16*AF16 | AI16: =AG16+AH16
AB17: 15 | AC17: Y-STRAINER 25NB | AD17: 1 | AE17: No | AF17: =' Oil Burner'!AF18 | AG17: =AD17*AF17 | AI17: =AG17+AH17
AB18: 16 | AC18: ENCON-7A BURNER BLOCK | AD18: 1 | AE18: No | AF18: =' Oil Burner'!AF19 | AI18: 31048
AB19: 17 | AC19: M.S.PIPE-50NB*100MM | AD19: 1 | AE19: NO | AF19: =' Oil Burner'!AF21 | AG19: =AD19*AF19 | AI19: =AG19+AH19
AB20: 18 | AC20: Labour charge | AI20: 5000
AB21: 19 | AC21: PAINT PRIMER,BOLT | AG21: 400 | AI21: 500
AF22: TOTAL | AI22: =SUM(AI3:AI21)

Sheet Recuperator
A1: Recuperator F | M1: Recuperator HT
A2: Model | B2: MS Tube "C" Class (mtr) | C2: CI Gills (Nos) | D2: M.S. Angle 65,50 (Kg) | E2: M.S. Angle 100,100 (Kg) | F2: M.S Plate 16mm* 5mm | G2: Hardware Bolt (KG) | H2: M.S.Chanel (Kg) | I2: Toal Cost | M2: Model | N2: M.S. Plate 16mm*10mm | O2: M.S. Plate 5mm | P2: M.S. Angle 50*6 | Q2: S.S Sheet | R2: Total Cost
A3: 10 F | B3: 38 | D3: 269 | E3: 103 | F3: 200 | G3: 18 | H3: 98 | I3: =K12 | M3: 1 HT | N3: 29 | O3: 129 | P3: 9 | Q3: 62 | R3: =T12
A4: 20 F | B4: 64 | D4: 270 | E4: 56 | F4: 450 | G4: 20 | I4: =K13 | M4: 2 HT | N4: 32 | O4: 150 | P4: 9 | Q4: 86 | R4: =T13
A5: 30 F | B5: 128 | D5: 427 | E5: 279 | F5: 795 | G5: 30 | I5: =K14 | M5: 5 HT | N5: 53 | O5: 311 | P5: 13.5 | Q5: 223 | R5: =T14
A6: 40 F | B6: 146 | D6: 392 | E6: 305 | F6: 795 | G6: 40 | I6: =K15 | M6: 10 HT | N6: 93 | O6: 571 | P6: 22 | Q6: 435 | R6: =T15
A7: 50 F | B7: 182 | D7: 431 | E7: 312 | F7: 960 | G7: 40 | I7: =K16
A8: 100 F | B8: 354 | D8: 456 | E8: 381 | F8: 170 | G8: 35 | I8: =K17
A11: Model | B11: MS Tube "C" Class (mtr) | C11: CI Gills (Nos) | D11: M.S. Angle 65,50 (Kg) | E11: M.S. Angle 100,100 (Kg) | F11: M.S Plate 16mm* 5mm | G11: Hardware Bolt (KG) | H11: M.S.Chanel (Kg) | I11: Toal Cost | J11: 0.3 | K11: 0.8 | M11: Model | N11: M.S. Plate 16mm*10mm | O11: M.S. Plate 5mm | P11: M.S. Angle 50*6 | Q11: S.S Sheet | R11: cost | S11: 0.3 | T11: 0.8
A12: 10 F | B12: =(B3/0.3*Rates!$C$23) | C12: 0 | D12: =D3*Rates!$C$9 | E12: =E3*Rates!$C$7 | F12: =F3*Rates!$C$12 | G12: =G3*Rates!$C$6 | H12: =H3*Rates!C10 | I12: =SUM(B12:G12) | J12: =I12*1.3 | K12: =J12*1.8 | M12: 1 HT | N12: =N3*Rates!$C$13 | O12: =O3*Rates!$C$14 | P12: =P3*Rates!$C$8 | Q12: =Q3*Rates!$C$27 | R12: =SUM(N12:Q12) | S12: =R12*1.3 | T12: =S12*1.8
A13: 20 F | B13: =(B4/0.3*Rates!$C$23) | C13: 0 | D13: =D4*Rates!$C$9 | E13: =E4*Rates!$C$7 | F13: =F4*Rates!$C$12 | G13: =G4*Rates!$C$6 | I13: =SUM(B13:G13) | J13: =I13*1.3 | K13: =J13*1.8 | M13: 2 HT | N13: =N4*Rates!$C$13 | O13: =O4*Rates!$C$14 | P13: =P4*Rates!$C$8 | Q13: =Q4*Rates!$C$27 | R13: =SUM(N13:Q13) | S13: =R13*1.3 | T13: =S13*1.8
A14: 30 F | B14: =(B5/0.3*Rates!$C$23) | C14: 0 | D14: =D5*Rates!$C$9 | E14: =E5*Rates!$C$7 | F14: =F5*Rates!$C$12 | G14: =G5*Rates!$C$6 | I14: =SUM(B14:G14) | J14: =I14*1.3 | K14: =J14*1.8 | M14: 5 HT | N14: =N5*Rates!$C$13 | O14: =O5*Rates!$C$14 | P14: =P5*Rates!$C$8 | Q14: =Q5*Rates!$C$27 | R14: =SUM(N14:Q14) | S14: =R14*1.3 | T14: =S14*1.8
A15: 40 F | B15: =(B6/0.3*Rates!$C$23) | C15: 0 | D15: =D6*Rates!$C$9 | E15: =E6*Rates!$C$7 | F15: =F6*Rates!$C$12 | G15: =G6*Rates!$C$6 | I15: =SUM(B15:G15) | J15: =I15*1.3 | K15: =J15*1.8 | M15: 10 HT | N15: =N6*Rates!$C$13 | O15: =O6*Rates!$C$14 | P15: =P6*Rates!$C$8 | Q15: =Q6*Rates!$C$27 | R15: =SUM(N15:Q15) | S15: =R15*1.3 | T15: =S15*1.8
A16: 50 F | B16: =(B7/0.3*Rates!$C$23) | C16: 0 | D16: =D7*Rates!$C$9 | E16: =E7*Rates!$C$7 | F16: =F7*Rates!$C$12 | G16: =G7*Rates!$C$6 | I16: =SUM(B16:G16) | J16: =I16*1.3 | K16: =J16*1.8
A17: 100 F | B17: =(B8/0.3*Rates!$C$23) | C17: 0 | D17: =D8*Rates!$C$9 | E17: =E8*Rates!$C$7 | F17: =F8*Rates!$C$12 | G17: =G8*Rates!$C$6 | I17: =SUM(B17:G17) | J17: =I17*1.3 | K17: =J17*1.8
A19: Recuperator FS
A20: Model | B20: MS Tube "C" Class (mtr) | C20: MS Tube "B" Class (mtr) | D20: CI Gills (Nos) | E20: M.S. Angle 65,50 (Kg) | F20: M.S. Angle 100,100 (Kg) | G20: M.S Plate 16mm* 5mm | H20: Hardware Bolt (kg) | I20: M.S.Chanel (kg) | J20: Total Cost
A21: 10 FS | B21: 25 | C21: 25 | E21: 269 | F21: 103 | G21: 245 | H21: 18 | I21: 98 | J21: =L31
A22: 20 FS | B22: 52 | C22: 52 | E22: 344 | F22: 227 | G22: 575 | H22: 23 | J22: =L32
A23: 30 FS | B23: 91 | C23: 91 | E23: 390 | F23: 280 | G23: 798 | H23: 30 | J23: =L33
A24: 40 FS | B24: 124 | C24: 124 | E24: 395 | F24: 305 | G24: 825 | H24: 35 | J24: =L34
A25: 50 FS | B25: 158 | C25: 158 | E25: 510 | F25: 312 | G25: 950 | H25: 37 | J25: =L35
A26: 70 FS | B26: 261 | C26: 261 | E26: 516 | F26: 352 | G26: 1015 | H26: 30 | J26: =L36
A27: 100 FS | B27: 315 | C27: 315 | E27: 456 | F27: 381 | G27: 1190 | H27: 35 | J27: =L37
A30: Model | B30: MS Tube "C" Class (mtr) | C30: MS Tube "B" Class (mtr) | D30: CI Gills (Nos) | E30: M.S. Angle 65,50 (Kg) | F30: M.S. Angle 100,100 (Kg) | G30: M.S Plate 16mm* 5mm | H30: Hardware Bolt (kg) | I30: M.S.Chanel (kg) | K30: 0.3 | L30: 0.8
A31: 10 FS | B31: =B21*Rates!$C$23*4.27 | C31: =C21*Rates!$C$22*4.27 | E31: =E21*Rates!$C$9 | F31: =F21*Rates!$C$7 | G31: =G21*Rates!$C$12 | H31: =H21*Rates!$C$6 | I31: =I21*Rates!$C$10 | J31: =SUM(B31:I31) | K31: =J31*1.3 | L31: =K31*1.8
A32: 20 FS | B32: =B22*Rates!$C$23*4.27 | C32: =C22*Rates!$C$22*4.27 | E32: =E22*Rates!$C$9 | F32: =F22*Rates!$C$7 | G32: =G22*Rates!$C$12 | H32: =H22*Rates!$C$6 | I32: =I22*Rates!$C$10 | J32: =SUM(B32:I32) | K32: =J32*1.3 | L32: =K32*1.8
A33: 30 FS | B33: =B23*Rates!$C$23*4.27 | C33: =C23*Rates!$C$22*4.27 | E33: =E23*Rates!$C$9 | F33: =F23*Rates!$C$7 | G33: =G23*Rates!$C$12 | H33: =H23*Rates!$C$6 | I33: =I23*Rates!$C$10 | J33: =SUM(B33:I33) | K33: =J33*1.3 | L33: =K33*1.8
A34: 40 FS | B34: =B24*Rates!$C$23*4.27 | C34: =C24*Rates!$C$22*4.27 | E34: =E24*Rates!$C$9 | F34: =F24*Rates!$C$7 | G34: =G24*Rates!$C$12 | H34: =H24*Rates!$C$6 | I34: =I24*Rates!$C$10 | J34: =SUM(B34:I34) | K34: =J34*1.3 | L34: =K34*1.8
A35: 50 FS | B35: =B25*Rates!$C$23*4.27 | C35: =C25*Rates!$C$22*4.27 | E35: =E25*Rates!$C$9 | F35: =F25*Rates!$C$7 | G35: =G25*Rates!$C$12 | H35: =H25*Rates!$C$6 | I35: =I25*Rates!$C$10 | J35: =SUM(B35:I35) | K35: =J35*1.3 | L35: =K35*1.8
A36: 70 FS | B36: =B26*Rates!$C$23*4.27 | C36: =C26*Rates!$C$22*4.27 | E36: =E26*Rates!$C$9 | F36: =F26*Rates!$C$7 | G36: =G26*Rates!$C$12 | H36: =H26*Rates!$C$6 | I36: =I26*Rates!$C$10 | J36: =SUM(B36:I36) | K36: =J36*1.3 | L36: =K36*1.8
A37: 100 FS | B37: =B27*Rates!$C$23*4.27 | C37: =C27*Rates!$C$22*4.27 | E37: =E27*Rates!$C$9 | F37: =F27*Rates!$C$7 | G37: =G27*Rates!$C$12 | H37: =H27*Rates!$C$6 | I37: =I27*Rates!$C$10 | J37: =SUM(B37:I37) | K37: =J37*1.3 | L37: =K37*1.8

Sheet Gas Burner
A1: BURNER PARTS 50 NM³ (GAIL design Hole Type) | J1: BURNER PARTS 100 NM³ (GAIL design Hole Type) | S1: BURNER PARTS 150 NM³ (GAIL design Hole Type)
A2: S.NO. | B2: PARTICULARS | C2: QTY | D2: UNIT | E2: RATE | F2: AMOUNT | G2: M/C COST | H2: TOTAL AMOUNT | J2: S.NO. | K2: PARTICULARS | L2: QTY | M2: UNIT | N2: RATE | O2: AMOUNT | P2: M/C COST | Q2: TOTAL AMOUNT | S2: 5 | T2: PARTICULARS | U2: QTY | V2: UNIT | W2: RATE | X2: AMOUNT | Y2: M/C COST | Z2: TOTAL AMOUNT
A4: 1 | B4: S.S PIPE | C4: 19 | D4: Kgs | E4: =Rates!C30 | F4: =C4*E4 | H4: =F4+G4 | J4: 1 | K4: S.S PIPE | L4: 34 | M4: Kgs | N4: =E4 | O4: =L4*N4 | Q4: =O4+P4 | S4: 1 | T4: S.S PIPE | U4: 34 | V4: Kgs | W4: =N4 | X4: =U4*W4 | Z4: =X4+Y4
A5: 2 | B5: M.S PLATE | C5: 27 | D5: Kgs | E5: =Rates!C12 | F5: =C5*E5 | H5: =F5+G5 | J5: 2 | K5: M.S PLATE | L5: 42 | M5: Kgs | N5: =E5 | O5: =L5*N5 | Q5: =O5+P5 | S5: 2 | T5: M.S PLATE | U5: 42 | V5: Kgs | W5: =N5 | X5: =U5*W5 | Z5: =X5+Y5
A6: 3 | B6: DRILL | F6: 1800 | H6: =F6+G6 | J6: 3 | K6: DRILL | Q6: 2000 | S6: 3 | T6: DRILL | Z6: 2000
A7: 4 | B7: BUTTERFLY VALVE-6 (INCH ) | C7: 1 | D7: NO | E7: =Rates!K23 | F7: =C7*E7 | H7: =F7+G7 | J7: 4 | K7: BUTTERFLY VALVE-6 (INCH ) | L7: 1 | M7: NO | N7: =E7 | O7: =L7*N7 | Q7: =O7+P7 | S7: 4 | T7: BUTTERFLY VALVE-6 (INCH ) | U7: 1 | V7: NO | W7: =N7 | X7: =U7*W7 | Z7: =X7+Y7
A8: 5 | B8: Ball valve | C8: 1 | D8: NO | E8: =Rates!K26 | F8: =C8*E8 | H8: =F8+G8 | J8: 5 | K8: Ball valve | L8: 1 | M8: NO | N8: =E8 | O8: =L8*N8 | Q8: =O8+P8 | S8: 5 | T8: Ball valve | U8: 1 | V8: NO | W8: =N8 | X8: =U8*W8 | Z8: =X8+Y8
A9: 6 | B9: FLEXIBLE HOSE-40NB*750MM WITH ADOPTER | C9: 1 | D9: NO | E9: =Rates!K27 | F9: =C9*E9 | H9: =F9+G9 | J9: 6 | K9: FLEXIBLE HOSE-40NB*750MM WITH ADOPTER | L9: 1 | M9: NO | N9: =E9 | O9: =L9*N9 | Q9: =O9+P9 | S9: 6 | T9: FLEXIBLE HOSE-40NB*750MM WITH ADOPTER | U9: 1 | V9: NO | W9: =N9 | X9: =U9*W9 | Z9: =X9+Y9
A10: 7 | B10: BURNER PLATE | C10: 40 | D10: Kgs | E10: =Rates!K5 | F10: =C10*E10 | H10: =F10+G10 | J10: 7 | K10: BURNER PLATE | L10: 50 | M10: Kgs | N10: =E10 | O10: =L10*N10 | Q10: =O10+P10 | S10: 7 | T10: BURNER PLATE | U10: 50 | V10: Kgs | W10: =N10 | X10: =U10*W10 | Z10: =X10+Y10
A11: 8 | B11: BURNER BLOCK | C11: 70 | D11: Kgs | E11: =Rates!K25 | F11: =C11*E11 | H11: =F11+G11 | J11: 8 | K11: BURNER BLOCK | L11: 110 | M11: Kgs | N11: =E11 | O11: =L11*N11 | Q11: 4760 | S11: 8 | T11: BURNER BLOCK | U11: 110 | V11: Kgs | W11: =N11 | X11: =U11*W11 | Z11: 4760
A12: 9 | B12: labour charge | F12: 5000 | H12: =F12+G12 | J12: 9 | K12: labour charge | Q12: 5500 | S12: 9 | T12: labour charge | Z12: 5000
A13: 10 | B13: PAINT PRIMER,BOLT | H13: 350 | J13: 10 | K13: PAINT PRIMER,BOLT | Q13: 500 | S13: 10 | T13: PAINT PRIMER,BOLT | Z13: 400
E14: TOTAL | H14: =SUM(H4:H13) | N14: TOTAL | Q14: =SUM(Q4:Q13) | W14: TOTAL | Z14: =SUM(Z4:Z13)
A17: BURNER PARTS 100 NM³ PowerTrade | J17: BURNER PARTS 100 NM³ Ada
A18: S.NO. | B18: PARTICULARS | C18: QTY | D18: UNIT | E18: RATE | F18: AMOUNT | G18: M/C COST | H18: TOTAL AMOUNT | J18: S.NO. | K18: PARTICULARS | L18: QTY | M18: UNIT | N18: RATE | O18: AMOUNT | P18: M/C COST | Q18: TOTAL AMOUNT
A20: 1 | B20: AIR TUBE | C20: 51 | D20: Kgs | E20: 70 | F20: =C20*E20 | G20: 2760 | H20: =F20+G20 | J20: 1 | K20: AIR TUBE | L20: 30 | M20: Kgs | N20: =Rates!K5 | O20: =L20*N20 | P20: 2760 | Q20: =O20+P20
A21: 2 | B21: BAISE | C21: 24 | D21: Kgs | E21: 70 | F21: =C21*E21 | G21: 1500 | H21: =F21+G21 | J21: 2 | K21: BAISE | L21: 22 | M21: Kgs | N21: =N20 | O21: =L21*N21 | P21: 1500 | Q21: =O21+P21
A22: 3 | B22: RING | C22: 8 | D22: Kgs | E22: 70 | F22: =C22*E22 | G22: 750 | H22: =F22+G22 | J22: 3 | K22: RING | L22: 8 | M22: Kgs | N22: =N21 | O22: =L22*N22 | P22: 750 | Q22: =O22+P22
A23: 4 | B23: SS PIPE | C23: 3 | D23: Kgs | E23: 240 | F23: =C23*E23 | H23: =F23+G23 | J23: 4 | K23: SS PIPE | L23: 3 | M23: Kgs | N23: =N4 | O23: =L23*N23 | Q23: =O23+P23
A24: 5 | B24: MS PLATE | C24: 10 | D24: Kgs | E24: 70 | F24: =C24*E24 | G24: 400 | H24: =F24+G24 | J24: 5 | K24: MS PLATE | L24: 10 | M24: Kgs | N24: =N5 | O24: =L24*N24 | P24: 400 | Q24: =O24+P24
A25: 6 | B25: BUTTERFLY VALVE-6 (INCH ) | C25: 1 | D25: NO | E25: 3000 | F25: =C25*E25 | H25: =F25+G25 | J25: 6 | K25: BUTTERFLY VALVE-6 (INCH ) | L25: 1 | M25: NO | N25: =N7 | O25: =L25*N25 | Q25: =O25+P25
A26: 7 | B26: Ball valve | C26: 1 | D26: NO | E26: 2050 | F26: =C26*E26 | H26: =F26+G26 | J26: 7 | K26: Ball valve | L26: 1 | M26: NO | N26: =W8 | O26: =L26*N26 | Q26: =O26+P26
A27: 8 | B27: FLEXIBLE HOSE-40NB*750MM WITH ADOPTER | C27: 1 | D27: NO | E27: 1750 | F27: =C27*E27 | H27: =F27+G27 | J27: 8 | K27: FLEXIBLE HOSE-40NB*750MM WITH ADOPTER | L27: 1 | M27: NO | N27: =W9 | O27: =L27*N27 | Q27: =O27+P27
A28: 9 | B28: BURNER PLATE | C28: 50 | D28: Kgs | E28: 70 | F28: =C28*E28 | H28: =F28+G28 | J28: 9 | K28: BURNER PLATE | L28: 50 | M28: Kgs | N28: =N10 | O28: =L28*N28 | Q28: =O28+P28
A29: 10 | B29: BURNER BLOCK | C29: 110 | D29: Kgs | E29: 41 | F29: =C29*E29 | H29: 4760 | J29: 10 | K29: BURNER BLOCK | L29: 110 | M29: Kgs | N29: =N11 | O29: =L29*N29 | Q29: 4760
A30: 11 | B30: labour charge | H30: 500 | J30: 11 | K30: labour charge | Q30: 500
A31: 12 | B31: PAINT PRIMER,BOLT | H31: 400 | J31: 12 | K31: PAINT PRIMER,BOLT | Q31: 400
E32: TOTAL | H32: =SUM(H20:H31) | N32: TOTAL | Q32: =SUM(Q20:Q31)
B35: Casting weight of ADA – 1 . base – 30 kg
B36: 2 . air tube – 35 kg
B37: 3. Ring – 10 kg
B38: Power trade - 1. Air tube – 60 kg
B39: 2. base - 35 kg
B40: 3. Ring – 10 kg

Sheet Blower
A1: ENCON FUEL COMBUSTORS BLOWERS (DIRECT MOUNTED) (W.E.F Jul'21)
A2: MEDIUM PRESSURE | H2: PERKIN Rates
A3: MODEL | B3: H.P. | C3: CFM | D3: NM3 /HR | E3: PRESSURE | F3: PRICE Without motor | G3: PRICE With motor | H3: Blower weight Approx | I3: Per Kg. Price | J3: Amount | K3: Motor Price ABB | L3: PRICE Without, motor | M3: PRICE With motor | O3: * Raised 12% from Last
A4: ENCON 28/3 | B4: 3 | C4: 300 | D4: 510 | E4: 28” W.G. | F4: 50400 | G4: 69000 | H4: 130 | J4: 28000 | K4: 12500 | L4: =J4*1.8 | M4: =K4*1.5+L4 | O4: 12320 | P4: =J4/H4 | Q4: 45000 | R4: =Q4/(H4*1.8) | S4: =P4/R4-1 | U4: 57000 | V4: =G4/U4-1 | X4: =M4-L4 | Y4: =X4/O4
A5: ENCON 28/5 | B5: 5 | C5: 550 | D5: 930 | E5: 28” W.G. | F5: 51500 | G5: 76000 | H5: 160 | J5: 28622 | K5: 16200 | L5: =J5*1.8 | M5: =K5*1.5+L5 | O5: 16170 | P5: =J5/H5 | Q5: 46000 | R5: =Q5/(H5*1.8) | S5: =P5/R5-1 | U5: 66000 | V5: =G5/U5-1 | X5: =M5-L5 | Y5: =X5/O5
A6: ENCON 28/7.5 | B6: 7.5 | C6: 850 | D6: 1450 | E6: 28” W.G. | F6: 56500 | G6: 95200 | H6: 180 | J6: 31360 | K6: 25800 | L6: =J6*1.8 | M6: =K6*1.5+L6 | O6: 25795 | P6: =J6/H6 | Q6: 50400 | R6: =Q6/(H6*1.8) | S6: =P6/R6-1 | U6: 87000 | V6: =G6/U6-1 | X6: =M6-L6 | Y6: =X6/O6
A7: ENCON 28/10 | B7: 10 | C7: 1200 | D7: 2040 | E7: 28” W.G. | F7: 60500 | G7: 101000 | H7: 190 | J7: 33600 | K7: 27000 | L7: =J7*1.8 | M7: =K7*1.5+L7 | O7: 26950 | P7: =J7/H7 | Q7: 54000 | R7: =Q7/(H7*1.8) | S7: =P7/R7-1 | U7: 92000 | V7: =G7/U7-1 | X7: =M7-L7 | Y7: =X7/O7
A8: ENCON 28/15 | B8: 15 | C8: 1700 | D8: 2890 | E8: 28” W.G. | F8: 76000 | G8: 148000 | H8: 200 | J8: 39200 | K8: 51500 | L8: =J8*1.8 | M8: =K8*1.5+L8 | O8: 51310 | P8: =J8/H8 | Q8: 63000 | R8: =Q8/(H8*1.8) | S8: =P8/R8-1 | U8: 136000 | V8: =G8/U8-1 | X8: =M8-L8 | Y8: =X8/O8
A9: ENCON 28/20 | B9: 20 | C9: 2200 | D9: 3740 | E9: 28” W.G. | F9: 87000 | G9: 168000 | H9: 210 | J9: 44800 | K9: 58000 | L9: =J9*1.8 | M9: =K9*1.5+L9 | O9: 57995 | P9: =J9/H9 | Q9: 72000 | R9: =Q9/(H9*1.8) | S9: =P9/R9-1 | U9: 155000 | V9: =G9/U9-1 | X9: =M9-L9 | Y9: =X9/O9
A10: ENCON 28/25 | B10: 25 | C10: 3000 | D10: 5100 | E10: 28” W.G. | F10: 91000 | G10: 195000 | H10: 220 | J10: 50400 | K10: 69500 | L10: =J10*1.8 | M10: =K10*1.5+L10 | O10: 69230 | P10: =J10/H10 | Q10: 81000 | R10: =Q10/(H10*1.8) | S10: =P10/R10-1 | U10: 180000 | V10: =G10/U10-1 | X10: =M10-L10 | Y10: =X10/O10
A11: ENCON 28/30 | B11: 30 | C11: 3500 | D11: 5950 | E11: 28” W.G. | F11: 111000 | G11: 230000 | H11: 275 | J11: 61600 | K11: 79000 | L11: =J11*1.8 | M11: =K11*1.5+L11 | O11: 78925 | P11: =J11/H11 | Q11: 99000 | R11: =Q11/(H11*1.8) | S11: =P11/R11-1 | U11: 210000 | V11: =G11/U11-1 | X11: =M11-L11 | Y11: =X11/O11
A12: ENCON 28/40 | B12: 40 | C12: 4800 | D12: 7900 | E12: 28” W.G. | F12: 131000 | G12: 296000 | H12: 330 | J12: 72800 | K12: 110000 | L12: =J12*1.8 | M12: =K12*1.5+L12 | O12: 109620 | P12: =J12/H12 | Q12: 117000 | R12: =Q12/(H12*1.8) | S12: =P12/R12-1 | U12: 274000 | V12: =G12/U12-1 | X12: =M12-L12 | Y12: =X12/O12
A13: ENCON 28/50 | B13: 50 | C13: 5950 | D13: 9850 | E13: 28” W.G. | F13: 151500 | G13: 339000 | H13: 370 | J13: 84000 | K13: 125000 | L13: =J13*1.8 | M13: =K13*1.5+L13 | O13: 124215 | P13: =J13/H13 | Q13: 135000 | R13: =Q13/(H13*1.8) | S13: =P13/R13-1 | U13: 318000 | V13: =G13/U13-1 | X13: =M13-L13 | Y13: =X13/O13
A14: ENCON 28/60 | B14: 60 | C14: 7100 | D14: 11750 | E14: 28” W.G. | F14: 175000 | G14: 417000 | H14: 475 | J14: 96320 | K14: 162000 | L14: =J14*1.8 | M14: =K14*1.5+L14 | O14: 161630 | P14: =J14/H14 | Q14: 154800 | R14: =Q14/(H14*1.8) | S14: =P14/R14-1 | U14: 395000 | V14: =G14/U14-1 | X14: =M14-L14 | Y14: =X14/O14
A15: HIGH PRESSURE | H15: PERKIN Rates
A16: MODEL | B16: H.P. | C16: CFM | D16: NM3 /HR | E16: PRESSURE | F16: PRICE Without motor | G16: PRICE With motor | H16: Blower weight Approx | I16: Per Kg. Price | J16: Amount | K16: Motor Price ABB | L16: PRICE Without, motor | M16: PRICE With motor | O16: * Raised 12% from Last
A17: ENCON 40/5 | B17: 5 | C17: 400 | D17: 680 | E17: 40” W.G. | F17: 56500 | G17: 81000 | H17: 160 | J17: 31360 | K17: 16200 | L17: =J17*1.8 | M17: =K17*1.5+L17 | P17: =J17/H17 | Q17: 50400 | R17: =Q17/(H17*1.8) | S17: =P17/R17-1 | U17: 74000 | V17: =G17/U17-1
A18: ENCON 40/7.5 | B18: 7.5 | C18: 600 | D18: 1020 | E18: 40” W.G. | F18: 60500 | G18: 99500 | H18: 180 | J18: 33600 | K18: 25800 | L18: =J18*1.8 | M18: =K18*1.5+L18 | P18: =J18/H18 | Q18: 54000 | R18: =Q18/(H18*1.8) | S18: =P18/R18-1 | U18: 91000 | V18: =G18/U18-1
A19: ENCON 40/10 | B19: 10 | C19: 800 | D19: 1360 | E19: 40” W.G. | F19: 76000 | G19: 111000 | H19: 190 | J19: 39200 | K19: 27000 | L19: =J19*1.8 | M19: =K19*1.5+L19 | P19: =J19/H19 | Q19: 63000 | R19: =Q19/(H19*1.8) | S19: =P19/R19-1 | U19: 101000 | V19: =G19/U19-1
A20: ENCON 40/15 | B20: 15 | C20: 1200 | D20: 2040 | E20: 40” W.G. | F20: 87000 | G20: 158000 | H20: 200 | J20: 44800 | K20: 51500 | L20: =J20*1.8 | M20: =K20*1.5+L20 | P20: =J20/H20 | Q20: 72000 | R20: =Q20/(H20*1.8) | S20: =P20/R20-1 | U20: 145000 | V20: =G20/U20-1
A21: ENCON 40/20 | B21: 20 | C21: 1600 | D21: 2730 | E21: 40” W.G. | F21: 91000 | G21: 178000 | H21: 210 | J21: 50400 | K21: 58000 | L21: =J21*1.8 | M21: =K21*1.5+L21 | P21: =J21/H21 | Q21: 81000 | R21: =Q21/(H21*1.8) | S21: =P21/R21-1 | U21: 164000 | V21: =G21/U21-1
A22: ENCON 40/25 | B22: 25 | C22: 2000 | D22: 3400 | E22: 40” W.G. | F22: 111000 | G22: 215000 | H22: 220 | J22: 61600 | K22: 69500 | L22: =J22*1.8 | M22: =K22*1.5+L22 | P22: =J22/H22 | Q22: 99000 | R22: =Q22/(H22*1.8) | S22: =P22/R22-1 | U22: 198000 | V22: =G22/U22-1
A23: ENCON 40/30 | B23: 30 | C23: 2400 | D23: 4000 | E23: 40” W.G. | F23: 131000 | G23: 250000 | H23: 275 | J23: 72800 | K23: 79000 | L23: =J23*1.8 | M23: =K23*1.5+L23 | P23: =J23/H23 | Q23: 117000 | R23: =Q23/(H23*1.8) | S23: =P23/R23-1 | U23: 228000 | V23: =G23/U23-1
A24: ENCON 40/40 | B24: 40 | C24: 3200 | D24: 5200 | E24: 40” W.G. | F24: 151500 | G24: 316500 | H24: 330 | J24: 84000 | K24: 110000 | L24: =J24*1.8 | M24: =K24*1.5+L24 | P24: =J24/H24 | Q24: 135000 | R24: =Q24/(H24*1.8) | S24: =P24/R24-1 | U24: 292000 | V24: =G24/U24-1
A25: ENCON 40/50 | B25: 50 | C25: 4000 | D25: 6500 | E25: 40” W.G. | F25: 175000 | G25: 361000 | H25: 370 | J25: 96320 | K25: 125000 | L25: =J25*1.8 | M25: =K25*1.5+L25 | P25: =J25/H25 | Q25: 155000 | R25: =Q25/(H25*1.8) | S25: =P25/R25-1 | U25: 334000 | V25: =G25/U25-1
A26: ENCON 40/60 | B26: 60 | C26: 4800 | D26: 7800 | E26: 40” W.G. | F26: 198000 | G26: 441000 | H26: 475 | J26: 109760 | K26: 162000 | L26: =J26*1.8 | M26: =K26*1.5+L26 | P26: =J26/H26 | Q26: 177000 | R26: =Q26/(H26*1.8) | S26: =P26/R26-1 | U26: 417000 | V26: =G26/U26-1
A27: Note:
A28: (1) The ex works price indicated for fuel combustors are inclusive of the electric motor of reputed make, such as, NGEF, ABB, Crompton etc. on which the impeller would be directly mounted.
A29: (2) Quoted prices for 40 HP and above Blowers are for V Belt/coupled mounting.
A37: Blower DM 40 | L37: Blower DM 28
A38: Model | B38: M.S Angle 65,50 KG | C38: M.S Sheet 8mm Kg | D38: M.S Sheet 4mm KG | E38: M.S Sheet 2mm KG | F38: MS Flat KG | G38: CI Hub Nos | H38: Hardware KG | I38: Total Cost | L38: Model | M38: M.S Angle 65,50 Kg | N38: M.S Sheet 5mm Kg | O38: M.S Sheet 4mm Kg | P38: M.S Sheet 2mm Kg | Q38: MS Flat Kg | R38: CI Hub Nos | S38: Hardware Kg | T38: Total Cost
A39: 5/40 | B39: 14 | C39: 34 | D39: 50 | E39: 15 | F39: 6 | G39: 1 | H39: 3 | I39: =K49 | L39: 5/28 | M39: 12 | N39: 32 | O39: 51 | P39: 11 | Q39: 3 | R39: 1 | S39: 3 | T39: =V49
A40: 7.5/40 | B40: 14 | C40: 39 | D40: 61 | E40: 15 | F40: 8 | G40: 1 | H40: 3 | I40: =K50 | L40: 7.5/28 | M40: 13 | N40: 34 | O40: 48 | P40: 13 | Q40: 3 | R40: 1 | S40: 3 | T40: =V50
A41: 10/40 | B41: 14 | C41: 40 | D41: 62 | E41: 15 | F41: 8 | G41: 1 | H41: 3 | I41: =K51 | L41: 10/28 | M41: 13 | N41: 39 | O41: 50 | P41: 15 | Q41: 3 | R41: 1 | S41: 3 | T41: =V51
A42: 15/40 | B42: 25 | C42: 43 | D42: 62 | E42: 19 | F42: 8 | G42: 1 | H42: 3 | I42: =K52 | L42: 15/28 | M42: 24 | N42: 47 | O42: 61 | P42: 15 | Q42: 4 | R42: 1 | S42: 3 | T42: =V52
A43: 20/40 | B43: 30 | C43: 46 | D43: 63 | E43: 20 | F43: 9 | G43: 1 | H43: 3 | I43: =K53 | L43: 20/28 | M43: 25 | N43: 49 | O43: 62 | P43: 15 | Q43: 4 | R43: 1 | S43: 3 | T43: =V53
A44: 25/40 | B44: 30 | C44: 46 | D44: 63 | E44: 20 | F44: 9 | G44: 1 | H44: 3 | I44: =K54 | L44: 25/28 | M44: 25 | N44: 50 | O44: 65 | P44: 17 | Q44: 4 | R44: 1 | S44: 3 | T44: =V54
A45: 30/40 | B45: 30 | C45: 48 | D45: 65 | E45: 21 | F45: 8 | G45: 1 | H45: 3 | I45: =K55 | L45: 30/28 | M45: 25 | N45: 50 | O45: 66 | P45: 17 | Q45: 4 | R45: 1 | S45: 3 | T45: =V55
A48: Model | B48: M.S Angle 65,50 KG | C48: M.S Sheet 5mm* 8mm Kg | D48: M.S Sheet 4mm* 3mm KG | E48: M.S Sheet 2mm KG | F48: MS Flat KG | G48: CI Hub Nos | H48: Hardware KG | J48: 0.3 | K48: 0.8 | L48: Model | M48: M.S Angle 65,50 Kg | N48: M.S Sheet 5mm* 8mm Kg | O48: M.S Sheet 4mm* 3mm Kg | P48: M.S Sheet 2.5mm* 2mm Kg | Q48: MS Flat Kg | R48: CI Hub Nos | S48: Hardware Kg | U48: 0.3 | V48: 0.8
A49: 5/40 | B49: =B39*Rates!$C$9 | C49: =C39*Rates!$C$21 | D49: =D39*Rates!$C$19 | E49: =E39*Rates!$C$17 | F49: =F39*Rates!$C$11 | G49: =G39*Rates!$C$4 | H49: =H39*Rates!$C$6 | I49: =SUM(B49:H49) | J49: =I49*1.3 | K49: =J49*1.8 | L49: 5/28 | M49: =M39*Rates!$C$9 | N49: =N39*Rates!$C$14 | O49: =O39*Rates!$C$19 | P49: =P39*Rates!$C$17 | Q49: =Q39*Rates!$C$11 | R49: =R39*Rates!$C$4 | S49: =S39*Rates!$C$6 | T49: =SUM(M49:S49) | U49: =T49*1.3 | V49: =U49*1.8
A50: 7.5/40 | B50: =B40*Rates!$C$9 | C50: =C40*Rates!$C$21 | D50: =D40*Rates!$C$19 | E50: =E40*Rates!$C$17 | F50: =F40*Rates!$C$11 | G50: =G40*Rates!$C$4 | H50: =H40*Rates!$C$6 | I50: =SUM(B50:H50) | J50: =I50*1.3 | K50: =J50*1.8 | L50: 7.5/28 | M50: =M40*Rates!$C$9 | N50: =N40*Rates!$C$14 | O50: =O40*Rates!$C$19 | P50: =P40*Rates!$C$17 | Q50: =Q40*Rates!$C$11 | R50: =R40*Rates!$C$4 | S50: =S40*Rates!C7 | T50: =SUM(M50:S50) | U50: =T50*1.3 | V50: =U50*1.8
A51: 10/40 | B51: =B41*Rates!$C$9 | C51: =C41*Rates!$C$21 | D51: =D41*Rates!$C$19 | E51: =E41*Rates!$C$17 | F51: =F41*Rates!$C$11 | G51: =G41*Rates!$C$4 | H51: =H41*Rates!$C$6 | I51: =SUM(B51:H51) | J51: =I51*1.3 | K51: =J51*1.8 | L51: 10/28 | M51: =M41*Rates!$C$9 | N51: =N41*Rates!$C$14 | O51: =O41*Rates!$C$19 | P51: =P41*Rates!$C$17 | Q51: =Q41*Rates!$C$11 | R51: =R41*Rates!$C$4 | S51: =S41*Rates!C8 | T51: =SUM(M51:S51) | U51: =T51*1.3 | V51: =U51*1.8
A52: 15/40 | B52: =B42*Rates!$C$9 | C52: =C42*Rates!$C$21 | D52: =D42*Rates!$C$19 | E52: =E42*Rates!$C$17 | F52: =F42*Rates!$C$11 | G52: =G42*Rates!$C$4 | H52: =H42*Rates!$C$6 | I52: =SUM(B52:H52) | J52: =I52*1.3 | K52: =J52*1.8 | L52: 15/28 | M52: =M42*Rates!$C$9 | N52: =N42*Rates!$C$14 | O52: =O42*Rates!$C$19 | P52: =P42*Rates!$C$17 | Q52: =Q42*Rates!$C$11 | R52: =R42*Rates!$C$4 | S52: =S42*Rates!C9 | T52: =SUM(M52:S52) | U52: =T52*1.3 | V52: =U52*1.8
A53: 20/40 | B53: =B43*Rates!$C$9 | C53: =C43*Rates!$C$21 | D53: =D43*Rates!$C$19 | E53: =E43*Rates!$C$17 | F53: =F43*Rates!$C$11 | G53: =G43*Rates!$C$4 | H53: =H43*Rates!$C$6 | I53: =SUM(B53:H53) | J53: =I53*1.3 | K53: =J53*1.8 | L53: 20/28 | M53: =M43*Rates!$C$9 | N53: =N43*Rates!$C$14 | O53: =O43*Rates!$C$19 | P53: =P43*Rates!$C$17 | Q53: =Q43*Rates!$C$11 | R53: =R43*Rates!$C$4 | S53: =S43*Rates!C10 | T53: =SUM(M53:S53) | U53: =T53*1.3 | V53: =U53*1.8
A54: 25/40 | B54: =B44*Rates!$C$9 | C54: =C44*Rates!$C$21 | D54: =D44*Rates!$C$19 | E54: =E44*Rates!$C$17 | F54: =F44*Rates!$C$11 | G54: =G44*Rates!$C$4 | H54: =H44*Rates!$C$6 | I54: =SUM(B54:H54) | J54: =I54*1.3 | K54: =J54*1.8 | L54: 25/28 | M54: =M44*Rates!$C$9 | N54: =N44*Rates!$C$14 | O54: =O44*Rates!$C$19 | P54: =P44*Rates!$C$17 | Q54: =Q44*Rates!$C$11 | R54: =R44*Rates!$C$4 | S54: =S44*Rates!C11 | T54: =SUM(M54:S54) | U54: =T54*1.3 | V54: =U54*1.8
A55: 30/40 | B55: =B45*Rates!$C$9 | C55: =C45*Rates!$C$21 | D55: =D45*Rates!$C$19 | E55: =E45*Rates!$C$17 | F55: =F45*Rates!$C$11 | G55: =G45*Rates!$C$4 | H55: =H45*Rates!$C$6 | I55: =SUM(B55:H55) | J55: =I55*1.3 | K55: =J55*1.8 | L55: 30/28 | M55: =M45*Rates!$C$9 | N55: =N45*Rates!$C$14 | O55: =O45*Rates!$C$19 | P55: =P45*Rates!$C$17 | Q55: =Q45*Rates!$C$11 | R55: =R45*Rates!$C$4 | S55: =S45*Rates!C12 | T55: =SUM(M55:S55) | U55: =T55*1.3 | V55: =U55*1.8
A57: Blower IDM
A58: Model | B58: M.S Angle 65,50 Kg | C58: M.S Sheet 8mm Kg | D58: M.S Sheet 4mm Kg | E58: M.S Sheet 2mm Kg | F58: MS Flat Kg | G58: CI Hub Kg | H58: Hardware Kg | I58: M.S Round Kg | J58: Plumber block with Bearing Nos | K58: Coupling Nos | L58: M.S Chanel Kg | M58: Total Cost
A59: 40/28 | B59: 42 | C59: 106 | D59: 70 | E59: 17 | F59: 4 | G59: 1 | H59: 3.5 | I59: 34 | J59: 2 | K59: 1 | L59: 15 | M59: =O67
A60: 50/28 | B60: 40 | C60: 238 | D60: 10 | E60: 10 | F60: 4 | G60: 1 | H60: 3.5 | I60: 36 | J60: 2 | K60: 1 | L60: 15 | M60: =O68
A61: 60/28 | B61: 30 | C61: 191 | D61: 10 | E61: 11 | F61: 10 | G61: 1 | H61: 3.5 | I61: 38 | J61: 2 | L61: 47 | M61: =O69
A62: 30/40 | B62: 27 | C62: 47 | D62: 63 | E62: 22 | F62: 9 | G62: 1 | H62: 3.5 | I62: 33 | J62: 2 | L62: 35 | M62: =O70
A63: 50/40 | B63: 30 | C63: 60 | D63: 97 | E63: 23 | F63: 9 | G63: 1 | H63: 3.5 | I63: 33 | J63: 2 | L63: 35 | M63: =O71
A66: Model | B66: M.S Angle 65,50 Kg | C66: M.S Sheet 8mm Kg | D66: M.S Sheet 4mm Kg | E66: M.S Sheet 2mm Kg | F66: MS Flat Kg | G66: CI Hub Kg | H66: Hardware Kg | I66: M.S Round Kg | J66: Plumber block with Bearing Nos | K66: Coupling Nos | L66: M.S Chanel Kg | M66: cost | N66: 0.3 | O66: 0.8
A67: 40/28 | B67: =B59*Rates!$C$9 | C67: =C59*Rates!$C$21 | D67: =D59*Rates!$C$19 | E67: =E59*Rates!$C$17 | F67: =F59*Rates!$C$11 | G67: =G59*Rates!$C$4 | H67: =H59*Rates!$C$6 | I67: =I59*Rates!$C$16 | J67: =J59*Rates!$C$25 | K67: =K59*Rates!$C$5 | L67: =L59*Rates!$C$24 | M67: =SUM(B67:L67) | N67: =M67*1.3 | O67: =N67*1.8
A68: 50/28 | B68: =B60*Rates!$C$9 | C68: =C60*Rates!$C$21 | D68: =D60*Rates!$C$19 | E68: =E60*Rates!$C$17 | F68: =F60*Rates!$C$11 | G68: =G60*Rates!$C$4 | H68: =H60*Rates!$C$6 | I68: =I60*Rates!$C$16 | J68: =J60*Rates!$C$25 | K68: =K60*Rates!$C$5 | L68: =L60*Rates!$C$24 | M68: =SUM(B68:L68) | N68: =M68*1.3 | O68: =N68*1.8
A69: 60/28 | B69: =B61*Rates!$C$9 | C69: =C61*Rates!$C$21 | D69: =D61*Rates!$C$19 | E69: =E61*Rates!$C$17 | F69: =F61*Rates!$C$11 | G69: =G61*Rates!$C$4 | H69: =H61*Rates!$C$6 | I69: =I61*Rates!$C$16 | J69: =J61*Rates!$C$25 | K69: =K61*Rates!$C$5 | L69: =L61*Rates!$C$24 | M69: =SUM(B69:L69) | N69: =M69*1.3 | O69: =N69*1.8
A70: 30/40 | B70: =B62*Rates!$C$9 | C70: =C62*Rates!$C$21 | D70: =D62*Rates!$C$19 | E70: =E62*Rates!$C$17 | F70: =F62*Rates!$C$11 | G70: =G62*Rates!$C$4 | H70: =H62*Rates!$C$6 | I70: =I62*Rates!$C$16 | J70: =J62*Rates!$C$25 | K70: =K62*Rates!$C$5 | L70: =L62*Rates!$C$24 | M70: =SUM(B70:L70) | N70: =M70*1.3 | O70: =N70*1.8
A71: 50/40 | B71: =B63*Rates!$C$9 | C71: =C63*Rates!$C$21 | D71: =D63*Rates!$C$19 | E71: =E63*Rates!$C$17 | F71: =F63*Rates!$C$11 | G71: =G63*Rates!$C$4 | H71: =H63*Rates!$C$6 | I71: =I63*Rates!$C$16 | J71: =J63*Rates!$C$25 | K71: =K63*Rates!$C$5 | L71: =L63*Rates!$C$24 | M71: =SUM(B71:L71) | N71: =M71*1.3 | O71: =N71*1.8

Sheet HPU
A1: Costing of Heating & Pumping Unit 3 KW Date : 01.07.2022 | Q1: Costing of Heating & Pumping Unit 6 KW Date : 01.07.2022 | AG1: Costing of Heating & Pumping Unit 9 KW Date : 01.07.2022 | AW1: Costing of Heating & Pumping Unit 12 KW Date : 01.07.2022 | BM1: Costing of Heating & Pumping Unit 16 KW Date : 01.07.2022 | CC1: Costing of Heating & Pumping Unit 20 KW Date : 01.07.2022 | CS1: Costing of Heating & Pumping Unit 24 KW Date : 01.07.2022 | DH1: Costing of Heating & Pumping Unit 30 KW Date : 01.07.2022 | DX1: Costing of Heating & Pumping Unit 36 KW Date : 01.07.2022 | EN1: Costing of Heating & Pumping Unit 48 KW Date : 01.07.2022
A2: Duplex 1 | G2: Duplex 2 | K2: Simplex | Q2: Duplex 1 | W2: Duplex 2 | AA2: Simplex | AG2: Duplex 1 | AM2: Duplex 2 | AQ2: Simplex | AW2: Duplex 1 | BC2: Duplex 2 | BG2: Simplex | BM2: Duplex 1 | BS2: Duplex 2 | BW2: Simplex | CC2: Duplex 1 | CI2: Duplex 2 | CM2: Simplex | CS2: Duplex 1 | CY2: Duplex 2 | DC2: Simplex | DH2: Duplex 1 | DN2: Duplex 2 | DR2: Simplex | DX2: Duplex 1 | ED2: Duplex 2 | EH2: Simplex | EN2: Duplex 1 | ET2: Duplex 2 | EX2: Simplex
A3: S No. | B3: Items | C3: Qty. | D3: Unit | E3: Rate | F3: Amount | Q3: S No. | R3: Items | S3: Qty. | T3: Unit | U3: Rate | V3: Amount | AG3: S No. | AH3: Items | AI3: Qty. | AJ3: Unit | AK3: Rate | AL3: Amount | AW3: S No. | AX3: Items | AY3: Qty. | AZ3: Unit | BA3: Rate | BB3: Amount | BM3: S No. | BN3: Items | BO3: Qty. | BP3: Unit | BQ3: Rate | BR3: Amount | CC3: S No. | CD3: Items | CE3: Qty. | CF3: Unit | CG3: Rate | CH3: Amount | CS3: S No. | CT3: Items | CU3: Qty. | CV3: Unit | CW3: Rate | CX3: Amount | DH3: S No. | DI3: Items | DJ3: Qty. | DK3: Unit | DL3: Rate | DM3: Amount | DX3: S No. | DY3: Items | DZ3: Qty. | EA3: Unit | EB3: Rate | EC3: Amount | EN3: S No. | EO3: Items | EP3: Qty. | EQ3: Unit | ER3: Rate | ES3: Amount
G4: Qty. | H4: Unit | I4: Rate | J4: Amount | K4: Qty. | L4: Unit | M4: Rate | N4: Amount | O4: Pre. Price | W4: Qty. | X4: Unit | Y4: Rate | Z4: Amount | AA4: Qty. | AB4: Unit | AC4: Rate | AD4: Amount | AE4: Pre. Price | AM4: Qty. | AN4: Unit | AO4: Rate | AP4: Amount | AQ4: Qty. | AR4: Unit | AS4: Rate | AT4: Amount | AU4: Pre. Price | BC4: Qty. | BD4: Unit | BE4: Rate | BF4: Amount | BG4: Qty. | BH4: Unit | BI4: Rate | BJ4: Amount | BK4: Pre. Price | BS4: Qty. | BT4: Unit | BU4: Rate | BV4: Amount | BW4: Qty. | BX4: Unit | BY4: Rate | BZ4: Amount | CA4: Pre. Price | CI4: Qty. | CJ4: Unit | CK4: Rate | CL4: Amount | CM4: Qty. | CN4: Unit | CO4: Rate | CP4: Amount | CQ4: Pre.Price | CY4: Qty. | CZ4: Unit | DA4: Rate | DB4: Amount | DC4: Qty. | DD4: Unit | DE4: Rate | DF4: Amount | DN4: Qty. | DO4: Unit | DP4: Rate | DQ4: Amount | DR4: Qty. | DS4: Unit | DT4: Rate | DU4: Amount | DV4: Pre. Price | ED4: Qty. | EE4: Unit | EF4: Rate | EG4: Amount | EH4: Qty. | EI4: Unit | EJ4: Rate | EK4: Amount | EL4: Pre Price | ET4: Qty. | EU4: Unit | EV4: Rate | EW4: Amount | EX4: Qty. | EY4: Unit | EZ4: Rate | FA4: Amount | FB4: Pre. Price
A5: 1 | B5: M.S Channel 75x40(2700 mm long) | C5: 20 | D5: Kg | E5: =Rates!C10 | F5: =C5*E5 | G5: 25.9 | H5: kg | I5: =E5 | J5: =G5*I5 | K5: 20 | L5: Kg | M5: =I5 | N5: =K5*M5 | O5: 71 | Q5: 1 | R5: M.S Channel 75x40(2700 mm long) | S5: 20 | T5: Kg | U5: =Rates!C10 | V5: =S5*U5 | W5: 25.9 | X5: kg | Y5: =U5 | Z5: =W5*Y5 | AA5: 20 | AB5: Kg | AC5: =U5 | AD5: =AA5*AC5 | AE5: 71 | AG5: 1 | AH5: M.S Channel 75x40(2900 mm long) | AI5: 21.4 | AJ5: Kg | AK5: =Rates!C10 | AL5: =AI5*AK5 | AM5: 42.8 | AN5: kg | AO5: =AK5 | AP5: =AM5*AO5 | AQ5: 21.4 | AR5: Kg | AS5: =AK5 | AT5: =AQ5*AS5 | AU5: 71 | AW5: 1 | AX5: M.S Channel 75x40(3200 mm long) | AY5: 22.8 | AZ5: Kg | BA5: =Rates!C10 | BB5: =AY5*BA5 | BC5: 45.6 | BD5: kg | BE5: =BA5 | BF5: =BC5*BE5 | BG5: 22.8 | BH5: Kg | BI5: =BA5 | BJ5: =BG5*BI5 | BK5: 71 | BM5: 1 | BN5: M.S Channel 75x40(3200 mm long) | BO5: 22.8 | BP5: Kg | BQ5: =Rates!C10 | BR5: =BO5*BQ5 | BS5: 45.6 | BT5: kg | BU5: =BQ5 | BV5: =BS5*BU5 | BW5: 22.8 | BX5: Kg | BY5: =BQ5 | BZ5: =BW5*BY5 | CA5: 71 | CC5: 1 | CD5: M.S Channel 75x40(3400 mm long) | CE5: 25 | CF5: Kg | CG5: =Rates!C10 | CH5: =CE5*CG5 | CI5: 48 | CJ5: kg | CK5: =CG5 | CL5: =CI5*CK5 | CM5: 25 | CN5: Kg | CO5: =CG5 | CP5: =CM5*CO5 | CQ5: 71 | CS5: 1 | CT5: M.S Channel 75x40(3600 mm long) | CU5: 25.7 | CV5: Kg | CW5: =Rates!C10 | CX5: =CU5*CW5 | CY5: 51.4 | CZ5: kg | DA5: =CW5 | DB5: =CY5*DA5 | DC5: 25.7 | DD5: Kg | DE5: =CW5 | DF5: =DC5*DE5 | DG5: =DF5-CP5 | DH5: 1 | DI5: M.S Channel 75x40(3600 mm long) | DJ5: 25.7 | DK5: Kg | DL5: =Rates!C10 | DM5: =DJ5*DL5 | DN5: 51.4 | DO5: kg | DP5: =DL5 | DQ5: =DN5*DP5 | DR5: 25.7 | DS5: Kg | DT5: =DL5 | DU5: =DR5*DT5 | DV5: 71 | DX5: 1 | DY5: M.S Channel 75x40(3600 mm long) | DZ5: 25.7 | EA5: Kg | EB5: =Rates!C10 | EC5: =DZ5*EB5 | ED5: 51.4 | EE5: kg | EF5: =EB5 | EG5: =ED5*EF5 | EH5: 25.7 | EI5: Kg | EJ5: =EB5 | EK5: =EH5*EJ5 | EL5: 71 | EN5: 1 | EO5: M.S Channel 100x50( 5 mtr. long) | EP5: 47.8 | EQ5: Kg | ER5: =Rates!C10 | ES5: =EP5*ER5 | ET5: 68.8 | EU5: kg | EV5: =ER5 | EW5: =ET5*EV5 | EX5: 47.8 | EY5: Kg | EZ5: =ER5 | FA5: =EX5*EZ5 | FB5: 71
A6: 2 | B6: M.S pipe 150 NB X 700 MM long | C6: 19.7 | D6: Kg | E6: =Rates!C22 | F6: =C6*E6 | G6: 39.4 | H6: kg | I6: =E6 | J6: =G6*I6 | K6: 19.7 | L6: Kg | M6: =I6 | N6: =K6*M6 | O6: 135 | Q6: 2 | R6: M.S pipe 200 NB X 700 MM long | S6: 29 | T6: Kg | U6: =Rates!C22 | V6: =S6*U6 | W6: 58 | X6: kg | Y6: =U6 | Z6: =W6*Y6 | AA6: 29 | AB6: Kg | AC6: =U6 | AD6: =AA6*AC6 | AE6: 135 | AG6: 2 | AH6: M.S Plate 5 mmx1051x700 mm | AI6: 29 | AJ6: Kg | AK6: =Rates!C14 | AL6: =AI6*AK6 | AM6: 58 | AN6: kg | AO6: =AK6 | AP6: =AM6*AO6 | AQ6: 29 | AR6: Kg | AS6: =AK6 | AT6: =AQ6*AS6 | AU6: 72 | AW6: 2 | AX6: M.S Plate 5 mmx1051x700 mm | AY6: 29 | AZ6: Kg | BA6: =Rates!C20 | BB6: =AY6*BA6 | BC6: 58 | BD6: kg | BE6: =BA6 | BF6: =BC6*BE6 | BG6: 29 | BH6: Kg | BI6: =BA6 | BJ6: =BG6*BI6 | BK6: 72 | BM6: 2 | BN6: M.S Plate 5 mmx1318x700 mm | BO6: 36 | BP6: Kg | BQ6: =Rates!C20 | BR6: =BO6*BQ6 | BS6: 72 | BT6: kg | BU6: =BQ6 | BV6: =BS6*BU6 | BW6: 36 | BX6: Kg | BY6: =BQ6 | BZ6: =BW6*BY6 | CA6: 72 | CC6: 2 | CD6: M.S Plate 5 mmx 1428x700 mm | CE6: 39 | CF6: Kg | CG6: =Rates!C20 | CH6: =CE6*CG6 | CI6: 78 | CJ6: kg | CK6: =CG6 | CL6: =CI6*CK6 | CM6: 39 | CN6: Kg | CO6: =CG6 | CP6: =CM6*CO6 | CQ6: 72 | CS6: 2 | CT6: M.S Plate 5 mmx 1444x700 mm | CU6: 39.6 | CV6: Kg | CW6: =Rates!C20 | CX6: =CU6*CW6 | CY6: 79 | CZ6: kg | DA6: =CW6 | DB6: =CY6*DA6 | DC6: 39.6 | DD6: Kg | DE6: =CW6 | DF6: =DC6*DE6 | DG6: =DF6-CP6 | DH6: 2 | DI6: M.S Plate 5 mmx 2166x700 mm | DJ6: 59.5 | DK6: Kg | DL6: =Rates!C20 | DM6: =DJ6*DL6 | DN6: 119 | DO6: kg | DP6: =DL6 | DQ6: =DN6*DP6 | DR6: 59.5 | DS6: Kg | DT6: =DL6 | DU6: =DR6*DT6 | DV6: 72 | DX6: 2 | DY6: M.S Plate 5 mmx 2245x700 mm | DZ6: 61.6 | EA6: Kg | EB6: =Rates!C20 | EC6: =DZ6*EB6 | ED6: 123 | EE6: kg | EF6: =EB6 | EG6: =ED6*EF6 | EH6: 61.6 | EI6: Kg | EJ6: =EB6 | EK6: =EH6*EJ6 | EL6: 72 | EN6: 2 | EO6: M.S Plate 5 mmx 2794x700 mm | EP6: 77 | EQ6: Kg | ER6: =Rates!C20 | ES6: =EP6*ER6 | ET6: 154 | EU6: kg | EV6: =ER6 | EW6: =ET6*EV6 | EX6: 77 | EY6: Kg | EZ6: =ER6 | FA6: =EX6*EZ6 | FB6: 72
A7: 3 | B7: HR Sheet 850x1000X3 MM | C7: 20 | D7: Kg | E7: =Rates!C18 | F7: =C7*E7 | G7: 28 | H7: kg | I7: =E7 | J7: =G7*I7 | K7: 20 | L7: Kg | M7: =I7 | N7: =K7*M7 | O7: 77 | Q7: 3 | R7: HR Sheet 1050X900X3 MM | S7: 22.3 | T7: Kg | U7: =Rates!C18 | V7: =S7*U7 | W7: 30.7 | X7: kg | Y7: =U7 | Z7: =W7*Y7 | AA7: 22.3 | AB7: Kg | AC7: =U7 | AD7: =AA7*AC7 | AE7: 77 | AG7: 3 | AH7: HR Sheet 1100x1000X3 MM | AI7: 25.9 | AJ7: Kg | AK7: =Rates!C18 | AL7: =AI7*AK7 | AM7: 35.3 | AN7: kg | AO7: =AK7 | AP7: =AM7*AO7 | AQ7: 25.9 | AR7: Kg | AS7: =AK7 | AT7: =AQ7*AS7 | AU7: 77 | AW7: 3 | AX7: HR Sheet 1100x1200X3 MM | AY7: 31 | AZ7: Kg | BA7: =Rates!C18 | BB7: =AY7*BA7 | BC7: 41 | BD7: kg | BE7: =BA7 | BF7: =BC7*BE7 | BG7: 31 | BH7: Kg | BI7: =BA7 | BJ7: =BG7*BI7 | BK7: 77 | BM7: 3 | BN7: HR Sheet 1100x1200X3 MM | BO7: 31 | BP7: Kg | BQ7: =Rates!C18 | BR7: =BO7*BQ7 | BS7: 41 | BT7: kg | BU7: =BQ7 | BV7: =BS7*BU7 | BW7: 31 | BX7: Kg | BY7: =BQ7 | BZ7: =BW7*BY7 | CA7: 77 | CC7: 3 | CD7: HR Sheet 1200x1300X3 MM | CE7: 36.7 | CF7: Kg | CG7: =Rates!C18 | CH7: =CE7*CG7 | CI7: 50.8 | CJ7: kg | CK7: =CG7 | CL7: =CI7*CK7 | CM7: 36.7 | CN7: Kg | CO7: =CG7 | CP7: =CM7*CO7 | CQ7: 77 | CS7: 3 | CT7: HR Sheet 1300x1400X3 MM | CU7: 42.8 | CV7: Kg | CW7: =Rates!C18 | CX7: =CU7*CW7 | CY7: 90.4 | CZ7: kg | DA7: =CW7 | DB7: =CY7*DA7 | DC7: 42.8 | DD7: Kg | DE7: =CW7 | DF7: =DC7*DE7 | DG7: =DF7-CP7 | DH7: 3 | DI7: HR Sheet 1300x1400X3 MM | DJ7: 42.8 | DK7: Kg | DL7: =Rates!C18 | DM7: =DJ7*DL7 | DN7: 90.4 | DO7: kg | DP7: =DL7 | DQ7: =DN7*DP7 | DR7: 42.8 | DS7: Kg | DT7: =DL7 | DU7: =DR7*DT7 | DV7: 77 | DX7: 3 | DY7: HR Sheet 1300x1400X3 MM | DZ7: 42.8 | EA7: Kg | EB7: =Rates!C18 | EC7: =DZ7*EB7 | ED7: 90.4 | EE7: kg | EF7: =EB7 | EG7: =ED7*EF7 | EH7: 42.8 | EI7: Kg | EJ7: =EB7 | EK7: =EH7*EJ7 | EL7: 77 | EN7: 3 | EO7: HR Sheet 1800x1900X5 MM | EP7: 134 | EQ7: Kg | ER7: =Rates!C14 | ES7: =EP7*ER7 | ET7: 183 | EU7: kg | EV7: =ER7 | EW7: =ET7*EV7 | EX7: 134 | EY7: Kg | EZ7: =ER7 | FA7: =EX7*EZ7 | FB7: 72
A8: 4 | B8: HR Sheet 709 X175X3 MM | C8: 3 | D8: Kg | E8: =E7 | F8: =C8*E8 | G8: 6 | H8: kg | I8: =E8 | J8: =G8*I8 | K8: 3 | L8: Kg | M8: =I8 | N8: =K8*M8 | O8: 77 | Q8: 4 | R8: HR Sheet 286 diaX175X3 MM | S8: 6 | T8: Kg | U8: =U7 | V8: =S8*U8 | W8: 12 | X8: kg | Y8: =U8 | Z8: =W8*Y8 | AA8: 6 | AB8: Kg | AC8: =U8 | AD8: =AA8*AC8 | AE8: 77 | AG8: 4 | AH8: HR Sheet 1274 X175X3 MM | AI8: 5 | AJ8: Kg | AK8: =AK7 | AL8: =AI8*AK8 | AM8: 10 | AN8: kg | AO8: =AK8 | AP8: =AM8*AO8 | AQ8: 5 | AR8: Kg | AS8: =AK8 | AT8: =AQ8*AS8 | AU8: 77 | AW8: 4 | AX8: HR Sheet 1274 X175X3 MM | AY8: 5 | AZ8: Kg | BA8: =Rates!C18 | BB8: =AY8*BA8 | BC8: 10 | BD8: kg | BE8: =BA8 | BF8: =BC8*BE8 | BG8: 5 | BH8: Kg | BI8: =BA8 | BJ8: =BG8*BI8 | BK8: 77 | BM8: 4 | BN8: HR Sheet 1318 X175X3 MM | BO8: 5.4 | BP8: Kg | BQ8: =Rates!C18 | BR8: =BO8*BQ8 | BS8: 10.8 | BT8: kg | BU8: =BQ8 | BV8: =BS8*BU8 | BW8: 5.4 | BX8: Kg | BY8: =BQ8 | BZ8: =BW8*BY8 | CA8: 77 | CC8: 4 | CD8: HR Sheet 1632 X175X3 MM | CE8: 7 | CF8: Kg | CG8: =Rates!C18 | CH8: =CE8*CG8 | CI8: 14 | CJ8: kg | CK8: =CG8 | CL8: =CI8*CK8 | CM8: 7 | CN8: Kg | CO8: =CG8 | CP8: =CM8*CO8 | CQ8: 77 | CS8: 4 | CT8: HR Sheet 1651 X175X3 MM | CU8: 7 | CV8: Kg | CW8: =Rates!C18 | CX8: =CU8*CW8 | CY8: 14 | CZ8: kg | DA8: =CW8 | DB8: =CY8*DA8 | DC8: 7 | DD8: Kg | DE8: =CW8 | DF8: =DC8*DE8 | DG8: =DF8-CP8 | DH8: 4 | DI8: HR Sheet 2373 X175X3 MM | DJ8: 10 | DK8: Kg | DL8: =Rates!C18 | DM8: =DJ8*DL8 | DN8: 20 | DO8: kg | DP8: =DL8 | DQ8: =DN8*DP8 | DR8: 10 | DS8: Kg | DT8: =DL8 | DU8: =DR8*DT8 | DV8: 77 | DX8: 4 | DY8: HR Sheet 2452 X175X3 MM | DZ8: 10 | EA8: Kg | EB8: =Rates!C18 | EC8: =DZ8*EB8 | ED8: 20 | EE8: kg | EF8: =EB8 | EG8: =ED8*EF8 | EH8: 10 | EI8: Kg | EJ8: =EB8 | EK8: =EH8*EJ8 | EL8: 77 | EN8: 4 | EO8: HR Sheet 3000 X175X3 MM | EP8: 12 | EQ8: Kg | ER8: =Rates!C18 | ES8: =EP8*ER8 | ET8: 24 | EU8: kg | EV8: =ER8 | EW8: =ET8*EV8 | EX8: 12 | EY8: Kg | EZ8: =ER8 | FA8: =EX8*EZ8 | FB8: 77
A9: 5 | B9: M.S Plate 226 diax3 mm | C9: 1.5 | D9: Kg | E9: =E8 | F9: =C9*E9 | G9: 3 | H9: Kg | I9: =E9 | J9: =G9*I9 | K9: 1.5 | L9: Kg | M9: =I9 | N9: =K9*M9 | O9: 77 | Q9: 5 | R9: M.S Plate 5 MM motor base | S9: 10.8 | T9: Kg | U9: =Rates!C20 | V9: =S9*U9 | W9: 10.8 | X9: kg | Y9: =U9 | Z9: =W9*Y9 | AA9: 10.8 | AB9: Kg | AC9: =U9 | AD9: =AA9*AC9 | AE9: 72 | AG9: 5 | AH9: M.S Plate 406 diax3 mm | AI9: 3.8 | AJ9: Kg | AK9: =AK8 | AL9: =AI9*AK9 | AM9: 7.6 | AN9: Kg | AO9: =AK9 | AP9: =AM9*AO9 | AQ9: 3.8 | AR9: Kg | AS9: =AK9 | AT9: =AQ9*AS9 | AU9: 77 | AW9: 5 | AX9: M.S Plate 406 diax3 mm | AY9: 3.8 | AZ9: Kg | BA9: =Rates!C18 | BB9: =AY9*BA9 | BC9: 7.6 | BD9: Kg | BE9: =BA9 | BF9: =BC9*BE9 | BG9: 3.8 | BH9: Kg | BI9: =BA9 | BJ9: =BG9*BI9 | BK9: 77 | BM9: 5 | BN9: M.S Plate 486 diax3 mm | BO9: 5.5 | BP9: Kg | BQ9: =Rates!C18 | BR9: =BO9*BQ9 | BS9: 11 | BT9: Kg | BU9: =BQ9 | BV9: =BS9*BU9 | BW9: 5.5 | BX9: Kg | BY9: =BQ9 | BZ9: =BW9*BY9 | CA9: 77 | CC9: 5 | CD9: M.S Plate 526 diax3 mm | CE9: 6.5 | CF9: Kg | CG9: =Rates!C18 | CH9: =CE9*CG9 | CI9: 13 | CJ9: Kg | CK9: =CG9 | CL9: =CI9*CK9 | CM9: 6.5 | CN9: Kg | CO9: =CG9 | CP9: =CM9*CO9 | CQ9: 77 | CS9: 5 | CT9: M.S Plate 526 diax3 mm | CU9: 6.5 | CV9: Kg | CW9: =Rates!C18 | CX9: =CU9*CW9 | CY9: 13 | CZ9: Kg | DA9: =CW9 | DB9: =CY9*DA9 | DC9: 6.5 | DD9: Kg | DE9: =CW9 | DF9: =DC9*DE9 | DG9: =DF9-CP9 | DH9: 5 | DI9: M.S Plate 756 diax3 mm | DJ9: 13.4 | DK9: Kg | DL9: =Rates!C18 | DM9: =DJ9*DL9 | DN9: 26.8 | DO9: Kg | DP9: =DL9 | DQ9: =DN9*DP9 | DR9: 13.4 | DS9: Kg | DT9: =DL9 | DU9: =DR9*DT9 | DV9: 77 | DX9: 5 | DY9: M.S Plate 781 diax3 mm | DZ9: 14 | EA9: Kg | EB9: =Rates!C18 | EC9: =DZ9*EB9 | ED9: 28 | EE9: Kg | EF9: =EB9 | EG9: =ED9*EF9 | EH9: 14 | EI9: Kg | EJ9: =EB9 | EK9: =EH9*EJ9 | EL9: 77 | EN9: 5 | EO9: M.S Plate 956 diax3 mm | EP9: 21 | EQ9: Kg | ER9: =Rates!C18 | ES9: =EP9*ER9 | ET9: 42 | EU9: Kg | EV9: =ER9 | EW9: =ET9*EV9 | EX9: 21 | EY9: Kg | EZ9: =ER9 | FA9: =EX9*EZ9 | FB9: 77
A10: 6 | B10: M.S Plate 5 MM motor base | C10: 10.8 | D10: Kg | E10: =Rates!C20 | F10: =C10*E10 | G10: 10.8 | H10: kg | I10: =E10 | J10: =G10*I10 | K10: 10.8 | L10: Kg | M10: =I10 | N10: =K10*M10 | O10: 72 | Q10: 6 | R10: M.S Plate 280 diax16 MM | S10: 9.8 | T10: Kg | U10: =Rates!C12 | V10: =S10*U10 | W10: 19.6 | X10: Kg | Y10: =U10 | Z10: =W10*Y10 | AA10: 9.8 | AB10: Kg | AC10: =U10 | AD10: =AA10*AC10 | AE10: 72 | AG10: 6 | AH10: M.S Plate 5 MM motor base | AI10: 10.8 | AJ10: Kg | AK10: =AK6 | AL10: =AI10*AK10 | AM10: 10.8 | AN10: kg | AO10: =AK10 | AP10: =AM10*AO10 | AQ10: 10.8 | AR10: Kg | AS10: =AK10 | AT10: =AQ10*AS10 | AU10: 72 | AW10: 6 | AX10: M.S Plate 5 MM motor base | AY10: 10.8 | AZ10: Kg | BA10: =Rates!C20 | BB10: =AY10*BA10 | BC10: 10.8 | BD10: kg | BE10: =BA10 | BF10: =BC10*BE10 | BG10: 10.8 | BH10: Kg | BI10: =BA10 | BJ10: =BG10*BI10 | BK10: 72 | BM10: 6 | BN10: M.S Plate 5 MM motor base | BO10: 10.8 | BP10: Kg | BQ10: =Rates!C20 | BR10: =BO10*BQ10 | BS10: 10.8 | BT10: kg | BU10: =BQ10 | BV10: =BS10*BU10 | BW10: 10.8 | BX10: Kg | BY10: =BQ10 | BZ10: =BW10*BY10 | CA10: 72 | CC10: 6 | CD10: M.S Plate 5 MM motor base | CE10: 10.8 | CF10: Kg | CG10: =Rates!C20 | CH10: =CE10*CG10 | CI10: 10.8 | CJ10: kg | CK10: =CG10 | CL10: =CI10*CK10 | CM10: 10.8 | CN10: Kg | CO10: =CG10 | CP10: =CM10*CO10 | CQ10: 72 | CS10: 6 | CT10: M.S Plate 5 MM motor base | CU10: 10.8 | CV10: Kg | CW10: =Rates!C20 | CX10: =CU10*CW10 | CY10: 10.8 | CZ10: kg | DA10: =CW10 | DB10: =CY10*DA10 | DC10: 10.8 | DD10: Kg | DE10: =CW10 | DF10: =DC10*DE10 | DG10: =DF10-CP10 | DH10: 6 | DI10: M.S Plate 5 MM motor base | DJ10: 14 | DK10: Kg | DL10: =Rates!C14 | DM10: =DJ10*DL10 | DN10: 14 | DO10: kg | DP10: =DL10 | DQ10: =DN10*DP10 | DR10: 14 | DS10: Kg | DT10: =DL10 | DU10: =DR10*DT10 | DV10: 72 | DX10: 6 | DY10: M.S Plate 5 MM motor base | DZ10: 14 | EA10: Kg | EB10: =Rates!C14 | EC10: =DZ10*EB10 | ED10: 14 | EE10: kg | EF10: =EB10 | EG10: =ED10*EF10 | EH10: 14 | EI10: Kg | EJ10: =EB10 | EK10: =EH10*EJ10 | EL10: 72 | EN10: 6 | EO10: M.S Plate 5 MM motor base | EP10: 14 | EQ10: Kg | ER10: =Rates!C20 | ES10: =EP10*ER10 | ET10: 14 | EU10: kg | EV10: =ER10 | EW10: =ET10*EV10 | EX10: 14 | EY10: Kg | EZ10: =ER10 | FA10: =EX10*EZ10 | FB10: 72
A11: 7 | B11: M.S Plate 220 diax16 MM | C11: 6 | D11: Kg | E11: =Rates!C13 | F11: =C11*E11 | G11: 12 | H11: Kg | I11: =E11 | J11: =G11*I11 | K11: 6 | L11: Kg | M11: =I11 | N11: =K11*M11 | O11: 72 | Q11: 7 | R11: M.S Plate 240 dia x5 mm | S11: 2.2 | T11: Kg | U11: =Rates!C14 | V11: =S11*U11 | W11: 4.4 | X11: Kg | Y11: =U11 | Z11: =W11*Y11 | AA11: 2.2 | AB11: Kg | AC11: =U11 | AD11: =AA11*AC11 | AE11: 72 | AG11: 7 | AH11: M.S Plate 400 diax16 MM | AI11: 20 | AJ11: Kg | AK11: =Rates!C12 | AL11: =AI11*AK11 | AM11: 40 | AN11: Kg | AO11: =AK11 | AP11: =AM11*AO11 | AQ11: 20 | AR11: Kg | AS11: =AK11 | AT11: =AQ11*AS11 | AU11: 72 | AW11: 7 | AX11: M.S Plate 400 diax16 MM | AY11: 20 | AZ11: Kg | BA11: =Rates!C12 | BB11: =AY11*BA11 | BC11: 40 | BD11: Kg | BE11: =BA11 | BF11: =BC11*BE11 | BG11: 20 | BH11: Kg | BI11: =BA11 | BJ11: =BG11*BI11 | BK11: 72 | BM11: 7 | BN11: M.S Plate 480 diax16 MM | BO11: 29 | BP11: Kg | BQ11: =Rates!C12 | BR11: =BO11*BQ11 | BS11: 58 | BT11: Kg | BU11: =BQ11 | BV11: =BS11*BU11 | BW11: 29 | BX11: Kg | BY11: =BQ11 | BZ11: =BW11*BY11 | CA11: 72 | CC11: 7 | CD11: M.S Plate 520 diax16 MM | CE11: 34 | CF11: Kg | CG11: =Rates!C12 | CH11: =CE11*CG11 | CI11: 68 | CJ11: Kg | CK11: =CG11 | CL11: =CI11*CK11 | CM11: 34 | CN11: Kg | CO11: =CG11 | CP11: =CM11*CO11 | CQ11: 72 | CS11: 7 | CT11: M.S Plate 520 diax16 MM | CU11: 34 | CV11: Kg | CW11: =Rates!C12 | CX11: =CU11*CW11 | CY11: 68 | CZ11: Kg | DA11: =CW11 | DB11: =CY11*DA11 | DC11: 34 | DD11: Kg | DE11: =CW11 | DF11: =DC11*DE11 | DG11: =DF11-CP11 | DH11: 7 | DI11: M.S Plate 750 diax16 MM | DJ11: 70 | DK11: Kg | DL11: =Rates!C12 | DM11: =DJ11*DL11 | DN11: 140 | DO11: Kg | DP11: =DL11 | DQ11: =DN11*DP11 | DR11: 70 | DS11: Kg | DT11: =DL11 | DU11: =DR11*DT11 | DV11: 72 | DX11: 7 | DY11: M.S Plate 775 diax16 MM | DZ11: 75.4 | EA11: Kg | EB11: =Rates!C12 | EC11: =DZ11*EB11 | ED11: 150.8 | EE11: Kg | EF11: =EB11 | EG11: =ED11*EF11 | EH11: 75.4 | EI11: Kg | EJ11: =EB11 | EK11: =EH11*EJ11 | EL11: 72 | EN11: 7 | EO11: M.S Plate 950 diax20MM | EP11: 141 | EQ11: Kg | ER11: =Rates!C12 | ES11: =EP11*ER11 | ET11: 282 | EU11: Kg | EV11: =ER11 | EW11: =ET11*EV11 | EX11: 141 | EY11: Kg | EZ11: =ER11 | FA11: =EX11*EZ11 | FB11: 72
A12: 8 | B12: M.S Plate 240 dia x5 mm | C12: 2.2 | D12: Kg | E12: =Rates!C20 | F12: =C12*E12 | G12: 4.4 | H12: Kg | I12: =E12 | J12: =G12*I12 | K12: 2.2 | L12: Kg | M12: =I12 | N12: =K12*M12 | O12: 72 | Q12: 8 | R12: M.S Pipe 20 NB (5 mtr.) | S12: 9 | T12: kg | U12: =Rates!C22 | V12: =S12*U12 | W12: 9 | X12: kg | Y12: =U12 | Z12: =W12*Y12 | AA12: 9 | AB12: kg | AC12: =U12 | AD12: =AA12*AC12 | AE12: 135 | AG12: 8 | AH12: M.S Plate 380 dia x5 mm | AI12: 5.6 | AJ12: Kg | AK12: =AK10 | AL12: =AI12*AK12 | AM12: 11.2 | AN12: Kg | AO12: =AK12 | AP12: =AM12*AO12 | AQ12: 5.6 | AR12: Kg | AS12: =AK12 | AT12: =AQ12*AS12 | AU12: 72 | AW12: 8 | AX12: M.S Plate 380 dia x5 mm | AY12: 5.6 | AZ12: Kg | BA12: =Rates!C20 | BB12: =AY12*BA12 | BC12: 11.2 | BD12: Kg | BE12: =BA12 | BF12: =BC12*BE12 | BG12: 5.6 | BH12: Kg | BI12: =BA12 | BJ12: =BG12*BI12 | BK12: 72 | BM12: 8 | BN12: M.S Plate 440 dia x5 mm | BO12: 7 | BP12: Kg | BQ12: =Rates!C20 | BR12: =BO12*BQ12 | BS12: 14 | BT12: Kg | BU12: =BQ12 | BV12: =BS12*BU12 | BW12: 7 | BX12: Kg | BY12: =BQ12 | BZ12: =BW12*BY12 | CA12: 72 | CC12: 8 | CD12: M.S Plate 480 dia x5 mm | CE12: 9 | CF12: Kg | CG12: =Rates!C20 | CH12: =CE12*CG12 | CI12: 18 | CJ12: Kg | CK12: =CG12 | CL12: =CI12*CK12 | CM12: 9 | CN12: Kg | CO12: =CG12 | CP12: =CM12*CO12 | CQ12: 72 | CS12: 8 | CT12: M.S Plate 480 dia x5 mm | CU12: 9 | CV12: Kg | CW12: =Rates!C20 | CX12: =CU12*CW12 | CY12: 18 | CZ12: Kg | DA12: =CW12 | DB12: =CY12*DA12 | DC12: 9 | DD12: Kg | DE12: =CW12 | DF12: =DC12*DE12 | DG12: =DF12-CP12 | DH12: 8 | DI12: M.S Plate 770 dia x5 mm | DJ12: 23 | DK12: Kg | DL12: =Rates!C20 | DM12: =DJ12*DL12 | DN12: 46 | DO12: Kg | DP12: =DL12 | DQ12: =DN12*DP12 | DR12: 23 | DS12: Kg | DT12: =DL12 | DU12: =DR12*DT12 | DV12: 72 | DX12: 8 | DY12: M.S Plate 770 dia x5 mm | DZ12: 23 | EA12: Kg | EB12: =Rates!C20 | EC12: =DZ12*EB12 | ED12: 46 | EE12: Kg | EF12: =EB12 | EG12: =ED12*EF12 | EH12: 23 | EI12: Kg | EJ12: =EB12 | EK12: =EH12*EJ12 | EL12: 72 | EN12: 8 | EO12: M.S Plate 910 dia x5 mm | EP12: 32.5 | EQ12: Kg | ER12: =Rates!C20 | ES12: =EP12*ER12 | ET12: 65 | EU12: Kg | EV12: =ER12 | EW12: =ET12*EV12 | EX12: 32.5 | EY12: Kg | EZ12: =ER12 | FA12: =EX12*EZ12 | FB12: 72
A13: 9 | B13: M.S Pipe 20 NB (5 mtr.) | C13: 9 | D13: kg | E13: =Rates!C22 | F13: =C13*E13 | G13: 9 | H13: kg | I13: =E13 | J13: =G13*I13 | K13: 9 | L13: kg | M13: =I13 | N13: =K13*M13 | O13: 135 | Q13: 9 | R13: M.S Pipe 15 NB (.5 mtr.) | S13: 1.5 | T13: Kg | U13: =Rates!C22 | V13: =S13*U13 | W13: 1.5 | X13: kg | Y13: =U13 | Z13: =W13*Y13 | AA13: 1.5 | AB13: Kg | AC13: =U13 | AD13: =AA13*AC13 | AE13: 135 | AG13: 9 | AH13: M.S Pipe 20 NB (5 mtr.) | AI13: 9 | AJ13: kg | AK13: =Rates!C22 | AL13: =AI13*AK13 | AM13: 9 | AN13: kg | AO13: =AK13 | AP13: =AM13*AO13 | AQ13: 9 | AR13: kg | AS13: =AK13 | AT13: =AQ13*AS13 | AU13: 135 | AW13: 9 | AX13: M.S Pipe 20 NB (5 mtr.) | AY13: 9 | AZ13: kg | BA13: =Rates!C22 | BB13: =AY13*BA13 | BC13: 9 | BD13: kg | BE13: =BA13 | BF13: =BC13*BE13 | BG13: 9 | BH13: kg | BI13: =BA13 | BJ13: =BG13*BI13 | BK13: 135 | BM13: 9 | BN13: M.S Pipe 20 NB (6 mtr.) | BO13: 10.8 | BP13: kg | BQ13: =Rates!C22 | BR13: =BO13*BQ13 | BS13: 10.8 | BT13: kg | BU13: =BQ13 | BV13: =BS13*BU13 | BW13: 10.8 | BX13: kg | BY13: =BQ13 | BZ13: =BW13*BY13 | CA13: 135 | CC13: 9 | CD13: M.S Pipe 20 NB (6 mtr.) | CE13: 10.8 | CF13: kg | CG13: =Rates!C22 | CH13: =CE13*CG13 | CI13: 10.8 | CJ13: kg | CK13: =CG13 | CL13: =CI13*CK13 | CM13: 10.8 | CN13: kg | CO13: =CG13 | CP13: =CM13*CO13 | CQ13: 135 | CS13: 9 | CT13: M.S Pipe 20 NB (6 mtr.) | CU13: 10.8 | CV13: kg | CW13: =Rates!C22 | CX13: =CU13*CW13 | CY13: 10.8 | CZ13: kg | DA13: =CW13 | DB13: =CY13*DA13 | DC13: 10.8 | DD13: kg | DE13: =CW13 | DF13: =DC13*DE13 | DG13: =DF13-CP13 | DH13: 9 | DI13: M.S Pipe 25 NB (6 mtr.) | DJ13: 20 | DK13: kg | DL13: =Rates!C22 | DM13: =DJ13*DL13 | DN13: 20 | DO13: kg | DP13: =DL13 | DQ13: =DN13*DP13 | DR13: 20 | DS13: kg | DT13: =DL13 | DU13: =DR13*DT13 | DV13: 135 | DX13: 9 | DY13: M.S Pipe 25 NB (6 mtr.) | DZ13: 20 | EA13: kg | EB13: =Rates!C22 | EC13: =DZ13*EB13 | ED13: 20 | EE13: kg | EF13: =EB13 | EG13: =ED13*EF13 | EH13: 20 | EI13: kg | EJ13: =EB13 | EK13: =EH13*EJ13 | EL13: 135 | EN13: 9 | EO13: M.S Pipe 32 NB (9 mtr.) | EP13: 32 | EQ13: kg | ER13: =Rates!C22 | ES13: =EP13*ER13 | ET13: 32 | EU13: kg | EV13: =ER13 | EW13: =ET13*EV13 | EX13: 32 | EY13: kg | EZ13: =ER13 | FA13: =EX13*EZ13 | FB13: 135
A14: 10 | B14: M.S Pipe 15 NB (.5 mtr.) | C14: 1.5 | D14: Kg | E14: =Rates!C22 | F14: =C14*E14 | G14: 1.5 | H14: kg | I14: =E14 | J14: =G14*I14 | K14: 1.5 | L14: Kg | M14: =I14 | N14: =K14*M14 | O14: 135 | Q14: 10 | R14: M.S Channel 100X50(400 mm long) | S14: 3.8 | T14: Kg | U14: =Rates!C10 | V14: =S14*U14 | W14: 7.6 | X14: kg | Y14: =U14 | Z14: =W14*Y14 | AA14: 3.8 | AB14: Kg | AC14: =U14 | AD14: =AA14*AC14 | AE14: 71 | AG14: 10 | AH14: M.S Pipe 15 NB (.5 mtr.) | AI14: 1.5 | AJ14: Kg | AK14: =Rates!C22 | AL14: =AI14*AK14 | AM14: 1.5 | AN14: kg | AO14: =AK14 | AP14: =AM14*AO14 | AQ14: 1.5 | AR14: Kg | AS14: =AK14 | AT14: =AQ14*AS14 | AU14: 135 | AW14: 10 | AX14: M.S Pipe 15 NB (.5 mtr.) | AY14: 1.5 | AZ14: Kg | BA14: =Rates!C22 | BB14: =AY14*BA14 | BC14: 1.5 | BD14: kg | BE14: =BA14 | BF14: =BC14*BE14 | BG14: 1.5 | BH14: Kg | BI14: =BA14 | BJ14: =BG14*BI14 | BK14: 135 | BM14: 10 | BN14: M.S Pipe 15 NB (.5 mtr.) | BO14: 1.5 | BP14: Kg | BQ14: =Rates!C22 | BR14: =BO14*BQ14 | BS14: 1.5 | BT14: kg | BU14: =BQ14 | BV14: =BS14*BU14 | BW14: 1.5 | BX14: Kg | BY14: =BQ14 | BZ14: =BW14*BY14 | CA14: 135 | CC14: 10 | CD14: M.S Pipe 15 NB (.5 mtr.) | CE14: 1.5 | CF14: Kg | CG14: =Rates!C22 | CH14: =CE14*CG14 | CI14: 1.5 | CJ14: kg | CK14: =CG14 | CL14: =CI14*CK14 | CM14: 1.5 | CN14: Kg | CO14: =CG14 | CP14: =CM14*CO14 | CQ14: 135 | CS14: 10 | CT14: M.S Pipe 15 NB (.5 mtr.) | CU14: 1.5 | CV14: Kg | CW14: =Rates!C22 | CX14: =CU14*CW14 | CY14: 1.5 | CZ14: kg | DA14: =CW14 | DB14: =CY14*DA14 | DC14: 1.5 | DD14: Kg | DE14: =CW14 | DF14: =DC14*DE14 | DG14: =DF14-CP14 | DH14: 10 | DI14: M.S Pipe 20 NB (.5 mtr.) | DJ14: 1.5 | DK14: Kg | DL14: =Rates!C22 | DM14: =DJ14*DL14 | DN14: 1.5 | DO14: kg | DP14: =DL14 | DQ14: =DN14*DP14 | DR14: 1.5 | DS14: Kg | DT14: =DL14 | DU14: =DR14*DT14 | DV14: 135 | DX14: 10 | DY14: M.S Pipe 20 NB (.5 mtr.) | DZ14: 1.5 | EA14: Kg | EB14: =Rates!C22 | EC14: =DZ14*EB14 | ED14: 1.5 | EE14: kg | EF14: =EB14 | EG14: =ED14*EF14 | EH14: 1.5 | EI14: Kg | EJ14: =EB14 | EK14: =EH14*EJ14 | EL14: 135 | EN14: 10 | EO14: M.S Pipe 25NB (0.5 mtr.) | EP14: 2 | EQ14: Kg | ER14: =Rates!C22 | ES14: =EP14*ER14 | ET14: 2 | EU14: kg | EV14: =ER14 | EW14: =ET14*EV14 | EX14: 2 | EY14: Kg | EZ14: =ER14 | FA14: =EX14*EZ14 | FB14: 135
A15: 11 | B15: M.S Channel 100X50(400 mm long) | C15: 3.8 | D15: Kg | E15: =Rates!C10 | F15: =C15*E15 | G15: 7.6 | H15: kg | I15: =E15 | J15: =G15*I15 | K15: 3.8 | L15: Kg | M15: =I15 | N15: =K15*M15 | O15: 71 | Q15: 11 | R15: M.S Flange 15 NB | S15: 4 | T15: nos | U15: 140 | V15: =S15*U15 | W15: 4 | X15: nos | Y15: 140 | Z15: =W15*Y15 | AA15: 2 | AB15: nos | AC15: 140 | AD15: =AA15*AC15 | AE15: 140 | AG15: 11 | AH15: M.S Channel 100X50(700 mm long) | AI15: 6.6 | AJ15: Kg | AK15: =Rates!C10 | AL15: =AI15*AK15 | AM15: 13.2 | AN15: kg | AO15: =AK15 | AP15: =AM15*AO15 | AQ15: 6.6 | AR15: Kg | AS15: =AK15 | AT15: =AQ15*AS15 | AU15: 71 | AW15: 11 | AX15: M.S Channel 100X50(700 mm long) | AY15: 6.6 | AZ15: Kg | BA15: =Rates!C10 | BB15: =AY15*BA15 | BC15: 13.2 | BD15: kg | BE15: =BA15 | BF15: =BC15*BE15 | BG15: 6.6 | BH15: Kg | BI15: =BA15 | BJ15: =BG15*BI15 | BK15: 71 | BM15: 11 | BN15: M.S Channel 100X50(760 mm long) | BO15: 7.26 | BP15: Kg | BQ15: =Rates!C10 | BR15: =BO15*BQ15 | BS15: 15.2 | BT15: kg | BU15: =BQ15 | BV15: =BS15*BU15 | BW15: 7.26 | BX15: Kg | BY15: =BQ15 | BZ15: =BW15*BY15 | CA15: 71 | CC15: 11 | CD15: M.S Channel 100X50(960 mm long) | CE15: 9 | CF15: Kg | CG15: =Rates!C10 | CH15: =CE15*CG15 | CI15: 18 | CJ15: kg | CK15: =CG15 | CL15: =CI15*CK15 | CM15: 9 | CN15: Kg | CO15: =CG15 | CP15: =CM15*CO15 | CQ15: 71 | CS15: 11 | CT15: M.S Channel 100X50(960 mm long) | CU15: 9 | CV15: Kg | CW15: =Rates!C10 | CX15: =CU15*CW15 | CY15: 18 | CZ15: kg | DA15: =CW15 | DB15: =CY15*DA15 | DC15: 9 | DD15: Kg | DE15: =CW15 | DF15: =DC15*DE15 | DG15: =DF15-CP15 | DH15: 11 | DI15: M.S Channel 100X50(1540 mm long) | DJ15: 14.7 | DK15: Kg | DL15: =Rates!C10 | DM15: =DJ15*DL15 | DN15: 29.4 | DO15: kg | DP15: =DL15 | DQ15: =DN15*DP15 | DR15: 14.7 | DS15: Kg | DT15: =DL15 | DU15: =DR15*DT15 | DV15: 71 | DX15: 11 | DY15: M.S Channel 100X50(1540 mm long) | DZ15: 14.7 | EA15: Kg | EB15: =Rates!C10 | EC15: =DZ15*EB15 | ED15: 29.4 | EE15: kg | EF15: =EB15 | EG15: =ED15*EF15 | EH15: 14.7 | EI15: Kg | EJ15: =EB15 | EK15: =EH15*EJ15 | EL15: 71 | EN15: 11 | EO15: M.S Channel 100X50(1900 mm long) | EP15: 18 | EQ15: Kg | ER15: =Rates!C10 | ES15: =EP15*ER15 | ET15: 36 | EU15: kg | EV15: =ER15 | EW15: =ET15*EV15 | EX15: 18 | EY15: Kg | EZ15: =ER15 | FA15: =EX15*EZ15 | FB15: 71
A16: 12 | B16: M.S Flange 15 NB | C16: 4 | D16: nos | E16: 140 | F16: =C16*E16 | G16: 4 | H16: nos | I16: 140 | J16: =G16*I16 | K16: 4 | L16: nos | M16: 140 | N16: =K16*M16 | O16: 140 | Q16: 12 | R16: M.S flat 40x5x800 (4 NOS.) | S16: 4.8 | T16: Kg | U16: =Rates!C11 | V16: =S16*U16 | W16: 6 | X16: kg | Y16: =U16 | Z16: =W16*Y16 | AA16: 4.8 | AB16: Kg | AC16: =U16 | AD16: =AA16*AC16 | AE16: 71 | AG16: 12 | AH16: M.S Flange 15 NB | AI16: 4 | AJ16: nos | AK16: 140 | AL16: =AI16*AK16 | AM16: 4 | AN16: nos | AO16: 140 | AP16: =AM16*AO16 | AQ16: 4 | AR16: nos | AS16: 140 | AT16: =AQ16*AS16 | AU16: 140 | AW16: 12 | AX16: M.S Flange 15 NB | AY16: 4 | AZ16: nos | BA16: 140 | BB16: =AY16*BA16 | BC16: 4 | BD16: nos | BE16: 140 | BF16: =BC16*BE16 | BG16: 4 | BH16: nos | BI16: 140 | BJ16: =BG16*BI16 | BK16: 140 | BM16: 12 | BN16: M.S Flange 15 NB | BO16: 4 | BP16: nos | BQ16: 140 | BR16: =BO16*BQ16 | BS16: 4 | BT16: nos | BU16: 140 | BV16: =BS16*BU16 | BW16: 4 | BX16: nos | BY16: 140 | BZ16: =BW16*BY16 | CA16: 140 | CC16: 12 | CD16: M.S Flange 15 NB | CE16: 4 | CF16: nos | CG16: 140 | CH16: =CE16*CG16 | CI16: 4 | CJ16: nos | CK16: 140 | CL16: =CI16*CK16 | CM16: 4 | CN16: nos | CO16: 140 | CP16: =CM16*CO16 | CQ16: 140 | CS16: 12 | CT16: M.S Flange 15 NB | CU16: 4 | CV16: nos | CW16: 140 | CX16: =CU16*CW16 | CY16: 4 | CZ16: nos | DA16: 140 | DB16: =CY16*DA16 | DC16: 4 | DD16: nos | DE16: 140 | DF16: =DC16*DE16 | DG16: =DF16-CP16 | DH16: 12 | DI16: M.S Flange 20 NB | DJ16: 4 | DK16: nos | DL16: 150 | DM16: =DJ16*DL16 | DN16: 4 | DO16: nos | DP16: 65 | DQ16: =DN16*DP16 | DR16: 4 | DS16: nos | DT16: 65 | DU16: =DR16*DT16 | DV16: 150 | DX16: 12 | DY16: M.S Flange 20 NB | DZ16: 4 | EA16: nos | EB16: 150 | EC16: =DZ16*EB16 | ED16: 4 | EE16: nos | EF16: 150 | EG16: =ED16*EF16 | EH16: 4 | EI16: nos | EJ16: 150 | EK16: =EH16*EJ16 | EL16: 150 | EN16: 12 | EO16: M.S Flange 25 NB | EP16: 4 | EQ16: nos | ER16: 175 | ES16: =EP16*ER16 | ET16: 4 | EU16: nos | EV16: 175 | EW16: =ET16*EV16 | EX16: 4 | EY16: nos | EZ16: 175 | FA16: =EX16*EZ16 | FB16: 175
A17: 13 | B17: M.S flat 40x5x800 (4 NOS.) | C17: 4.8 | D17: Kg | E17: =Rates!C11 | F17: =C17*E17 | G17: 6 | H17: kg | I17: =E17 | J17: =G17*I17 | K17: 4.8 | L17: Kg | M17: =E17 | N17: =K17*M17 | O17: 71 | Q17: 13 | R17: M.S Flange 20 NB | S17: 20 | T17: Nos | U17: 150 | V17: =S17*U17 | W17: 24 | X17: Nos | Y17: 150 | Z17: =W17*Y17 | AA17: 20 | AB17: Nos | AC17: 150 | AD17: =AA17*AC17 | AE17: 150 | AG17: 13 | AH17: M.S flat 40x5x800 (4 NOS.) | AI17: 4.8 | AJ17: Kg | AK17: =Rates!C11 | AL17: =AI17*AK17 | AM17: 6 | AN17: kg | AO17: =AK17 | AP17: =AM17*AO17 | AQ17: 4.8 | AR17: Kg | AS17: =AK17 | AT17: =AQ17*AS17 | AU17: 71 | AW17: 13 | AX17: M.S flat 40x5x800 (4 NOS.) | AY17: 4.8 | AZ17: Kg | BA17: =Rates!C11 | BB17: =AY17*BA17 | BC17: 6 | BD17: kg | BE17: =BA17 | BF17: =BC17*BE17 | BG17: 4.8 | BH17: Kg | BI17: =BA17 | BJ17: =BG17*BI17 | BK17: 71 | BM17: 13 | BN17: M.S flat 40x5x800 (4 NOS.) | BO17: 4.8 | BP17: Kg | BQ17: =Rates!C11 | BR17: =BO17*BQ17 | BS17: 6 | BT17: kg | BU17: =BQ17 | BV17: =BS17*BU17 | BW17: 4.8 | BX17: Kg | BY17: =BQ17 | BZ17: =BW17*BY17 | CA17: 71 | CC17: 13 | CD17: M.S flat 40x5x800 (4 NOS.) | CE17: 4.8 | CF17: Kg | CG17: =Rates!C11 | CH17: =CE17*CG17 | CI17: 6 | CJ17: kg | CK17: =CG17 | CL17: =CI17*CK17 | CM17: 4.8 | CN17: Kg | CO17: =CG17 | CP17: =CM17*CO17 | CQ17: 71 | CS17: 13 | CT17: M.S flat 40x5x800 (4 NOS.) | CU17: 4.8 | CV17: Kg | CW17: =Rates!C11 | CX17: =CU17*CW17 | CY17: 6 | CZ17: kg | DA17: =CW17 | DB17: =CY17*DA17 | DC17: 4.8 | DD17: Kg | DE17: =CW17 | DF17: =DC17*DE17 | DG17: =DF17-CP17 | DH17: 13 | DI17: M.S flat 40x5x800 (4 NOS.) | DJ17: 4.8 | DK17: Kg | DL17: =Rates!C11 | DM17: =DJ17*DL17 | DN17: 6 | DO17: kg | DP17: =DL17 | DQ17: =DN17*DP17 | DR17: 4.8 | DS17: Kg | DT17: =DL17 | DU17: =DR17*DT17 | DV17: 71 | DX17: 13 | DY17: M.S flat 40x5x800 (4 NOS.) | DZ17: 4.8 | EA17: Kg | EB17: =Rates!C11 | EC17: =DZ17*EB17 | ED17: 6 | EE17: kg | EF17: =EB17 | EG17: =ED17*EF17 | EH17: 4.8 | EI17: Kg | EJ17: =EB17 | EK17: =EH17*EJ17 | EL17: 71 | EN17: 13 | EO17: M.S flat 40x5x800 (4 NOS.) | EP17: 4.8 | EQ17: Kg | ER17: =Rates!C11 | ES17: =EP17*ER17 | ET17: 6 | EU17: kg | EV17: =ER17 | EW17: =ET17*EV17 | EX17: 4.8 | EY17: Kg | EZ17: =ER17 | FA17: =EX17*EZ17 | FB17: 71
A18: 14 | B18: M.S Flange 20 NB | C18: 20 | D18: Nos | E18: 150 | F18: =C18*E18 | G18: 24 | H18: Nos | I18: 150 | J18: =G18*I18 | K18: 20 | L18: Nos | M18: 150 | N18: =K18*M18 | O18: 150 | Q18: 14 | R18: M.S Elbow 20 NB | S18: 4 | T18: Nos | U18: 90 | V18: =S18*U18 | W18: 4 | X18: Nos | Y18: 90 | Z18: =W18*Y18 | AA18: 4 | AB18: Nos | AC18: 90 | AD18: =AA18*AC18 | AE18: 90 | AG18: 14 | AH18: M.S Flange 20 NB | AI18: 20 | AJ18: Nos | AK18: 150 | AL18: =AI18*AK18 | AM18: 24 | AN18: Nos | AO18: 150 | AP18: =AM18*AO18 | AQ18: 20 | AR18: Nos | AS18: 150 | AT18: =AQ18*AS18 | AU18: 150 | AW18: 14 | AX18: M.S Flange 20 NB | AY18: 20 | AZ18: Nos | BA18: 150 | BB18: =AY18*BA18 | BC18: 24 | BD18: Nos | BE18: 150 | BF18: =BC18*BE18 | BG18: 20 | BH18: Nos | BI18: 150 | BJ18: =BG18*BI18 | BK18: 150 | BM18: 14 | BN18: M.S Flange 20 NB | BO18: 20 | BP18: Nos | BQ18: 150 | BR18: =BO18*BQ18 | BS18: 24 | BT18: Nos | BU18: 150 | BV18: =BS18*BU18 | BW18: 20 | BX18: Nos | BY18: 150 | BZ18: =BW18*BY18 | CA18: 150 | CC18: 14 | CD18: M.S Flange 20 NB | CE18: 20 | CF18: Nos | CG18: 150 | CH18: =CE18*CG18 | CI18: 24 | CJ18: Nos | CK18: 150 | CL18: =CI18*CK18 | CM18: 20 | CN18: Nos | CO18: 150 | CP18: =CM18*CO18 | CQ18: 150 | CS18: 14 | CT18: M.S Flange 20 NB | CU18: 20 | CV18: Nos | CW18: 150 | CX18: =CU18*CW18 | CY18: 24 | CZ18: Nos | DA18: 150 | DB18: =CY18*DA18 | DC18: 20 | DD18: Nos | DE18: 150 | DF18: =DC18*DE18 | DG18: =DF18-CP18 | DH18: 14 | DI18: M.S Flange 25 NB | DJ18: 20 | DK18: Nos | DL18: 175 | DM18: =DJ18*DL18 | DN18: 24 | DO18: Nos | DP18: 175 | DQ18: =DN18*DP18 | DR18: 20 | DS18: Nos | DT18: 175 | DU18: =DR18*DT18 | DV18: 175 | DX18: 14 | DY18: M.S Flange 25 NB | DZ18: 20 | EA18: Nos | EB18: 175 | EC18: =DZ18*EB18 | ED18: 24 | EE18: Nos | EF18: 175 | EG18: =ED18*EF18 | EH18: 20 | EI18: Nos | EJ18: 175 | EK18: =EH18*EJ18 | EL18: 175 | EN18: 14 | EO18: M.S Flange 32 NB | EP18: 20 | EQ18: Nos | ER18: 200 | ES18: =EP18*ER18 | ET18: 24 | EU18: Nos | EV18: 200 | EW18: =ET18*EV18 | EX18: 20 | EY18: Nos | EZ18: 200 | FA18: =EX18*EZ18 | FB18: 200
A19: 15 | B19: M.S Elbow 20 NB | C19: 4 | D19: Nos | E19: 90 | F19: =C19*E19 | G19: 4 | H19: Nos | I19: 90 | J19: =G19*I19 | K19: 4 | L19: Nos | M19: 90 | N19: =K19*M19 | O19: 90 | Q19: 15 | R19: M.S TEE 20 NB | S19: 6 | T19: Nos | U19: 105 | V19: =S19*U19 | W19: 6 | X19: Nos | Y19: 105 | Z19: =W19*Y19 | AA19: 6 | AB19: Nos | AC19: 105 | AD19: =AA19*AC19 | AE19: 105 | AG19: 15 | AH19: M.S Elbow 20 NB | AI19: 4 | AJ19: Nos | AK19: 90 | AL19: =AI19*AK19 | AM19: 4 | AN19: Nos | AO19: 90 | AP19: =AM19*AO19 | AQ19: 4 | AR19: Nos | AS19: 90 | AT19: =AQ19*AS19 | AU19: 90 | AW19: 15 | AX19: M.S Elbow 20 NB | AY19: 4 | AZ19: Nos | BA19: 90 | BB19: =AY19*BA19 | BC19: 4 | BD19: Nos | BE19: 90 | BF19: =BC19*BE19 | BG19: 4 | BH19: Nos | BI19: 90 | BJ19: =BG19*BI19 | BK19: 90 | BM19: 15 | BN19: M.S Elbow 20 NB | BO19: 4 | BP19: Nos | BQ19: 90 | BR19: =BO19*BQ19 | BS19: 4 | BT19: Nos | BU19: 90 | BV19: =BS19*BU19 | BW19: 4 | BX19: Nos | BY19: 90 | BZ19: =BW19*BY19 | CA19: 90 | CC19: 15 | CD19: M.S Elbow 20 NB | CE19: 4 | CF19: Nos | CG19: 90 | CH19: =CE19*CG19 | CI19: 4 | CJ19: Nos | CK19: 90 | CL19: =CI19*CK19 | CM19: 4 | CN19: Nos | CO19: 90 | CP19: =CM19*CO19 | CQ19: 90 | CS19: 15 | CT19: M.S Elbow 20 NB | CU19: 4 | CV19: Nos | CW19: 90 | CX19: =CU19*CW19 | CY19: 4 | CZ19: Nos | DA19: 90 | DB19: =CY19*DA19 | DC19: 4 | DD19: Nos | DE19: 90 | DF19: =DC19*DE19 | DG19: =DF19-CP19 | DH19: 15 | DI19: M.S Elbow 25NB | DJ19: 4 | DK19: Nos | DL19: 150 | DM19: =DJ19*DL19 | DN19: 4 | DO19: Nos | DP19: 150 | DQ19: =DN19*DP19 | DR19: 4 | DS19: Nos | DT19: 150 | DU19: =DR19*DT19 | DV19: 150 | DX19: 15 | DY19: M.S Elbow 25NB | DZ19: 4 | EA19: Nos | EB19: 150 | EC19: =DZ19*EB19 | ED19: 4 | EE19: Nos | EF19: 150 | EG19: =ED19*EF19 | EH19: 4 | EI19: Nos | EJ19: 150 | EK19: =EH19*EJ19 | EL19: 150 | EN19: 15 | EO19: M.S Elbow 32NB | EP19: 4 | EQ19: Nos | ER19: 200 | ES19: =EP19*ER19 | ET19: 4 | EU19: Nos | EV19: 200 | EW19: =ET19*EV19 | EX19: 4 | EY19: Nos | EZ19: 200 | FA19: =EX19*EZ19 | FB19: 200
A20: 16 | B20: M.S TEE 20 NB | C20: 6 | D20: Nos | E20: 105 | F20: =C20*E20 | G20: 6 | H20: Nos | I20: 105 | J20: =G20*I20 | K20: 6 | L20: Nos | M20: 105 | N20: =K20*M20 | O20: 105 | Q20: 16 | R20: M.S Bend 20 NB | S20: 4 | T20: Nos | U20: 50 | V20: =S20*U20 | W20: 4 | X20: Nos | Y20: 50 | Z20: =W20*Y20 | AA20: 4 | AB20: Nos | AC20: 50 | AD20: =AA20*AC20 | AE20: 50 | AG20: 16 | AH20: M.S TEE 20 NB | AI20: 6 | AJ20: Nos | AK20: 105 | AL20: =AI20*AK20 | AM20: 6 | AN20: Nos | AO20: 105 | AP20: =AM20*AO20 | AQ20: 6 | AR20: Nos | AS20: 105 | AT20: =AQ20*AS20 | AU20: 105 | AW20: 16 | AX20: M.S TEE 20 NB | AY20: 6 | AZ20: Nos | BA20: 105 | BB20: =AY20*BA20 | BC20: 6 | BD20: Nos | BE20: 105 | BF20: =BC20*BE20 | BG20: 6 | BH20: Nos | BI20: 105 | BJ20: =BG20*BI20 | BK20: 105 | BM20: 16 | BN20: M.S TEE 20 NB | BO20: 6 | BP20: Nos | BQ20: 105 | BR20: =BO20*BQ20 | BS20: 6 | BT20: Nos | BU20: 105 | BV20: =BS20*BU20 | BW20: 6 | BX20: Nos | BY20: 105 | BZ20: =BW20*BY20 | CA20: 105 | CC20: 16 | CD20: M.S TEE 20 NB | CE20: 6 | CF20: Nos | CG20: 105 | CH20: =CE20*CG20 | CI20: 6 | CJ20: Nos | CK20: 105 | CL20: =CI20*CK20 | CM20: 6 | CN20: Nos | CO20: =CK20 | CP20: =CM20*CO20 | CQ20: 105 | CS20: 16 | CT20: M.S TEE 20 NB | CU20: 6 | CV20: Nos | CW20: 105 | CX20: =CU20*CW20 | CY20: 6 | CZ20: Nos | DA20: 105 | DB20: =CY20*DA20 | DC20: 6 | DD20: Nos | DE20: 105 | DF20: =DC20*DE20 | DG20: =DF20-CP20 | DH20: 16 | DI20: M.S TEE 25 NB | DJ20: 6 | DK20: Nos | DL20: 200 | DM20: =DJ20*DL20 | DN20: 6 | DO20: Nos | DP20: 200 | DQ20: =DN20*DP20 | DR20: 6 | DS20: Nos | DT20: 200 | DU20: =DR20*DT20 | DV20: 200 | DX20: 16 | DY20: M.S TEE 25 NB | DZ20: 6 | EA20: Nos | EB20: 200 | EC20: =DZ20*EB20 | ED20: 6 | EE20: Nos | EF20: 200 | EG20: =ED20*EF20 | EH20: 6 | EI20: Nos | EJ20: 200 | EK20: =EH20*EJ20 | EL20: 200 | EN20: 16 | EO20: M.S TEE 32 NB | EP20: 6 | EQ20: Nos | ER20: 250 | ES20: =EP20*ER20 | ET20: 6 | EU20: Nos | EV20: 250 | EW20: =ET20*EV20 | EX20: 6 | EY20: Nos | EZ20: 250 | FA20: =EX20*EZ20 | FB20: 250
A21: 17 | B21: M.S Bend 20 NB | C21: 4 | D21: Nos | E21: 50 | F21: =C21*E21 | G21: 4 | H21: Nos | I21: 50 | J21: =G21*I21 | K21: 4 | L21: Nos | M21: 50 | N21: =K21*M21 | O21: 50 | Q21: 17 | R21: M.S Plug 20 NB | S21: 3 | T21: Nos | U21: 20 | V21: =S21*U21 | W21: 4 | X21: Nos | Y21: 20 | Z21: =W21*Y21 | AA21: 3 | AB21: Nos | AC21: 20 | AD21: =AA21*AC21 | AE21: 20 | AG21: 17 | AH21: M.S Bend 20 NB | AI21: 4 | AJ21: Nos | AK21: 50 | AL21: =AI21*AK21 | AM21: 4 | AN21: Nos | AO21: 50 | AP21: =AM21*AO21 | AQ21: 4 | AR21: Nos | AS21: 50 | AT21: =AQ21*AS21 | AU21: 50 | AW21: 17 | AX21: M.S Bend 20 NB | AY21: 4 | AZ21: Nos | BA21: 50 | BB21: =AY21*BA21 | BC21: 4 | BD21: Nos | BE21: 50 | BF21: =BC21*BE21 | BG21: 4 | BH21: Nos | BI21: 50 | BJ21: =BG21*BI21 | BK21: 50 | BM21: 17 | BN21: M.S Bend 20 NB | BO21: 4 | BP21: Nos | BQ21: 50 | BR21: =BO21*BQ21 | BS21: 4 | BT21: Nos | BU21: 50 | BV21: =BS21*BU21 | BW21: 4 | BX21: Nos | BY21: 50 | BZ21: =BW21*BY21 | CA21: 50 | CC21: 17 | CD21: M.S Bend 20 NB | CE21: 4 | CF21: Nos | CG21: 50 | CH21: =CE21*CG21 | CI21: 4 | CJ21: Nos | CK21: 50 | CL21: =CI21*CK21 | CM21: 4 | CN21: Nos | CO21: 50 | CP21: =CM21*CO21 | CQ21: 50 | CS21: 17 | CT21: M.S Bend 20 NB | CU21: 4 | CV21: Nos | CW21: 50 | CX21: =CU21*CW21 | CY21: 4 | CZ21: Nos | DA21: 50 | DB21: =CY21*DA21 | DC21: 4 | DD21: Nos | DE21: 50 | DF21: =DC21*DE21 | DG21: =DF21-CP21 | DH21: 17 | DI21: M.S Bend 25 NB | DJ21: 4 | DK21: Nos | DL21: 60 | DM21: =DJ21*DL21 | DN21: 4 | DO21: Nos | DP21: 60 | DQ21: =DN21*DP21 | DR21: 4 | DS21: Nos | DT21: 60 | DU21: =DR21*DT21 | DV21: 60 | DX21: 17 | DY21: M.S Bend 25 NB | DZ21: 4 | EA21: Nos | EB21: 60 | EC21: =DZ21*EB21 | ED21: 4 | EE21: Nos | EF21: 60 | EG21: =ED21*EF21 | EH21: 4 | EI21: Nos | EJ21: 60 | EK21: =EH21*EJ21 | EL21: 60 | EN21: 17 | EO21: M.S Bend 32 NB | EP21: 4 | EQ21: Nos | ER21: 75 | ES21: =EP21*ER21 | ET21: 4 | EU21: Nos | EV21: 75 | EW21: =ET21*EV21 | EX21: 4 | EY21: Nos | EZ21: 75 | FA21: =EX21*EZ21 | FB21: 75
A22: 18 | B22: M.S Plug 20 NB | C22: 3 | D22: Nos | E22: 20 | F22: =C22*E22 | G22: 4 | H22: Nos | I22: 20 | J22: =G22*I22 | K22: 3 | L22: Nos | M22: 20 | N22: =K22*M22 | O22: 20 | Q22: 18 | R22: M.S Socket 3/8" | S22: 1 | T22: Nos | U22: 20 | V22: =S22*U22 | W22: 1 | X22: Nos | Y22: 20 | Z22: =W22*Y22 | AA22: 1 | AB22: Nos | AC22: 20 | AD22: =AA22*AC22 | AE22: 20 | AG22: 18 | AH22: M.S Plug 20 NB | AI22: 3 | AJ22: Nos | AK22: 20 | AL22: =AI22*AK22 | AM22: 4 | AN22: Nos | AO22: 20 | AP22: =AM22*AO22 | AQ22: 3 | AR22: Nos | AS22: 20 | AT22: =AQ22*AS22 | AU22: 20 | AW22: 18 | AX22: M.S Plug 20 NB | AY22: 3 | AZ22: Nos | BA22: 20 | BB22: =AY22*BA22 | BC22: 4 | BD22: Nos | BE22: 20 | BF22: =BC22*BE22 | BG22: 3 | BH22: Nos | BI22: 20 | BJ22: =BG22*BI22 | BK22: 20 | BM22: 18 | BN22: M.S Plug 20 NB | BO22: 3 | BP22: Nos | BQ22: 20 | BR22: =BO22*BQ22 | BS22: 4 | BT22: Nos | BU22: 20 | BV22: =BS22*BU22 | BW22: 3 | BX22: Nos | BY22: 20 | BZ22: =BW22*BY22 | CA22: 20 | CC22: 18 | CD22: M.S Plug 20 NB | CE22: 3 | CF22: Nos | CG22: 20 | CH22: =CE22*CG22 | CI22: 4 | CJ22: Nos | CK22: 20 | CL22: =CI22*CK22 | CM22: 3 | CN22: Nos | CO22: 20 | CP22: =CM22*CO22 | CQ22: 20 | CS22: 18 | CT22: M.S Plug 20 NB | CU22: 3 | CV22: Nos | CW22: 20 | CX22: =CU22*CW22 | CY22: 4 | CZ22: Nos | DA22: 20 | DB22: =CY22*DA22 | DC22: 3 | DD22: Nos | DE22: 20 | DF22: =DC22*DE22 | DG22: =DF22-CP22 | DH22: 18 | DI22: M.S Plug 25 NB | DJ22: 3 | DK22: Nos | DL22: 35 | DM22: =DJ22*DL22 | DN22: 4 | DO22: Nos | DP22: 35 | DQ22: =DN22*DP22 | DR22: 3 | DS22: Nos | DT22: 35 | DU22: =DR22*DT22 | DV22: 35 | DX22: 18 | DY22: M.S Plug 25 NB | DZ22: 3 | EA22: Nos | EB22: 35 | EC22: =DZ22*EB22 | ED22: 4 | EE22: Nos | EF22: 35 | EG22: =ED22*EF22 | EH22: 3 | EI22: Nos | EJ22: 35 | EK22: =EH22*EJ22 | EL22: 35 | EN22: 18 | EO22: M.S Plug 32 NB | EP22: 3 | EQ22: Nos | ER22: 60 | ES22: =EP22*ER22 | ET22: 4 | EU22: Nos | EV22: 60 | EW22: =ET22*EV22 | EX22: 3 | EY22: Nos | EZ22: 60 | FA22: =EX22*EZ22 | FB22: 60
A23: 19 | B23: M.S Socket 3/8" | C23: 1 | D23: Nos | E23: 20 | F23: =C23*E23 | G23: 1 | H23: Nos | I23: 20 | J23: =G23*I23 | K23: 1 | L23: Nos | M23: 20 | N23: =K23*M23 | O23: 20 | Q23: 19 | R23: M.S Bush Nippal 1/2"x3/4" | S23: 1 | T23: Nos | U23: 20 | V23: =S23*U23 | W23: 2 | X23: Nos | Y23: 20 | Z23: =W23*Y23 | AA23: 1 | AB23: Nos | AC23: 20 | AD23: =AA23*AC23 | AE23: 20 | AG23: 19 | AH23: M.S Socket 3/8" | AI23: 1 | AJ23: Nos | AK23: 20 | AL23: =AI23*AK23 | AM23: 1 | AN23: Nos | AO23: 20 | AP23: =AM23*AO23 | AQ23: 1 | AR23: Nos | AS23: 20 | AT23: =AQ23*AS23 | AU23: 20 | AW23: 19 | AX23: M.S Socket 3/8" | AY23: 1 | AZ23: Nos | BA23: 20 | BB23: =AY23*BA23 | BC23: 1 | BD23: Nos | BE23: 20 | BF23: =BC23*BE23 | BG23: 1 | BH23: Nos | BI23: 20 | BJ23: =BG23*BI23 | BK23: 20 | BM23: 19 | BN23: M.S Socket 3/8" | BO23: 1 | BP23: Nos | BQ23: 20 | BR23: =BO23*BQ23 | BS23: 1 | BT23: Nos | BU23: 20 | BV23: =BS23*BU23 | BW23: 1 | BX23: Nos | BY23: 20 | BZ23: =BW23*BY23 | CA23: 20 | CC23: 19 | CD23: M.S Socket 3/8" | CE23: 1 | CF23: Nos | CG23: 20 | CH23: =CE23*CG23 | CI23: 1 | CJ23: Nos | CK23: 20 | CL23: =CI23*CK23 | CM23: 1 | CN23: Nos | CO23: 20 | CP23: =CM23*CO23 | CQ23: 20 | CS23: 19 | CT23: M.S Socket 3/8" | CU23: 1 | CV23: Nos | CW23: 20 | CX23: =CU23*CW23 | CY23: 1 | CZ23: Nos | DA23: 20 | DB23: =CY23*DA23 | DC23: 1 | DD23: Nos | DE23: 20 | DF23: =DC23*DE23 | DG23: =DF23-CP23 | DH23: 19 | DI23: M.S Socket 3/8" | DJ23: 1 | DK23: Nos | DL23: 20 | DM23: =DJ23*DL23 | DN23: 1 | DO23: Nos | DP23: 20 | DQ23: =DN23*DP23 | DR23: 1 | DS23: Nos | DT23: 20 | DU23: =DR23*DT23 | DV23: 20 | DX23: 19 | DY23: M.S Socket 3/8" | DZ23: 1 | EA23: Nos | EB23: 20 | EC23: =DZ23*EB23 | ED23: 1 | EE23: Nos | EF23: 20 | EG23: =ED23*EF23 | EH23: 1 | EI23: Nos | EJ23: 20 | EK23: =EH23*EJ23 | EL23: 20 | EN23: 19 | EO23: M.S Socket 3/8" | EP23: 1 | EQ23: Nos | ER23: 20 | ES23: =EP23*ER23 | ET23: 1 | EU23: Nos | EV23: 20 | EW23: =ET23*EV23 | EX23: 1 | EY23: Nos | EZ23: 20 | FA23: =EX23*EZ23 | FB23: 20
A24: 20 | B24: M.S Bush Nippal 1/2"x3/4" | C24: 1 | D24: Nos | E24: 20 | F24: =C24*E24 | G24: 2 | H24: Nos | I24: 20 | J24: =G24*I24 | K24: 1 | L24: Nos | M24: 20 | N24: =K24*M24 | O24: 20 | Q24: 20 | R24: Pressure Regulator 3/4" | S24: 1 | T24: Nos | U24: 1350 | V24: =S24*U24 | W24: 1 | X24: Nos | Y24: 1350 | Z24: =W24*Y24 | AA24: 1 | AB24: Nos | AC24: 1350 | AD24: =AA24*AC24 | AE24: 1350 | AG24: 20 | AH24: M.S Bush Nippal 1/2"x3/4" | AI24: 1 | AJ24: Nos | AK24: 20 | AL24: =AI24*AK24 | AM24: 2 | AN24: Nos | AO24: 20 | AP24: =AM24*AO24 | AQ24: 1 | AR24: Nos | AS24: 20 | AT24: =AQ24*AS24 | AU24: 20 | AW24: 20 | AX24: M.S Bush Nippal 1/2"x3/4" | AY24: 1 | AZ24: Nos | BA24: 20 | BB24: =AY24*BA24 | BC24: 2 | BD24: Nos | BE24: 20 | BF24: =BC24*BE24 | BG24: 1 | BH24: Nos | BI24: 20 | BJ24: =BG24*BI24 | BK24: 20 | BM24: 20 | BN24: M.S Bush Nippal 1/2"x3/4" | BO24: 1 | BP24: Nos | BQ24: 20 | BR24: =BO24*BQ24 | BS24: 2 | BT24: Nos | BU24: 20 | BV24: =BS24*BU24 | BW24: 1 | BX24: Nos | BY24: 20 | BZ24: =BW24*BY24 | CA24: 20 | CC24: 20 | CD24: M.S Bush Nippal 1/2"x3/4" | CE24: 1 | CF24: Nos | CG24: 20 | CH24: =CE24*CG24 | CI24: 2 | CJ24: Nos | CK24: 20 | CL24: =CI24*CK24 | CM24: 1 | CN24: Nos | CO24: 20 | CP24: =CM24*CO24 | CQ24: 20 | CS24: 20 | CT24: M.S Bush Nippal 1/2"x3/4" | CU24: 1 | CV24: Nos | CW24: 20 | CX24: =CU24*CW24 | CY24: 2 | CZ24: Nos | DA24: 20 | DB24: =CY24*DA24 | DC24: 1 | DD24: Nos | DE24: 20 | DF24: =DC24*DE24 | DG24: =DF24-CP24 | DH24: 20 | DI24: M.S Bush Nippal 1/2"x 25 NB | DJ24: 1 | DK24: Nos | DL24: 40 | DM24: =DJ24*DL24 | DN24: 2 | DO24: Nos | DP24: 40 | DQ24: =DN24*DP24 | DR24: 1 | DS24: Nos | DT24: 40 | DU24: =DR24*DT24 | DV24: 40 | DX24: 20 | DY24: M.S Bush Nippal 1/2"x 25 NB | DZ24: 1 | EA24: Nos | EB24: 40 | EC24: =DZ24*EB24 | ED24: 2 | EE24: Nos | EF24: 40 | EG24: =ED24*EF24 | EH24: 1 | EI24: Nos | EJ24: 40 | EK24: =EH24*EJ24 | EL24: 40 | EN24: 20 | EO24: M.S Bush Nippal 1/2"x 32 NB | EP24: 1 | EQ24: Nos | ER24: 60 | ES24: =EP24*ER24 | ET24: 2 | EU24: Nos | EV24: 60 | EW24: =ET24*EV24 | EX24: 1 | EY24: Nos | EZ24: 60 | FA24: =EX24*EZ24 | FB24: 60
A25: 21 | B25: Pressure Regulator 3/4" | C25: 1 | D25: Nos | E25: 1350 | F25: =C25*E25 | G25: 1 | H25: Nos | I25: 1350 | J25: =G25*I25 | K25: 1 | L25: Nos | M25: 1350 | N25: =K25*M25 | O25: 1350 | Q25: 21 | R25: Duplex Filter | S25: 1 | T25: Nos | U25: 3900 | V25: =S25*U25 | W25: 2 | X25: Nos | Y25: 3900 | Z25: =W25*Y25 | AA25: 1 | AB25: Nos | AC25: 3900 | AD25: =AA25*AC25 | AE25: 3900 | AG25: 21 | AH25: Pressure Regulator 3/4" | AI25: 1 | AJ25: Nos | AK25: 1350 | AL25: =AI25*AK25 | AM25: 1 | AN25: Nos | AO25: 1350 | AP25: =AM25*AO25 | AQ25: 1 | AR25: Nos | AS25: 1350 | AT25: =AQ25*AS25 | AU25: 1350 | AW25: 21 | AX25: Pressure Regulator 3/4" | AY25: 1 | AZ25: Nos | BA25: 1350 | BB25: =AY25*BA25 | BC25: 1 | BD25: Nos | BE25: 1350 | BF25: =BC25*BE25 | BG25: 1 | BH25: Nos | BI25: 1350 | BJ25: =BG25*BI25 | BK25: 1350 | BM25: 21 | BN25: Pressure Regulator 3/4" | BO25: 1 | BP25: Nos | BQ25: 1350 | BR25: =BO25*BQ25 | BS25: 1 | BT25: Nos | BU25: 1350 | BV25: =BS25*BU25 | BW25: 1 | BX25: Nos | BY25: 1350 | BZ25: =BW25*BY25 | CA25: 1350 | CC25: 21 | CD25: Pressure Regulator 3/4" | CE25: 1 | CF25: Nos | CG25: 1350 | CH25: =CE25*CG25 | CI25: 1 | CJ25: Nos | CK25: 1350 | CL25: =CI25*CK25 | CM25: 1 | CN25: Nos | CO25: 1350 | CP25: =CM25*CO25 | CQ25: 1350 | CS25: 21 | CT25: Pressure Regulator 3/4" | CU25: 1 | CV25: Nos | CW25: 1350 | CX25: =CU25*CW25 | CY25: 1 | CZ25: Nos | DA25: 1350 | DB25: =CY25*DA25 | DC25: 1 | DD25: Nos | DE25: 1350 | DF25: =DC25*DE25 | DG25: =DF25-CP25 | DH25: 21 | DI25: Pressure Regulator 25 NB | DJ25: 1 | DK25: Nos | DL25: 3500 | DM25: =DJ25*DL25 | DN25: 1 | DO25: Nos | DP25: 3500 | DQ25: =DN25*DP25 | DR25: 1 | DS25: Nos | DT25: 3500 | DU25: =DR25*DT25 | DV25: 3500 | DX25: 21 | DY25: Pressure Regulator 25 NB | DZ25: 1 | EA25: Nos | EB25: 3500 | EC25: =DZ25*EB25 | ED25: 1 | EE25: Nos | EF25: 3500 | EG25: =ED25*EF25 | EH25: 1 | EI25: Nos | EJ25: 3500 | EK25: =EH25*EJ25 | EL25: 3500 | EN25: 21 | EO25: Pressure Regulator 32 NB | EP25: 1 | EQ25: Nos | ER25: 5000 | ES25: =EP25*ER25 | ET25: 1 | EU25: Nos | EV25: 5000 | EW25: =ET25*EV25 | EX25: 1 | EY25: Nos | EZ25: 5000 | FA25: =EX25*EZ25 | FB25: 5000
A26: 22 | B26: Duplex Filter | C26: 1 | D26: Nos | E26: 3900 | F26: =C26*E26 | G26: 2 | H26: Nos | I26: 3900 | J26: =G26*I26 | K26: 1 | L26: Nos | M26: 3900 | N26: =K26*M26 | O26: 3900 | Q26: 22 | R26: Simplex Filter | S26: 1 | T26: Nos | U26: 1700 | V26: =S26*U26 | W26: 0 | X26: Nos | Y26: 0 | Z26: =W26*Y26 | AA26: 1 | AB26: Nos | AC26: 1500 | AD26: =AA26*AC26 | AE26: 1500 | AG26: 22 | AH26: Duplex Filter | AI26: 1 | AJ26: Nos | AK26: 3900 | AL26: =AI26*AK26 | AM26: 2 | AN26: Nos | AO26: 3900 | AP26: =AM26*AO26 | AQ26: 1 | AR26: Nos | AS26: 3900 | AT26: =AQ26*AS26 | AU26: 3900 | AW26: 22 | AX26: Duplex Filter | AY26: 1 | AZ26: Nos | BA26: 3900 | BB26: =AY26*BA26 | BC26: 2 | BD26: Nos | BE26: 3900 | BF26: =BC26*BE26 | BG26: 1 | BH26: Nos | BI26: 3900 | BJ26: =BG26*BI26 | BK26: 3900 | BM26: 22 | BN26: Duplex Filter | BO26: 1 | BP26: Nos | BQ26: 3900 | BR26: =BO26*BQ26 | BS26: 2 | BT26: Nos | BU26: 3900 | BV26: =BS26*BU26 | BW26: 1 | BX26: Nos | BY26: 3900 | BZ26: =BW26*BY26 | CA26: 3900 | CC26: 22 | CD26: Duplex Filter | CE26: 1 | CF26: Nos | CG26: 3900 | CH26: =CE26*CG26 | CI26: 2 | CJ26: Nos | CK26: 3900 | CL26: =CI26*CK26 | CM26: 1 | CN26: Nos | CO26: 3900 | CP26: =CM26*CO26 | CQ26: 3900 | CS26: 22 | CT26: Duplex Filter | CU26: 1 | CV26: Nos | CW26: 3900 | CX26: =CU26*CW26 | CY26: 2 | CZ26: Nos | DA26: 3900 | DB26: =CY26*DA26 | DC26: 1 | DD26: Nos | DE26: 3900 | DF26: =DC26*DE26 | DG26: =DF26-CP26 | DH26: 22 | DI26: Duplex Filter 25 NB | DJ26: 1 | DK26: Nos | DL26: 3900 | DM26: =DJ26*DL26 | DN26: 2 | DO26: Nos | DP26: 3900 | DQ26: =DN26*DP26 | DR26: 1 | DS26: Nos | DT26: 3900 | DU26: =DR26*DT26 | DV26: 3900 | DX26: 22 | DY26: Duplex Filter 25 NB | DZ26: 1 | EA26: Nos | EB26: 3900 | EC26: =DZ26*EB26 | ED26: 2 | EE26: Nos | EF26: 3900 | EG26: =ED26*EF26 | EH26: 1 | EI26: Nos | EJ26: 3900 | EK26: =EH26*EJ26 | EL26: 3900 | EN26: 22 | EO26: Duplex Filter 32 NB | EP26: 1 | EQ26: Nos | ER26: 4500 | ES26: =EP26*ER26 | ET26: 2 | EU26: Nos | EV26: 4500 | EW26: =ET26*EV26 | EX26: 1 | EY26: Nos | EZ26: 4500 | FA26: =EX26*EZ26 | FB26: 4500
A27: 23 | B27: Simplex Filter | C27: 1 | D27: Nos | E27: 1700 | F27: =C27*E27 | G27: 0 | H27: Nos | I27: 0 | J27: =G27*I27 | K27: 1 | L27: Nos | M27: 1500 | N27: =K27*M27 | O27: 1500 | Q27: 23 | R27: Gate Valve 20 NB | S27: 7 | T27: Nos | U27: 1000 | V27: =S27*U27 | W27: 9 | X27: Nos | Y27: 900 | Z27: =W27*Y27 | AA27: 5 | AB27: Nos | AC27: 900 | AD27: =AA27*AC27 | AE27: 900 | AG27: 23 | AH27: Simplex Filter | AI27: 1 | AJ27: Nos | AK27: 1700 | AL27: =AI27*AK27 | AM27: 0 | AN27: Nos | AO27: 0 | AP27: =AM27*AO27 | AQ27: 1 | AR27: Nos | AS27: 1500 | AT27: =AQ27*AS27 | AU27: 1500 | AW27: 23 | AX27: Simplex Filter | AY27: 1 | AZ27: Nos | BA27: 1700 | BB27: =AY27*BA27 | BC27: 0 | BD27: Nos | BE27: 0 | BF27: =BC27*BE27 | BG27: 1 | BH27: Nos | BI27: 1500 | BJ27: =BG27*BI27 | BK27: 1500 | BM27: 23 | BN27: Simplex Filter | BO27: 1 | BP27: Nos | BQ27: 1700 | BR27: =BO27*BQ27 | BS27: 0 | BT27: Nos | BU27: 0 | BV27: =BS27*BU27 | BW27: 1 | BX27: Nos | BY27: 1500 | BZ27: =BW27*BY27 | CA27: 1500 | CC27: 23 | CD27: Simplex Filter | CE27: 1 | CF27: Nos | CG27: 1700 | CH27: =CE27*CG27 | CI27: 0 | CJ27: Nos | CK27: 0 | CL27: =CI27*CK27 | CM27: 1 | CN27: Nos | CO27: 1500 | CP27: =CM27*CO27 | CQ27: 1500 | CS27: 23 | CT27: Simplex Filter | CU27: 1 | CV27: Nos | CW27: 1700 | CX27: =CU27*CW27 | CY27: 0 | CZ27: Nos | DA27: 0 | DB27: =CY27*DA27 | DC27: 1 | DD27: Nos | DE27: 1500 | DF27: =DC27*DE27 | DG27: =DF27-CP27 | DH27: 23 | DI27: Simplex Filter 25 NB | DJ27: 1 | DK27: Nos | DL27: 1700 | DM27: =DJ27*DL27 | DN27: 0 | DO27: Nos | DP27: 0 | DQ27: =DN27*DP27 | DR27: 1 | DS27: Nos | DT27: 1500 | DU27: =DR27*DT27 | DV27: 1500 | DX27: 23 | DY27: Simplex Filter 25 NB | DZ27: 1 | EA27: Nos | EB27: 1700 | EC27: =DZ27*EB27 | ED27: 0 | EE27: Nos | EF27: 0 | EG27: =ED27*EF27 | EH27: 1 | EI27: Nos | EJ27: 1500 | EK27: =EH27*EJ27 | EL27: 1500 | EN27: 23 | EO27: Simplex Filter 32 NB | EP27: 1 | EQ27: Nos | ER27: 3500 | ES27: =EP27*ER27 | ET27: 0 | EU27: Nos | EV27: 0 | EW27: =ET27*EV27 | EX27: 1 | EY27: Nos | EZ27: 3500 | FA27: =EX27*EZ27 | FB27: 3500
A28: 24 | B28: Gate Valve 20 NB | C28: 7 | D28: Nos | E28: 1000 | F28: =C28*E28 | G28: 9 | H28: Nos | I28: 900 | J28: =G28*I28 | K28: 5 | L28: Nos | M28: 900 | N28: =K28*M28 | O28: 900 | Q28: 24 | R28: Motor 0.5 HP , 1440 RPM | S28: 2 | T28: Nos | U28: 7000 | V28: =S28*U28 | W28: 2 | X28: Nos | Y28: 7000 | Z28: =W28*Y28 | AA28: 1 | AB28: Nos | AC28: 7000 | AD28: =AA28*AC28 | AE28: 7000 | AG28: 24 | AH28: Gate Valve 20 NB | AI28: 7 | AJ28: Nos | AK28: 1000 | AL28: =AI28*AK28 | AM28: 9 | AN28: Nos | AO28: 900 | AP28: =AM28*AO28 | AQ28: 5 | AR28: Nos | AS28: 900 | AT28: =AQ28*AS28 | AU28: 900 | AW28: 24 | AX28: Gate Valve 20 NB | AY28: 7 | AZ28: Nos | BA28: 1000 | BB28: =AY28*BA28 | BC28: 9 | BD28: Nos | BE28: 900 | BF28: =BC28*BE28 | BG28: 5 | BH28: Nos | BI28: 900 | BJ28: =BG28*BI28 | BK28: 900 | BM28: 24 | BN28: Gate Valve 20 NB | BO28: 7 | BP28: Nos | BQ28: 1000 | BR28: =BO28*BQ28 | BS28: 9 | BT28: Nos | BU28: 900 | BV28: =BS28*BU28 | BW28: 5 | BX28: Nos | BY28: 900 | BZ28: =BW28*BY28 | CA28: 900 | CC28: 24 | CD28: Gate Valve 20 NB | CE28: 7 | CF28: Nos | CG28: 1000 | CH28: =CE28*CG28 | CI28: 9 | CJ28: Nos | CK28: 900 | CL28: =CI28*CK28 | CM28: 5 | CN28: Nos | CO28: 900 | CP28: =CM28*CO28 | CQ28: 900 | CS28: 24 | CT28: Gate Valve 20 NB | CU28: 7 | CV28: Nos | CW28: 1000 | CX28: =CU28*CW28 | CY28: 9 | CZ28: Nos | DA28: 900 | DB28: =CY28*DA28 | DC28: 5 | DD28: Nos | DE28: 900 | DF28: =DC28*DE28 | DG28: =DF28-CP28 | DH28: 24 | DI28: Gate Valve 25 NB | DJ28: 7 | DK28: Nos | DL28: 1550 | DM28: =DJ28*DL28 | DN28: 9 | DO28: Nos | DP28: 1500 | DQ28: =DN28*DP28 | DR28: 5 | DS28: Nos | DT28: 1500 | DU28: =DR28*DT28 | DV28: 1500 | DX28: 24 | DY28: Gate Valve 25 NB | DZ28: 7 | EA28: Nos | EB28: 1550 | EC28: =DZ28*EB28 | ED28: 9 | EE28: Nos | EF28: 1500 | EG28: =ED28*EF28 | EH28: 5 | EI28: Nos | EJ28: 1500 | EK28: =EH28*EJ28 | EL28: 1500 | EN28: 24 | EO28: Gate Valve 32 NB | EP28: 7 | EQ28: Nos | ER28: 2000 | ES28: =EP28*ER28 | ET28: 9 | EU28: Nos | EV28: 2000 | EW28: =ET28*EV28 | EX28: 5 | EY28: Nos | EZ28: 2000 | FA28: =EX28*EZ28 | FB28: 2000
A29: 25 | B29: Motor 0.5 HP , 1440 RPM | C29: 2 | D29: Nos | E29: 7000 | F29: =C29*E29 | G29: 2 | H29: Nos | I29: 7000 | J29: =G29*I29 | K29: 1 | L29: Nos | M29: 7000 | N29: =K29*M29 | O29: 7000 | Q29: 25 | R29: Oil Pump AGP -15 | S29: 2 | T29: Nos | U29: 3500 | V29: =S29*U29 | W29: 2 | X29: Nos | Y29: 3500 | Z29: =W29*Y29 | AA29: 1 | AB29: Nos | AC29: 3500 | AD29: =AA29*AC29 | AE29: 3500 | AG29: 25 | AH29: Motor 0.5 HP , 1440 RPM | AI29: 2 | AJ29: Nos | AK29: 7000 | AL29: =AI29*AK29 | AM29: 2 | AN29: Nos | AO29: 7000 | AP29: =AM29*AO29 | AQ29: 1 | AR29: Nos | AS29: 7000 | AT29: =AQ29*AS29 | AU29: 7000 | AW29: 25 | AX29: Motor 0.5 HP , 1440 RPM | AY29: 2 | AZ29: Nos | BA29: 7000 | BB29: =AY29*BA29 | BC29: 2 | BD29: Nos | BE29: 7000 | BF29: =BC29*BE29 | BG29: 1 | BH29: Nos | BI29: 7000 | BJ29: =BG29*BI29 | BK29: 7000 | BM29: 25 | BN29: Motor 0.5 HP , 1440 RPM | BO29: 2 | BP29: Nos | BQ29: 7000 | BR29: =BO29*BQ29 | BS29: 2 | BT29: Nos | BU29: 7000 | BV29: =BS29*BU29 | BW29: 1 | BX29: Nos | BY29: 7000 | BZ29: =BW29*BY29 | CA29: 7000 | CC29: 25 | CD29: Motor 0.5 HP , 1440 RPM | CE29: 2 | CF29: Nos | CG29: 7000 | CH29: =CE29*CG29 | CI29: 2 | CJ29: Nos | CK29: 7000 | CL29: =CI29*CK29 | CM29: 1 | CN29: Nos | CO29: 7000 | CP29: =CM29*CO29 | CQ29: 7000 | CS29: 25 | CT29: Motor 0.5 HP , 1440 RPM | CU29: 2 | CV29: Nos | CW29: 7000 | CX29: =CU29*CW29 | CY29: 2 | CZ29: Nos | DA29: 7000 | DB29: =CY29*DA29 | DC29: 1 | DD29: Nos | DE29: 7000 | DF29: =DC29*DE29 | DG29: =DF29-CP29 | DH29: 25 | DI29: Motor 1 HP , 1440 RPM | DJ29: 2 | DK29: Nos | DL29: 9000 | DM29: =DJ29*DL29 | DN29: 2 | DO29: Nos | DP29: 9000 | DQ29: =DN29*DP29 | DR29: 1 | DS29: Nos | DT29: 9000 | DU29: =DR29*DT29 | DV29: 9000 | DX29: 25 | DY29: Motor 1 HP , 1440 RPM | DZ29: 2 | EA29: Nos | EB29: 9000 | EC29: =DZ29*EB29 | ED29: 2 | EE29: Nos | EF29: 9000 | EG29: =ED29*EF29 | EH29: 1 | EI29: Nos | EJ29: 9000 | EK29: =EH29*EJ29 | EL29: 9000 | EN29: 25 | EO29: Motor 1 HP , 1440 RPM | EP29: 2 | EQ29: Nos | ER29: 9000 | ES29: =EP29*ER29 | ET29: 2 | EU29: Nos | EV29: 9000 | EW29: =ET29*EV29 | EX29: 1 | EY29: Nos | EZ29: 9000 | FA29: =EX29*EZ29 | FB29: 9000
A30: 26 | B30: Oil Pump AGP -15 | C30: 2 | D30: Nos | E30: 3500 | F30: =C30*E30 | G30: 2 | H30: Nos | I30: 3500 | J30: =G30*I30 | K30: 1 | L30: Nos | M30: 3500 | N30: =K30*M30 | O30: 3500 | Q30: 26 | R30: Heater 6 KW | S30: 1 | T30: Nos | U30: 2050 | V30: =S30*U30 | W30: 2 | X30: Nos | Y30: 1925 | Z30: =W30*Y30 | AA30: 1 | AB30: Nos | AC30: 1925 | AD30: =AA30*AC30 | AE30: 1925 | AG30: 26 | AH30: Oil Pump AGP -15 | AI30: 2 | AJ30: Nos | AK30: 3500 | AL30: =AI30*AK30 | AM30: 2 | AN30: Nos | AO30: 3500 | AP30: =AM30*AO30 | AQ30: 1 | AR30: Nos | AS30: 3500 | AT30: =AQ30*AS30 | AU30: 3500 | AW30: 26 | AX30: Oil Pump AGP -15 | AY30: 2 | AZ30: Nos | BA30: 3500 | BB30: =AY30*BA30 | BC30: 2 | BD30: Nos | BE30: 3500 | BF30: =BC30*BE30 | BG30: 1 | BH30: Nos | BI30: 3500 | BJ30: =BG30*BI30 | BK30: 3500 | BM30: 26 | BN30: Oil Pump AGP -15 | BO30: 2 | BP30: Nos | BQ30: 3500 | BR30: =BO30*BQ30 | BS30: 2 | BT30: Nos | BU30: 3500 | BV30: =BS30*BU30 | BW30: 1 | BX30: Nos | BY30: 3500 | BZ30: =BW30*BY30 | CA30: 3500 | CC30: 26 | CD30: Oil Pump AGP -15 | CE30: 2 | CF30: Nos | CG30: 3500 | CH30: =CE30*CG30 | CI30: 2 | CJ30: Nos | CK30: 3500 | CL30: =CI30*CK30 | CM30: 1 | CN30: Nos | CO30: 3500 | CP30: =CM30*CO30 | CQ30: 3500 | CS30: 26 | CT30: Oil Pump AGP -15 | CU30: 2 | CV30: Nos | CW30: 3500 | CX30: =CU30*CW30 | CY30: 2 | CZ30: Nos | DA30: 3500 | DB30: =CY30*DA30 | DC30: 1 | DD30: Nos | DE30: 3500 | DF30: =DC30*DE30 | DG30: =DF30-CP30 | DH30: 26 | DI30: Oil Pump AGP - 20 | DJ30: 2 | DK30: Nos | DL30: 4500 | DM30: =DJ30*DL30 | DN30: 2 | DO30: Nos | DP30: 4500 | DQ30: =DN30*DP30 | DR30: 1 | DS30: Nos | DT30: 4500 | DU30: =DR30*DT30 | DV30: 4500 | DX30: 26 | DY30: Oil Pump AGP - 20 | DZ30: 2 | EA30: Nos | EB30: 4500 | EC30: =DZ30*EB30 | ED30: 2 | EE30: Nos | EF30: 4500 | EG30: =ED30*EF30 | EH30: 1 | EI30: Nos | EJ30: 4500 | EK30: =EH30*EJ30 | EL30: 4500 | EN30: 26 | EO30: Oil Pump AGP - 25 | EP30: 2 | EQ30: Nos | ER30: 17000 | ES30: =EP30*ER30 | ET30: 2 | EU30: Nos | EV30: 17000 | EW30: =ET30*EV30 | EX30: 1 | EY30: Nos | EZ30: 17000 | FA30: =EX30*EZ30 | FB30: 17000
A31: 27 | B31: Heater 3 KW | C31: 1 | D31: Nos | E31: 1550 | F31: =C31*E31 | G31: 2 | H31: Nos | I31: 1425 | J31: =G31*I31 | K31: 1 | L31: Nos | M31: 1425 | N31: =K31*M31 | O31: 1425 | Q31: 27 | R31: Pressure Gauge 0 -7 Kg | S31: 1 | T31: Nos | U31: 1200 | V31: =S31*U31 | W31: 1 | X31: Nos | Y31: 1000 | Z31: =W31*Y31 | AA31: 1 | AB31: Nos | AC31: 1000 | AD31: =AA31*AC31 | AE31: 1000 | AG31: 27 | AH31: Heater 3 KW | AI31: 3 | AJ31: Nos | AK31: 1550 | AL31: =AI31*AK31 | AM31: 6 | AN31: Nos | AO31: 1425 | AP31: =AM31*AO31 | AQ31: 3 | AR31: Nos | AS31: 1425 | AT31: =AQ31*AS31 | AU31: 1425 | AW31: 27 | AX31: Heater 4 KW | AY31: 3 | AZ31: Nos | BA31: 1750 | BB31: =AY31*BA31 | BC31: 6 | BD31: Nos | BE31: 1625 | BF31: =BC31*BE31 | BG31: 3 | BH31: Nos | BI31: 1625 | BJ31: =BG31*BI31 | BK31: 1625 | BM31: 27 | BN31: Heater 4 KW | BO31: 4 | BP31: Nos | BQ31: 1750 | BR31: =BO31*BQ31 | BS31: 8 | BT31: Nos | BU31: 1625 | BV31: =BS31*BU31 | BW31: 4 | BX31: Nos | BY31: 1625 | BZ31: =BW31*BY31 | CA31: 1625 | CC31: 27 | CD31: Heater 4 KW | CE31: 5 | CF31: Nos | CG31: 1750 | CH31: =CE31*CG31 | CI31: 10 | CJ31: Nos | CK31: 1625 | CL31: =CI31*CK31 | CM31: 5 | CN31: Nos | CO31: 1625 | CP31: =CM31*CO31 | CQ31: 1625 | CS31: 27 | CT31: Heater 6 KW | CU31: 4 | CV31: Nos | CW31: 2050 | CX31: =CU31*CW31 | CY31: 8 | CZ31: Nos | DA31: 1925 | DB31: =CY31*DA31 | DC31: 4 | DD31: Nos | DE31: 1925 | DF31: =DC31*DE31 | DG31: =DF31-CP31 | DH31: 27 | DI31: Heater 6 KW | DJ31: 5 | DK31: Nos | DL31: 2050 | DM31: =DJ31*DL31 | DN31: 10 | DO31: Nos | DP31: 1925 | DQ31: =DN31*DP31 | DR31: 5 | DS31: Nos | DT31: 1925 | DU31: =DR31*DT31 | DV31: 1925 | DX31: 27 | DY31: Heater 6 KW | DZ31: 6 | EA31: Nos | EB31: 2050 | EC31: =DZ31*EB31 | ED31: 12 | EE31: Nos | EF31: 1925 | EG31: =ED31*EF31 | EH31: 6 | EI31: Nos | EJ31: 1925 | EK31: =EH31*EJ31 | EL31: 1925 | EN31: 27 | EO31: Heater 6 KW | EP31: 8 | EQ31: Nos | ER31: 2050 | ES31: =EP31*ER31 | ET31: 16 | EU31: Nos | EV31: 1925 | EW31: =ET31*EV31 | EX31: 8 | EY31: Nos | EZ31: 1925 | FA31: =EX31*EZ31 | FB31: 1925
A32: 28 | B32: Pressure Gauge 0 -7 Kg | C32: 1 | D32: Nos | E32: 1200 | F32: =C32*E32 | G32: 1 | H32: Nos | I32: 1000 | J32: =G32*I32 | K32: 1 | L32: Nos | M32: 1000 | N32: =K32*M32 | O32: 1000 | Q32: 28 | R32: Temp. Gauge 0 -150 *C | S32: 1 | T32: Nos | U32: 600 | V32: =S32*U32 | W32: 2 | X32: Nos | Y32: 600 | Z32: =W32*Y32 | AA32: 1 | AB32: Nos | AC32: 600 | AD32: =AA32*AC32 | AE32: 600 | AG32: 28 | AH32: Pressure Gauge 0 -7 Kg | AI32: 1 | AJ32: Nos | AK32: 1200 | AL32: =AI32*AK32 | AM32: 1 | AN32: Nos | AO32: 1000 | AP32: =AM32*AO32 | AQ32: 1 | AR32: Nos | AS32: 1000 | AT32: =AQ32*AS32 | AU32: 1000 | AW32: 28 | AX32: Pressure Gauge 0 -7 Kg | AY32: 1 | AZ32: Nos | BA32: 1200 | BB32: =AY32*BA32 | BC32: 1 | BD32: Nos | BE32: 1000 | BF32: =BC32*BE32 | BG32: 1 | BH32: Nos | BI32: 1000 | BJ32: =BG32*BI32 | BK32: 1000 | BM32: 28 | BN32: Pressure Gauge 0 -7 Kg | BO32: 1 | BP32: Nos | BQ32: 1200 | BR32: =BO32*BQ32 | BS32: 1 | BT32: Nos | BU32: 1000 | BV32: =BS32*BU32 | BW32: 1 | BX32: Nos | BY32: 1000 | BZ32: =BW32*BY32 | CA32: 1000 | CC32: 28 | CD32: Pressure Gauge 0 -7 Kg | CE32: 1 | CF32: Nos | CG32: 1200 | CH32: =CE32*CG32 | CI32: 1 | CJ32: Nos | CK32: 1000 | CL32: =CI32*CK32 | CM32: 1 | CN32: Nos | CO32: 1000 | CP32: =CM32*CO32 | CQ32: 1000 | CS32: 28 | CT32: Pressure Gauge 0 -7 Kg | CU32: 1 | CV32: Nos | CW32: 1200 | CX32: =CU32*CW32 | CY32: 1 | CZ32: Nos | DA32: 1000 | DB32: =CY32*DA32 | DC32: 1 | DD32: Nos | DE32: 1000 | DF32: =DC32*DE32 | DG32: =DF32-CP32 | DH32: 28 | DI32: Pressure Gauge 0 -7 Kg | DJ32: 1 | DK32: Nos | DL32: 1200 | DM32: =DJ32*DL32 | DN32: 1 | DO32: Nos | DP32: 1000 | DQ32: =DN32*DP32 | DR32: 1 | DS32: Nos | DT32: 1000 | DU32: =DR32*DT32 | DV32: 1000 | DX32: 28 | DY32: Pressure Gauge 0 -7 Kg | DZ32: 1 | EA32: Nos | EB32: 1200 | EC32: =DZ32*EB32 | ED32: 1 | EE32: Nos | EF32: 1000 | EG32: =ED32*EF32 | EH32: 1 | EI32: Nos | EJ32: 1000 | EK32: =EH32*EJ32 | EL32: 1000 | EN32: 28 | EO32: Pressure Gauge 0 -7 Kg | EP32: 1 | EQ32: Nos | ER32: 1200 | ES32: =EP32*ER32 | ET32: 1 | EU32: Nos | EV32: 1000 | EW32: =ET32*EV32 | EX32: 1 | EY32: Nos | EZ32: 1000 | FA32: =EX32*EZ32 | FB32: 1000
A33: 29 | B33: Temp. Gauge 0 -150 *C | C33: 1 | D33: Nos | E33: 600 | F33: =C33*E33 | G33: 2 | H33: Nos | I33: 600 | J33: =G33*I33 | K33: 1 | L33: Nos | M33: 600 | N33: =K33*M33 | O33: 600 | Q33: 29 | R33: Thermostate | S33: 1 | T33: Nos | U33: 400 | V33: =S33*U33 | W33: 2 | X33: Nos | Y33: 350 | Z33: =W33*Y33 | AA33: 1 | AB33: Nos | AC33: 350 | AD33: =AA33*AC33 | AE33: 350 | AG33: 29 | AH33: Temp. Gauge 0 -150 *C | AI33: 1 | AJ33: Nos | AK33: 600 | AL33: =AI33*AK33 | AM33: 2 | AN33: Nos | AO33: 600 | AP33: =AM33*AO33 | AQ33: 1 | AR33: Nos | AS33: 600 | AT33: =AQ33*AS33 | AU33: 600 | AW33: 29 | AX33: Temp. Gauge 0 -150 *C | AY33: 1 | AZ33: Nos | BA33: 600 | BB33: =AY33*BA33 | BC33: 2 | BD33: Nos | BE33: 600 | BF33: =BC33*BE33 | BG33: 1 | BH33: Nos | BI33: 600 | BJ33: =BG33*BI33 | BK33: 600 | BM33: 29 | BN33: Temp. Gauge 0 -150 *C | BO33: 1 | BP33: Nos | BQ33: 600 | BR33: =BO33*BQ33 | BS33: 2 | BT33: Nos | BU33: 600 | BV33: =BS33*BU33 | BW33: 1 | BX33: Nos | BY33: 600 | BZ33: =BW33*BY33 | CA33: 600 | CC33: 29 | CD33: Temp. Gauge 0 -150 *C | CE33: 1 | CF33: Nos | CG33: 600 | CH33: =CE33*CG33 | CI33: 2 | CJ33: Nos | CK33: 600 | CL33: =CI33*CK33 | CM33: 1 | CN33: Nos | CO33: 600 | CP33: =CM33*CO33 | CQ33: 600 | CS33: 29 | CT33: Temp. Gauge 0 -150 *C | CU33: 1 | CV33: Nos | CW33: 600 | CX33: =CU33*CW33 | CY33: 2 | CZ33: Nos | DA33: 600 | DB33: =CY33*DA33 | DC33: 1 | DD33: Nos | DE33: 600 | DF33: =DC33*DE33 | DG33: =DF33-CP33 | DH33: 29 | DI33: Temp. Gauge 0 -150 *C | DJ33: 1 | DK33: Nos | DL33: 600 | DM33: =DJ33*DL33 | DN33: 2 | DO33: Nos | DP33: 600 | DQ33: =DN33*DP33 | DR33: 1 | DS33: Nos | DT33: 600 | DU33: =DR33*DT33 | DV33: 600 | DX33: 29 | DY33: Temp. Gauge 0 -150 *C | DZ33: 1 | EA33: Nos | EB33: 600 | EC33: =DZ33*EB33 | ED33: 2 | EE33: Nos | EF33: 600 | EG33: =ED33*EF33 | EH33: 1 | EI33: Nos | EJ33: 600 | EK33: =EH33*EJ33 | EL33: 600 | EN33: 29 | EO33: Temp. Gauge 0 -150 *C | EP33: 1 | EQ33: Nos | ER33: 600 | ES33: =EP33*ER33 | ET33: 2 | EU33: Nos | EV33: 600 | EW33: =ET33*EV33 | EX33: 1 | EY33: Nos | EZ33: 600 | FA33: =EX33*EZ33 | FB33: 600
A34: 30 | B34: Thermostate | C34: 1 | D34: Nos | E34: 400 | F34: =C34*E34 | G34: 2 | H34: Nos | I34: 350 | J34: =G34*I34 | K34: 1 | L34: Nos | M34: 350 | N34: =K34*M34 | O34: 350 | Q34: 30 | R34: Indicator | S34: 1 | T34: Nos | U34: 100 | V34: =S34*U34 | W34: 2 | X34: Nos | Y34: 100 | Z34: =W34*Y34 | AA34: 1 | AB34: Nos | AC34: 100 | AD34: =AA34*AC34 | AE34: 100 | AG34: 30 | AH34: Thermostate | AI34: 1 | AJ34: Nos | AK34: 400 | AL34: =AI34*AK34 | AM34: 2 | AN34: Nos | AO34: 350 | AP34: =AM34*AO34 | AQ34: 1 | AR34: Nos | AS34: 350 | AT34: =AQ34*AS34 | AU34: 350 | AW34: 30 | AX34: Thermostate | AY34: 1 | AZ34: Nos | BA34: 400 | BB34: 350 | BC34: 2 | BD34: Nos | BE34: 350 | BF34: =BC34*BE34 | BG34: 1 | BH34: Nos | BI34: 350 | BJ34: =BG34*BI34 | BK34: 230 | BM34: 30 | BN34: Thermostate | BO34: 1 | BP34: Nos | BQ34: 400 | BR34: =BO34*BQ34 | BS34: 2 | BT34: Nos | BU34: 350 | BV34: =BS34*BU34 | BW34: 1 | BX34: Nos | BY34: 350 | BZ34: =BW34*BY34 | CA34: 350 | CC34: 30 | CD34: Thermostate | CE34: 1 | CF34: Nos | CG34: 400 | CH34: =CE34*CG34 | CI34: 2 | CJ34: Nos | CK34: 350 | CL34: =CI34*CK34 | CM34: 1 | CN34: Nos | CO34: 350 | CP34: =CM34*CO34 | CQ34: 350 | CS34: 30 | CT34: Thermostate | CU34: 1 | CV34: Nos | CW34: 350 | CX34: =CU34*CW34 | CY34: 2 | CZ34: Nos | DA34: 350 | DB34: =CY34*DA34 | DC34: 1 | DD34: Nos | DE34: 350 | DF34: =DC34*DE34 | DG34: =DF34-CP34 | DH34: 30 | DI34: Thermostate | DJ34: 1 | DK34: Nos | DL34: 350 | DM34: =DJ34*DL34 | DN34: 2 | DO34: Nos | DP34: 350 | DQ34: =DN34*DP34 | DR34: 1 | DS34: Nos | DT34: 350 | DU34: =DR34*DT34 | DV34: 350 | DX34: 30 | DY34: Thermostate | DZ34: 1 | EA34: Nos | EB34: 350 | EC34: =DZ34*EB34 | ED34: 2 | EE34: Nos | EF34: 350 | EG34: =ED34*EF34 | EH34: 1 | EI34: Nos | EJ34: 350 | EK34: =EH34*EJ34 | EL34: 350 | EN34: 30 | EO34: Thermostate | EP34: 2 | EQ34: Nos | ER34: 350 | ES34: =EP34*ER34 | ET34: 4 | EU34: Nos | EV34: 350 | EW34: =ET34*EV34 | EX34: 2 | EY34: Nos | EZ34: 350 | FA34: =EX34*EZ34 | FB34: 350
A35: 31 | B35: Indicator | C35: 1 | D35: Nos | E35: 100 | F35: =C35*E35 | G35: 2 | H35: Nos | I35: 100 | J35: =G35*I35 | K35: 1 | L35: Nos | M35: 100 | N35: =K35*M35 | O35: 100 | Q35: 31 | R35: Connecting Plate | S35: 1 | T35: Nos | U35: 150 | V35: =S35*U35 | W35: 2 | X35: Nos | Y35: 100 | Z35: =W35*Y35 | AA35: 1 | AB35: Nos | AC35: 100 | AD35: =AA35*AC35 | AE35: 100 | AG35: 31 | AH35: Indicator | AI35: 1 | AJ35: Nos | AK35: 100 | AL35: =AI35*AK35 | AM35: 2 | AN35: Nos | AO35: 100 | AP35: =AM35*AO35 | AQ35: 1 | AR35: Nos | AS35: 100 | AT35: =AQ35*AS35 | AU35: 100 | AW35: 31 | AX35: Indicator | AY35: 1 | AZ35: Nos | BA35: 100 | BB35: =AY35*BA35 | BC35: 2 | BD35: Nos | BE35: 100 | BF35: =BC35*BE35 | BG35: 1 | BH35: Nos | BI35: 100 | BJ35: =BG35*BI35 | BK35: 100 | BM35: 31 | BN35: Indicator | BO35: 1 | BP35: Nos | BQ35: 100 | BR35: =BO35*BQ35 | BS35: 2 | BT35: Nos | BU35: 100 | BV35: =BS35*BU35 | BW35: 1 | BX35: Nos | BY35: 100 | BZ35: =BW35*BY35 | CA35: 100 | CC35: 31 | CD35: Indicator | CE35: 1 | CF35: Nos | CG35: 100 | CH35: =CE35*CG35 | CI35: 2 | CJ35: Nos | CK35: 100 | CL35: =CI35*CK35 | CM35: 1 | CN35: Nos | CO35: 100 | CP35: =CM35*CO35 | CQ35: 100 | CS35: 31 | CT35: Indicator | CU35: 1 | CV35: Nos | CW35: 100 | CX35: =CU35*CW35 | CY35: 2 | CZ35: Nos | DA35: 100 | DB35: =CY35*DA35 | DC35: 1 | DD35: Nos | DE35: 100 | DF35: =DC35*DE35 | DG35: =DF35-CP35 | DH35: 31 | DI35: Indicator | DJ35: 1 | DK35: Nos | DL35: 100 | DM35: =DJ35*DL35 | DN35: 2 | DO35: Nos | DP35: 100 | DQ35: =DN35*DP35 | DR35: 1 | DS35: Nos | DT35: 100 | DU35: =DR35*DT35 | DV35: 100 | DX35: 31 | DY35: Indicator | DZ35: 1 | EA35: Nos | EB35: 100 | EC35: =DZ35*EB35 | ED35: 2 | EE35: Nos | EF35: 100 | EG35: =ED35*EF35 | EH35: 1 | EI35: Nos | EJ35: 100 | EK35: =EH35*EJ35 | EL35: 100 | EN35: 31 | EO35: Indicator | EP35: 1 | EQ35: Nos | ER35: 100 | ES35: =EP35*ER35 | ET35: 2 | EU35: Nos | EV35: 100 | EW35: =ET35*EV35 | EX35: 1 | EY35: Nos | EZ35: 100 | FA35: =EX35*EZ35 | FB35: 100
A36: 32 | B36: Connecting Plate | C36: 1 | D36: Nos | E36: 150 | F36: =C36*E36 | G36: 2 | H36: Nos | I36: 100 | J36: =G36*I36 | K36: 1 | L36: Nos | M36: 100 | N36: =K36*M36 | O36: 100 | Q36: 32 | R36: Thimble | S36: 9 | T36: Nos | U36: 7 | V36: =S36*U36 | W36: 18 | X36: Nos | Y36: 7 | Z36: =W36*Y36 | AA36: 9 | AB36: Nos | AC36: 7 | AD36: =AA36*AC36 | AE36: 7 | AG36: 32 | AH36: Connecting Plate | AI36: 1 | AJ36: Nos | AK36: 150 | AL36: =AI36*AK36 | AM36: 2 | AN36: Nos | AO36: 100 | AP36: =AM36*AO36 | AQ36: 1 | AR36: Nos | AS36: 100 | AT36: =AQ36*AS36 | AU36: 100 | AW36: 32 | AX36: Connecting Plate | AY36: 1 | AZ36: Nos | BA36: 150 | BB36: =AY36*BA36 | BC36: 2 | BD36: Nos | BE36: 100 | BF36: =BC36*BE36 | BG36: 1 | BH36: Nos | BI36: 100 | BJ36: =BG36*BI36 | BK36: 100 | BM36: 32 | BN36: Connecting Plate | BO36: 1 | BP36: Nos | BQ36: 150 | BR36: =BO36*BQ36 | BS36: 2 | BT36: Nos | BU36: 100 | BV36: =BS36*BU36 | BW36: 1 | BX36: Nos | BY36: 100 | BZ36: =BW36*BY36 | CA36: 100 | CC36: 32 | CD36: Connecting Plate | CE36: 1 | CF36: Nos | CG36: 150 | CH36: =CE36*CG36 | CI36: 2 | CJ36: Nos | CK36: 100 | CL36: =CI36*CK36 | CM36: 1 | CN36: Nos | CO36: 100 | CP36: =CM36*CO36 | CQ36: 100 | CS36: 32 | CT36: Connecting Plate | CU36: 1 | CV36: Nos | CW36: 150 | CX36: =CU36*CW36 | CY36: 2 | CZ36: Nos | DA36: 100 | DB36: =CY36*DA36 | DC36: 1 | DD36: Nos | DE36: 100 | DF36: =DC36*DE36 | DG36: =DF36-CP36 | DH36: 32 | DI36: Connecting Plate | DJ36: 1 | DK36: Nos | DL36: 150 | DM36: =DJ36*DL36 | DN36: 2 | DO36: Nos | DP36: 100 | DQ36: =DN36*DP36 | DR36: 1 | DS36: Nos | DT36: 100 | DU36: =DR36*DT36 | DV36: 100 | DX36: 32 | DY36: Connecting Plate | DZ36: 1 | EA36: Nos | EB36: 150 | EC36: =DZ36*EB36 | ED36: 2 | EE36: Nos | EF36: 100 | EG36: =ED36*EF36 | EH36: 1 | EI36: Nos | EJ36: 100 | EK36: =EH36*EJ36 | EL36: 100 | EN36: 32 | EO36: Connecting Plate | EP36: 1 | EQ36: Nos | ER36: 150 | ES36: =EP36*ER36 | ET36: 2 | EU36: Nos | EV36: 100 | EW36: =ET36*EV36 | EX36: 1 | EY36: Nos | EZ36: 100 | FA36: =EX36*EZ36 | FB36: 100
A37: 33 | B37: Thimble | C37: 9 | D37: Nos | E37: 7 | F37: =C37*E37 | G37: 18 | H37: Nos | I37: 7 | J37: =G37*I37 | K37: 9 | L37: Nos | M37: 7 | N37: =K37*M37 | O37: 7 | Q37: 33 | R37: Glass Wire | S37: 1 | T37: Mtr | U37: 100 | V37: =S37*U37 | W37: 2 | X37: Mtr. | Y37: 100 | Z37: =W37*Y37 | AA37: 1 | AB37: Mtr | AC37: 100 | AD37: =AA37*AC37 | AE37: 100 | AG37: 33 | AH37: Thimble | AI37: 27 | AJ37: Nos | AK37: 7 | AL37: =AI37*AK37 | AM37: 54 | AN37: Nos | AO37: 7 | AP37: =AM37*AO37 | AQ37: 27 | AR37: Nos | AS37: 7 | AT37: =AQ37*AS37 | AU37: 7 | AW37: 33 | AX37: Thimble | AY37: 27 | AZ37: Nos | BA37: 7 | BB37: =AY37*BA37 | BC37: 54 | BD37: Nos | BE37: 7 | BF37: =BC37*BE37 | BG37: 27 | BH37: Nos | BI37: 7 | BJ37: =BG37*BI37 | BK37: 7 | BM37: 33 | BN37: Thimble | BO37: 36 | BP37: Nos | BQ37: 7 | BR37: =BO37*BQ37 | BS37: 72 | BT37: Nos | BU37: 7 | BV37: =BS37*BU37 | BW37: 36 | BX37: Nos | BY37: 7 | BZ37: =BW37*BY37 | CA37: 7 | CC37: 33 | CD37: Thimble | CE37: 45 | CF37: Nos | CG37: 7 | CH37: =CE37*CG37 | CI37: 90 | CJ37: Nos | CK37: 7 | CL37: =CI37*CK37 | CM37: 45 | CN37: Nos | CO37: 7 | CP37: =CM37*CO37 | CQ37: 7 | CS37: 33 | CT37: Thimble | CU37: 45 | CV37: Nos | CW37: 7 | CX37: =CU37*CW37 | CY37: 90 | CZ37: Nos | DA37: 7 | DB37: =CY37*DA37 | DC37: 45 | DD37: Nos | DE37: 7 | DF37: =DC37*DE37 | DG37: =DF37-CP37 | DH37: 33 | DI37: Thimble | DJ37: 45 | DK37: Nos | DL37: 7 | DM37: =DJ37*DL37 | DN37: 90 | DO37: Nos | DP37: 7 | DQ37: =DN37*DP37 | DR37: 45 | DS37: Nos | DT37: 7 | DU37: =DR37*DT37 | DV37: 7 | DX37: 33 | DY37: Thimble | DZ37: 45 | EA37: Nos | EB37: 7 | EC37: =DZ37*EB37 | ED37: 90 | EE37: Nos | EF37: 7 | EG37: =ED37*EF37 | EH37: 45 | EI37: Nos | EJ37: 7 | EK37: =EH37*EJ37 | EL37: 7 | EN37: 33 | EO37: Thimble | EP37: 63 | EQ37: Nos | ER37: 7 | ES37: =EP37*ER37 | ET37: 126 | EU37: Nos | EV37: 7 | EW37: =ET37*EV37 | EX37: 63 | EY37: Nos | EZ37: 7 | FA37: =EX37*EZ37 | FB37: 7
A38: 34 | B38: Glass Wire | C38: 1 | D38: Mtr | E38: 100 | F38: =C38*E38 | G38: 2 | H38: Mtr. | I38: 100 | J38: =G38*I38 | K38: 1 | L38: Mtr | M38: 100 | N38: =K38*M38 | O38: 100 | Q38: 34 | R38: Cross Tee | S38: n/a | W38: 1 | X38: nos | Y38: 200 | Z38: =W38*Y38 | AA38: n/a | AG38: 34 | AH38: Glass Wire | AI38: 2 | AJ38: Mtr | AK38: 100 | AL38: =AI38*AK38 | AM38: 4 | AN38: Mtr. | AO38: 100 | AP38: =AM38*AO38 | AQ38: 2 | AR38: Mtr | AS38: 100 | AT38: =AQ38*AS38 | AU38: 100 | AW38: 34 | AX38: Glass Wire | AY38: 2 | AZ38: Mtr | BA38: 100 | BB38: =AY38*BA38 | BC38: 4 | BD38: Mtr. | BE38: 100 | BF38: =BC38*BE38 | BG38: 2 | BH38: Mtr | BI38: 100 | BJ38: =BG38*BI38 | BK38: 100 | BM38: 34 | BN38: Glass Wire | BO38: 3 | BP38: Mtr | BQ38: 100 | BR38: =BO38*BQ38 | BS38: 6 | BT38: Mtr. | BU38: 100 | BV38: =BS38*BU38 | BW38: 3 | BX38: Mtr | BY38: 100 | BZ38: =BW38*BY38 | CA38: 100 | CC38: 34 | CD38: Glass Wire | CE38: 3.5 | CF38: Mtr | CG38: 100 | CH38: =CE38*CG38 | CI38: 7 | CJ38: Mtr. | CK38: 100 | CL38: =CI38*CK38 | CM38: 3.5 | CN38: Mtr | CO38: 100 | CP38: =CM38*CO38 | CQ38: 100 | CS38: 34 | CT38: Glass Wire | CU38: 3.5 | CV38: Mtr | CW38: 100 | CX38: =CU38*CW38 | CY38: 7 | CZ38: Mtr. | DA38: 100 | DB38: =CY38*DA38 | DC38: 3.5 | DD38: Mtr | DE38: 100 | DF38: =DC38*DE38 | DG38: =DF38-CP38 | DH38: 34 | DI38: Glass Wire | DJ38: 4 | DK38: Mtr | DL38: 100 | DM38: =DJ38*DL38 | DN38: 8 | DO38: Mtr. | DP38: 100 | DQ38: =DN38*DP38 | DR38: 4 | DS38: Mtr | DT38: 100 | DU38: =DR38*DT38 | DV38: 100 | DX38: 34 | DY38: Glass Wire | DZ38: 4 | EA38: Mtr | EB38: 80 | EC38: =DZ38*EB38 | ED38: 8 | EE38: Mtr. | EF38: 80 | EG38: =ED38*EF38 | EH38: 4 | EI38: Mtr | EJ38: 80 | EK38: =EH38*EJ38 | EL38: 80 | EN38: 34 | EO38: Glass Wire | EP38: 5 | EQ38: Mtr | ER38: 100 | ES38: =EP38*ER38 | ET38: 10 | EU38: Mtr. | EV38: 100 | EW38: =ET38*EV38 | EX38: 5 | EY38: Mtr | EZ38: 100 | FA38: =EX38*EZ38 | FB38: 100
A39: 35 | B39: Cross Tee | C39: n/a | G39: 1 | H39: nos | I39: 150 | J39: =G39*I39 | K39: n/a | Q39: 35 | R39: Star Coupling L -95 | S39: 2 | T39: Nos | U39: 300 | V39: =S39*U39 | W39: 2 | X39: Nos | Y39: 300 | Z39: =W39*Y39 | AA39: 1 | AB39: Nos | AC39: 300 | AD39: =AA39*AC39 | AE39: 300 | AG39: 35 | AH39: Cross Tee | AI39: n/a | AL39: 0 | AM39: 1 | AN39: nos | AO39: 200 | AP39: =AM39*AO39 | AQ39: n/a | AT39: 0 | AW39: 35 | AX39: Cross Tee | AY39: n/a | BB39: 0 | BC39: 1 | BD39: nos | BE39: 200 | BF39: =BC39*BE39 | BG39: n/a | BJ39: 0 | BM39: 35 | BN39: Cross Tee | BO39: n/a | BR39: 0 | BS39: 1 | BT39: nos | BU39: 200 | BV39: =BS39*BU39 | BW39: n/a | BZ39: 0 | CC39: 35 | CD39: Cross Tee | CE39: n/a | CH39: 0 | CI39: 1 | CJ39: nos | CK39: 200 | CL39: =CI39*CK39 | CM39: n/a | CP39: 0 | CS39: 35 | CT39: Cross Tee | CU39: n/a | CX39: 0 | CY39: 1 | CZ39: nos | DA39: 200 | DB39: =CY39*DA39 | DC39: n/a | DF39: 0 | DG39: =DF39-CP39 | DH39: 35 | DI39: Cross Tee 1'' | DJ39: n/a | DM39: 0 | DN39: 1 | DO39: nos | DP39: 250 | DQ39: =DN39*DP39 | DR39: n/a | DU39: 0 | DX39: 35 | DY39: Cross Tee 1'' | DZ39: n/a | EC39: 0 | ED39: 1 | EE39: nos | EF39: 250 | EG39: =ED39*EF39 | EH39: n/a | EK39: 0 | EN39: 35 | EO39: Cross Tee 1'' | EP39: n/a | ET39: 1 | EU39: nos | EV39: 250 | EW39: =ET39*EV39 | EX39: n/a
A40: 36 | B40: Star Coupling L -95 | C40: 2 | D40: Nos | E40: 300 | F40: =C40*E40 | G40: 2 | H40: Nos | I40: 300 | J40: =G40*I40 | K40: 1 | L40: Nos | M40: 300 | N40: =K40*M40 | O40: 300 | Q40: 36 | R40: Teflon Tape 3/4" | S40: 5 | T40: Nos | U40: 36 | V40: =S40*U40 | W40: 6 | X40: Nos | Y40: 36 | Z40: =W40*Y40 | AA40: 5 | AB40: Nos | AC40: 36 | AD40: =AA40*AC40 | AE40: 36 | AG40: 36 | AH40: Star Coupling L -95 | AI40: 2 | AJ40: Nos | AK40: 300 | AL40: =AI40*AK40 | AM40: 2 | AN40: Nos | AO40: 300 | AP40: =AM40*AO40 | AQ40: 1 | AR40: Nos | AS40: 300 | AT40: =AQ40*AS40 | AU40: 300 | AW40: 36 | AX40: Star Coupling L -95 | AY40: 2 | AZ40: Nos | BA40: 300 | BB40: =AY40*BA40 | BC40: 2 | BD40: Nos | BE40: 300 | BF40: =BC40*BE40 | BG40: 1 | BH40: Nos | BI40: 300 | BJ40: =BG40*BI40 | BK40: 300 | BM40: 36 | BN40: Star Coupling L -95 | BO40: 2 | BP40: Nos | BQ40: 300 | BR40: =BO40*BQ40 | BS40: 2 | BT40: Nos | BU40: 300 | BV40: =BS40*BU40 | BW40: 1 | BX40: Nos | BY40: 300 | BZ40: =BW40*BY40 | CA40: 300 | CC40: 36 | CD40: Star Coupling L -95 | CE40: 2 | CF40: Nos | CG40: 300 | CH40: =CE40*CG40 | CI40: 2 | CJ40: Nos | CK40: 300 | CL40: =CI40*CK40 | CM40: 1 | CN40: Nos | CO40: 300 | CP40: =CM40*CO40 | CQ40: 300 | CS40: 36 | CT40: Star Coupling L -95 | CU40: 2 | CV40: Nos | CW40: 300 | CX40: =CU40*CW40 | CY40: 2 | CZ40: Nos | DA40: 300 | DB40: =CY40*DA40 | DC40: 1 | DD40: Nos | DE40: 300 | DF40: =DC40*DE40 | DG40: =DF40-CP40 | DH40: 36 | DI40: Star Coupling L - 110 | DJ40: 2 | DK40: Nos | DL40: 800 | DM40: =DJ40*DL40 | DN40: 2 | DO40: Nos | DP40: 600 | DQ40: =DN40*DP40 | DR40: 1 | DS40: Nos | DT40: 600 | DU40: =DR40*DT40 | DV40: 600 | DX40: 36 | DY40: Star Coupling L - 110 | DZ40: 2 | EA40: Nos | EB40: 800 | EC40: =DZ40*EB40 | ED40: 2 | EE40: Nos | EF40: 600 | EG40: =ED40*EF40 | EH40: 1 | EI40: Nos | EJ40: 600 | EK40: =EH40*EJ40 | EL40: 600 | EN40: 36 | EO40: Star Coupling L - 110 | EP40: 2 | EQ40: Nos | ER40: 800 | ES40: =EP40*ER40 | ET40: 2 | EU40: Nos | EV40: 600 | EW40: =ET40*EV40 | EX40: 1 | EY40: Nos | EZ40: 600 | FA40: =EX40*EZ40 | FB40: 600
A41: 37 | B41: Teflon Tape 3/4" | C41: 5 | D41: Nos | E41: 37 | F41: =C41*E41 | G41: 6 | H41: Nos | I41: 37 | J41: =G41*I41 | K41: 5 | L41: Nos | M41: 37 | N41: =K41*M41 | O41: 37 | Q41: 37 | R41: Nut / Bolt 3/8x1/2'',5/16x1/2'' | S41: 2 | T41: kg | U41: 100 | V41: =S41*U41 | W41: 1.5 | X41: kg | Y41: 100 | Z41: =W41*Y41 | AA41: 2 | AB41: kg | AC41: 100 | AD41: =AA41*AC41 | AE41: 100 | AG41: 37 | AH41: Teflon Tape 3/4" | AI41: 5 | AJ41: Nos | AK41: 36 | AL41: =AI41*AK41 | AM41: 6 | AN41: Nos | AO41: 36 | AP41: =AM41*AO41 | AQ41: 5 | AR41: Nos | AS41: 36 | AT41: =AQ41*AS41 | AU41: 36 | AW41: 37 | AX41: Teflon Tape 3/4" | AY41: 5 | AZ41: Nos | BA41: 36 | BB41: =AY41*BA41 | BC41: 6 | BD41: Nos | BE41: 36 | BF41: =BC41*BE41 | BG41: 5 | BH41: Nos | BI41: 36 | BJ41: =BG41*BI41 | BK41: 36 | BM41: 37 | BN41: Teflon Tape 3/4" | BO41: 5 | BP41: Nos | BQ41: 36 | BR41: =BO41*BQ41 | BS41: 6 | BT41: Nos | BU41: 36 | BV41: =BS41*BU41 | BW41: 5 | BX41: Nos | BY41: 36 | BZ41: =BW41*BY41 | CA41: 36 | CC41: 37 | CD41: Teflon Tape 3/4" | CE41: 5 | CF41: Nos | CG41: 36 | CH41: =CE41*CG41 | CI41: 6 | CJ41: Nos | CK41: 36 | CL41: =CI41*CK41 | CM41: 5 | CN41: Nos | CO41: 36 | CP41: =CM41*CO41 | CQ41: 36 | CS41: 37 | CT41: Teflon Tape 3/4" | CU41: 5 | CV41: Nos | CW41: 36 | CX41: =CU41*CW41 | CY41: 6 | CZ41: Nos | DA41: 36 | DB41: =CY41*DA41 | DC41: 5 | DD41: Nos | DE41: 36 | DF41: =DC41*DE41 | DG41: =DF41-CP41 | DH41: 37 | DI41: Teflon Tape 3/4" | DJ41: 5 | DK41: Nos | DL41: 36 | DM41: =DJ41*DL41 | DN41: 6 | DO41: Nos | DP41: 36 | DQ41: =DN41*DP41 | DR41: 5 | DS41: Nos | DT41: 36 | DU41: =DR41*DT41 | DV41: 36 | DX41: 37 | DY41: Teflon Tape 3/4" | DZ41: 5 | EA41: Nos | EB41: 36 | EC41: =DZ41*EB41 | ED41: 6 | EE41: Nos | EF41: 36 | EG41: =ED41*EF41 | EH41: 5 | EI41: Nos | EJ41: 36 | EK41: =EH41*EJ41 | EL41: 36 | EN41: 37 | EO41: Teflon Tape 3/4" | EP41: 5 | EQ41: Nos | ER41: 36 | ES41: =EP41*ER41 | ET41: 6 | EU41: Nos | EV41: 36 | EW41: =ET41*EV41 | EX41: 5 | EY41: Nos | EZ41: 36 | FA41: =EX41*EZ41 | FB41: 36
A42: 38 | B42: Nut / Bolt 3/8x1/2'',5/16x1/2'' | C42: 2 | D42: kg | E42: 100 | F42: =C42*E42 | G42: 1.5 | H42: kg | I42: 100 | J42: =G42*I42 | K42: 2 | L42: kg | M42: 100 | N42: =K42*M42 | O42: 100 | Q42: 38 | R42: Red Oxide | S42: 1 | T42: Ltr. | U42: 150 | V42: =S42*U42 | W42: 1 | X42: Ltr. | Y42: 150 | Z42: =W42*Y42 | AA42: 1 | AB42: Ltr. | AC42: 150 | AD42: =AA42*AC42 | AE42: 150 | AG42: 38 | AH42: Nut / Bolt 3/8x1/2'',5/16x1/2'' | AI42: 2 | AJ42: kg | AK42: 100 | AL42: =AI42*AK42 | AM42: 1.5 | AN42: kg | AO42: 100 | AP42: =AM42*AO42 | AQ42: 2 | AR42: kg | AS42: 100 | AT42: =AQ42*AS42 | AU42: 100 | AW42: 38 | AX42: Nut / Bolt 3/8x1/2'',5/16x1/2'' | AY42: 2 | AZ42: kg | BA42: 100 | BB42: =AY42*BA42 | BC42: 1.5 | BD42: kg | BE42: 100 | BF42: =BC42*BE42 | BG42: 2 | BH42: kg | BI42: 100 | BJ42: =BG42*BI42 | BK42: 100 | BM42: 38 | BN42: Nut / Bolt 3/8x1/2'',5/16x1/2'' | BO42: 2 | BP42: kg | BQ42: 100 | BR42: =BO42*BQ42 | BS42: 1.5 | BT42: kg | BU42: 100 | BV42: =BS42*BU42 | BW42: 2 | BX42: kg | BY42: 80 | BZ42: =BW42*BY42 | CA42: 100 | CC42: 38 | CD42: Nut / Bolt 3/8x1/2'',5/16x1/2'' | CE42: 2 | CF42: kg | CG42: 100 | CH42: =CE42*CG42 | CI42: 1.5 | CJ42: kg | CK42: 100 | CL42: =CI42*CK42 | CM42: 2 | CN42: kg | CO42: 100 | CP42: =CM42*CO42 | CQ42: 100 | CS42: 38 | CT42: Nut / Bolt 3/8x1/2'',5/16x1/2'' | CU42: 2 | CV42: kg | CW42: 100 | CX42: =CU42*CW42 | CY42: 1.5 | CZ42: kg | DA42: 100 | DB42: =CY42*DA42 | DC42: 2 | DD42: kg | DE42: 100 | DF42: =DC42*DE42 | DG42: =DF42-CP42 | DH42: 38 | DI42: Nut / Bolt 1/2x 2 '',5/16x1/2'' | DJ42: 3.5 | DK42: kg | DL42: 100 | DM42: =DJ42*DL42 | DN42: 3.5 | DO42: kg | DP42: 100 | DQ42: =DN42*DP42 | DR42: 3.5 | DS42: kg | DT42: 100 | DU42: =DR42*DT42 | DV42: 100 | DX42: 38 | DY42: Nut / Bolt 1/2x 2 '',5/16x1/2'' | DZ42: 3.5 | EA42: kg | EB42: 100 | EC42: =DZ42*EB42 | ED42: 3.5 | EE42: kg | EF42: 100 | EG42: =ED42*EF42 | EH42: 3.5 | EI42: kg | EJ42: 100 | EK42: =EH42*EJ42 | EL42: 100 | EN42: 38 | EO42: Nut / Bolt 1/2x 2 '',5/16x1/2'' | EP42: 3.5 | EQ42: kg | ER42: 100 | ES42: =EP42*ER42 | ET42: 3.5 | EU42: kg | EV42: 100 | EW42: =ET42*EV42 | EX42: 3.5 | EY42: kg | EZ42: 100 | FA42: =EX42*EZ42 | FB42: 100
A43: 39 | B43: Red Oxide | C43: 1 | D43: Ltr. | E43: 150 | F43: =C43*E43 | G43: 1 | H43: Ltr. | I43: 150 | J43: =G43*I43 | K43: 1 | L43: Ltr. | M43: 150 | N43: =K43*M43 | O43: 150 | Q43: 39 | R43: Hammer Ton Deep Blue | S43: 0.5 | T43: g | U43: 250 | V43: =S43*U43 | W43: 1 | X43: Ltr. | Y43: 250 | Z43: =W43*Y43 | AA43: 0.5 | AB43: g | AC43: 250 | AD43: =AA43*AC43 | AE43: 250 | AG43: 39 | AH43: Red Oxide | AI43: 1 | AJ43: Ltr. | AK43: 150 | AL43: =AI43*AK43 | AM43: 1 | AN43: Ltr. | AO43: 150 | AP43: =AM43*AO43 | AQ43: 1 | AR43: Ltr. | AS43: 150 | AT43: =AQ43*AS43 | AU43: 150 | AW43: 39 | AX43: Red Oxide | AY43: 1 | AZ43: Ltr. | BA43: 150 | BB43: =AY43*BA43 | BC43: 1 | BD43: Ltr. | BE43: 150 | BF43: =BC43*BE43 | BG43: 1 | BH43: Ltr. | BI43: 150 | BJ43: =BG43*BI43 | BK43: 150 | BM43: 39 | BN43: Red Oxide | BO43: 1 | BP43: Ltr. | BQ43: 150 | BR43: =BO43*BQ43 | BS43: 1 | BT43: Ltr. | BU43: 150 | BV43: =BS43*BU43 | BW43: 1 | BX43: Ltr. | BY43: 150 | BZ43: =BW43*BY43 | CA43: 150 | CC43: 39 | CD43: Red Oxide | CE43: 1 | CF43: Ltr. | CG43: 150 | CH43: =CE43*CG43 | CI43: 1 | CJ43: Ltr. | CK43: 150 | CL43: =CI43*CK43 | CM43: 1 | CN43: Ltr. | CO43: 150 | CP43: =CM43*CO43 | CQ43: 150 | CS43: 39 | CT43: Red Oxide | CU43: 1 | CV43: Ltr. | CW43: 150 | CX43: =CU43*CW43 | CY43: 1 | CZ43: Ltr. | DA43: 150 | DB43: =CY43*DA43 | DC43: 1 | DD43: Ltr. | DE43: 150 | DF43: =DC43*DE43 | DG43: =DF43-CP43 | DH43: 39 | DI43: Red Oxide | DJ43: 2 | DK43: Ltr. | DL43: 150 | DM43: =DJ43*DL43 | DN43: 2 | DO43: Ltr. | DP43: 150 | DQ43: =DN43*DP43 | DR43: 2 | DS43: Ltr. | DT43: 150 | DU43: =DR43*DT43 | DV43: 150 | DX43: 39 | DY43: Red Oxide | DZ43: 2 | EA43: Ltr. | EB43: 150 | EC43: =DZ43*EB43 | ED43: 2 | EE43: Ltr. | EF43: 150 | EG43: =ED43*EF43 | EH43: 2 | EI43: Ltr. | EJ43: 150 | EK43: =EH43*EJ43 | EL43: 150 | EN43: 39 | EO43: Red Oxide | EP43: 2 | EQ43: Ltr. | ER43: 150 | ES43: =EP43*ER43 | ET43: 2 | EU43: Ltr. | EV43: 150 | EW43: =ET43*EV43 | EX43: 2 | EY43: Ltr. | EZ43: 150 | FA43: =EX43*EZ43 | FB43: 150
A44: 40 | B44: Hammer Ton Deep Blue | C44: 0.5 | D44: g | E44: 250 | F44: =C44*E44 | G44: 1 | H44: Ltr. | I44: 180 | J44: =G44*I44 | K44: 0.5 | L44: g | M44: 200 | N44: =K44*M44 | O44: 250 | Q44: 40 | R44: Alluminium Paint | S44: 1 | T44: Ltr. | U44: 350 | V44: =S44*U44 | W44: 1 | X44: Ltr. | Y44: 280 | Z44: =W44*Y44 | AA44: 1 | AB44: Ltr. | AC44: 280 | AD44: =AA44*AC44 | AE44: 280 | AG44: 40 | AH44: Hammer Ton Deep Blue | AI44: 0.5 | AJ44: g | AK44: 250 | AL44: =AI44*AK44 | AM44: 1 | AN44: Ltr. | AO44: 250 | AP44: =AM44*AO44 | AQ44: 0.5 | AR44: g | AS44: 250 | AT44: =AQ44*AS44 | AU44: 250 | AW44: 40 | AX44: Hammer Ton Deep Blue | AY44: 0.5 | AZ44: g | BA44: 250 | BB44: =AY44*BA44 | BC44: 1 | BD44: Ltr. | BE44: 250 | BF44: =BC44*BE44 | BG44: 0.5 | BH44: g | BI44: 250 | BJ44: =BG44*BI44 | BK44: 250 | BM44: 40 | BN44: Hammer Ton Deep Blue | BO44: 0.5 | BP44: g | BQ44: 250 | BR44: =BO44*BQ44 | BS44: 1 | BT44: Ltr. | BU44: 250 | BV44: =BS44*BU44 | BW44: 0.5 | BX44: g | BY44: 250 | BZ44: =BW44*BY44 | CA44: 250 | CC44: 40 | CD44: Hammer Ton Deep Blue | CE44: 0.5 | CF44: g | CG44: 250 | CH44: =CE44*CG44 | CI44: 1 | CJ44: Ltr. | CK44: 250 | CL44: =CI44*CK44 | CM44: 0.5 | CN44: g | CO44: 250 | CP44: =CM44*CO44 | CQ44: 250 | CS44: 40 | CT44: Hammer Ton Deep Blue | CU44: 0.5 | CV44: g | CW44: 250 | CX44: =CU44*CW44 | CY44: 1 | CZ44: Ltr. | DA44: 250 | DB44: =CY44*DA44 | DC44: 0.5 | DD44: g | DE44: 250 | DF44: =DC44*DE44 | DG44: =DF44-CP44 | DH44: 40 | DI44: Hammer Ton Deep Blue | DJ44: 1 | DK44: Kg | DL44: 250 | DM44: =DJ44*DL44 | DN44: 1 | DO44: Ltr. | DP44: 250 | DQ44: =DN44*DP44 | DR44: 1 | DS44: Kg | DT44: 250 | DU44: =DR44*DT44 | DV44: 250 | DX44: 40 | DY44: Hammer Ton Deep Blue | DZ44: 1 | EA44: Kg | EB44: 250 | EC44: =DZ44*EB44 | ED44: 1 | EE44: Ltr. | EF44: 250 | EG44: =ED44*EF44 | EH44: 1 | EI44: Kg | EJ44: 250 | EK44: =EH44*EJ44 | EL44: 250 | EN44: 40 | EO44: Hammer Ton Deep Blue | EP44: 1 | EQ44: Kg | ER44: 250 | ES44: =EP44*ER44 | ET44: 1 | EU44: Ltr. | EV44: 250 | EW44: =ET44*EV44 | EX44: 1 | EY44: Kg | EZ44: 250 | FA44: =EX44*EZ44 | FB44: 250
A45: 41 | B45: Alluminium Paint | C45: 1 | D45: Ltr. | E45: 350 | F45: =C45*E45 | G45: 1 | H45: Ltr. | I45: 280 | J45: =G45*I45 | K45: 1 | L45: Ltr. | M45: 280 | N45: =K45*M45 | O45: 280 | Q45: 41 | R45: Gurb Screw | S45: 2 | T45: Nos | U45: 5 | V45: =S45*U45 | W45: 2 | X45: Nos | Y45: 5 | Z45: =W45*Y45 | AA45: 2 | AB45: Nos | AC45: 5 | AD45: =AA45*AC45 | AE45: 5 | AG45: 41 | AH45: Alluminium Paint | AI45: 1 | AJ45: Ltr. | AK45: 350 | AL45: =AI45*AK45 | AM45: 1 | AN45: Ltr. | AO45: 250 | AP45: 280 | AQ45: 1 | AR45: Ltr. | AS45: 280 | AT45: =AQ45*AS45 | AU45: 280 | AW45: 41 | AX45: Alluminium Paint | AY45: 1 | AZ45: Ltr. | BA45: 350 | BB45: =AY45*BA45 | BC45: 1 | BD45: Ltr. | BE45: 280 | BF45: =BC45*BE45 | BG45: 1 | BH45: Ltr. | BI45: 280 | BJ45: =BG45*BI45 | BK45: 280 | BM45: 41 | BN45: Alluminium Paint | BO45: 1 | BP45: Ltr. | BQ45: 350 | BR45: =BO45*BQ45 | BS45: 1 | BT45: Ltr. | BU45: 250 | BV45: 280 | BW45: 1 | BX45: Ltr. | BY45: 280 | BZ45: =BW45*BY45 | CA45: 280 | CC45: 41 | CD45: Alluminium Paint | CE45: 1 | CF45: Ltr. | CG45: 350 | CH45: =CE45*CG45 | CI45: 1 | CJ45: Ltr. | CK45: 280 | CL45: =CI45*CK45 | CM45: 1 | CN45: Ltr. | CO45: 280 | CP45: =CM45*CO45 | CQ45: 280 | CS45: 41 | CT45: Alluminium Paint | CU45: 1 | CV45: Ltr. | CW45: 350 | CX45: =CU45*CW45 | CY45: 1 | CZ45: Ltr. | DA45: 280 | DB45: =CY45*DA45 | DC45: 1 | DD45: Ltr. | DE45: 280 | DF45: =DC45*DE45 | DG45: =DF45-CP45 | DH45: 41 | DI45: Alluminium Paint | DJ45: 2 | DK45: Ltr. | DL45: 350 | DM45: =DJ45*DL45 | DN45: 2 | DO45: Ltr. | DP45: 280 | DQ45: =DN45*DP45 | DR45: 2 | DS45: Ltr. | DT45: 280 | DU45: =DR45*DT45 | DV45: 280 | DX45: 41 | DY45: Alluminium Paint | DZ45: 2 | EA45: Ltr. | EB45: 350 | EC45: =DZ45*EB45 | ED45: 2 | EE45: Ltr. | EF45: 280 | EG45: =ED45*EF45 | EH45: 2 | EI45: Ltr. | EJ45: 280 | EK45: =EH45*EJ45 | EL45: 280 | EN45: 41 | EO45: Alluminium Paint | EP45: 2 | EQ45: Ltr. | ER45: 350 | ES45: =EP45*ER45 | ET45: 2 | EU45: Ltr. | EV45: 280 | EW45: =ET45*EV45 | EX45: 2 | EY45: Ltr. | EZ45: 280 | FA45: =EX45*EZ45 | FB45: 280
A46: 42 | B46: Gurb Screw | C46: 2 | D46: Nos | E46: 5 | F46: =C46*E46 | G46: 2 | H46: Nos | I46: 5 | J46: =G46*I46 | K46: 2 | L46: Nos | M46: 5 | N46: =K46*M46 | O46: 5 | Q46: 42 | R46: Gaskit (300x300x3 mm) | S46: 2 | T46: kg | U46: 120 | V46: =S46*U46 | W46: 2 | X46: kg | Y46: 120 | Z46: =W46*Y46 | AA46: 2 | AB46: kg | AC46: 120 | AD46: =AA46*AC46 | AE46: 120 | AG46: 42 | AH46: Gurb Screw | AI46: 2 | AJ46: Nos | AK46: 5 | AL46: =AI46*AK46 | AM46: 2 | AN46: Nos | AO46: 5 | AP46: =AM46*AO46 | AQ46: 2 | AR46: Nos | AS46: 5 | AT46: =AQ46*AS46 | AU46: 5 | AW46: 42 | AX46: Gurb Screw | AY46: 2 | AZ46: Nos | BA46: 5 | BB46: =AY46*BA46 | BC46: 2 | BD46: Nos | BE46: 5 | BF46: =BC46*BE46 | BG46: 2 | BH46: Nos | BI46: 5 | BJ46: =BG46*BI46 | BK46: 5 | BM46: 42 | BN46: Gurb Screw | BO46: 2 | BP46: Nos | BQ46: 5 | BR46: =BO46*BQ46 | BS46: 2 | BT46: Nos | BU46: 5 | BV46: =BS46*BU46 | BW46: 2 | BX46: Nos | BY46: 5 | BZ46: =BW46*BY46 | CA46: 5 | CC46: 42 | CD46: Gurb Screw | CE46: 2 | CF46: Nos | CG46: 5 | CH46: =CE46*CG46 | CI46: 2 | CJ46: Nos | CK46: 5 | CL46: =CI46*CK46 | CM46: 2 | CN46: Nos | CO46: 5 | CP46: =CM46*CO46 | CQ46: 5 | CS46: 42 | CT46: Gurb Screw | CU46: 2 | CV46: Nos | CW46: 5 | CX46: =CU46*CW46 | CY46: 2 | CZ46: Nos | DA46: 5 | DB46: =CY46*DA46 | DC46: 2 | DD46: Nos | DE46: 5 | DF46: =DC46*DE46 | DG46: =DF46-CP46 | DH46: 42 | DI46: Gurb Screw | DJ46: 2 | DK46: Nos | DL46: 5 | DM46: =DJ46*DL46 | DN46: 2 | DO46: Nos | DP46: 5 | DQ46: =DN46*DP46 | DR46: 2 | DS46: Nos | DT46: 5 | DU46: =DR46*DT46 | DV46: 5 | DX46: 42 | DY46: Gurb Screw | DZ46: 2 | EA46: Nos | EB46: 5 | EC46: =DZ46*EB46 | ED46: 2 | EE46: Nos | EF46: 5 | EG46: =ED46*EF46 | EH46: 2 | EI46: Nos | EJ46: 5 | EK46: =EH46*EJ46 | EL46: 5 | EN46: 42 | EO46: Gurb Screw | EP46: 2 | EQ46: Nos | ER46: 5 | ES46: =EP46*ER46 | ET46: 2 | EU46: Nos | EV46: 5 | EW46: =ET46*EV46 | EX46: 2 | EY46: Nos | EZ46: 5 | FA46: =EX46*EZ46 | FB46: 5
A47: 43 | B47: Gaskit (300x300x3 mm) | C47: 2 | D47: kg | E47: 120 | F47: =C47*E47 | G47: 2 | H47: kg | I47: 120 | J47: =G47*I47 | K47: 2 | L47: kg | M47: 120 | N47: =K47*M47 | O47: 120 | Q47: 43 | R47: LABOUR CHARGE | V47: 8000 | Z47: 8000 | AD47: 8000 | AG47: 43 | AH47: Gaskit (300x300x3 mm) | AI47: 2 | AJ47: kg | AK47: 120 | AL47: =AI47*AK47 | AM47: 2 | AN47: kg | AO47: 120 | AP47: =AM47*AO47 | AQ47: 2 | AR47: kg | AS47: 120 | AT47: =AQ47*AS47 | AU47: 120 | AW47: 43 | AX47: Gaskit (300x300x3 mm) | AY47: 2 | AZ47: kg | BA47: 120 | BB47: =AY47*BA47 | BC47: 2 | BD47: kg | BE47: 120 | BF47: =BC47*BE47 | BG47: 2 | BH47: kg | BI47: 120 | BJ47: =BG47*BI47 | BK47: 120 | BM47: 43 | BN47: Gaskit (300x300x3 mm) | BO47: 2 | BP47: kg | BQ47: 120 | BR47: =BO47*BQ47 | BS47: 2 | BT47: kg | BU47: 120 | BV47: =BS47*BU47 | BW47: 2 | BX47: kg | BY47: 120 | BZ47: =BW47*BY47 | CA47: 120 | CC47: 43 | CD47: Gaskit (300x300x3 mm) | CE47: 2 | CF47: kg | CG47: 120 | CH47: =CE47*CG47 | CI47: 2 | CJ47: kg | CK47: 120 | CL47: =CI47*CK47 | CM47: 2 | CN47: kg | CO47: 120 | CP47: =CM47*CO47 | CQ47: 120 | CS47: 43 | CT47: Gaskit (300x300x3 mm) | CU47: 2 | CV47: kg | CW47: 120 | CX47: =CU47*CW47 | CY47: 2 | CZ47: kg | DA47: 120 | DB47: =CY47*DA47 | DC47: 2 | DD47: kg | DE47: 120 | DF47: =DC47*DE47 | DG47: =DF47-CP47 | DH47: 43 | DI47: Gaskit (600x600x3 mm) | DJ47: 4 | DK47: kg | DL47: 120 | DM47: =DJ47*DL47 | DN47: 4 | DO47: kg | DP47: 120 | DQ47: =DN47*DP47 | DR47: 4 | DS47: kg | DT47: 120 | DU47: =DR47*DT47 | DV47: 120 | DX47: 43 | DY47: Gaskit (600x600x3 mm) | DZ47: 4 | EA47: kg | EB47: 120 | EC47: =DZ47*EB47 | ED47: 4 | EE47: kg | EF47: 120 | EG47: =ED47*EF47 | EH47: 4 | EI47: kg | EJ47: 120 | EK47: =EH47*EJ47 | EL47: 120 | EN47: 43 | EO47: Gaskit (700x700x3 mm) | EP47: 5 | EQ47: kg | ER47: 120 | ES47: =EP47*ER47 | ET47: 5 | EU47: kg | EV47: 120 | EW47: =ET47*EV47 | EX47: 5 | EY47: kg | EZ47: 120 | FA47: =EX47*EZ47 | FB47: 120
A48: 44 | B48: LABOUR CHARGE | F48: 8000 | J48: 8000 | N48: 8000 | R48: Total Amount | V48: =SUM(V5:V47) | Z48: =SUM(Z5:Z47) | AD48: =SUM(AD5:AD47) | AG48: 44 | AH48: LABOUR CHARGE | AL48: 8000 | AP48: 8000 | AT48: 8000 | AW48: 44 | AX48: LABOUR CHARGE | BB48: 8000 | BF48: 8000 | BJ48: 8000 | BM48: 44 | BN48: LABOUR CHARGE | BR48: 8000 | BV48: 8000 | BZ48: 8000 | CC48: 44 | CD48: LABOUR CHARGE | CH48: 8000 | CL48: 8000 | CP48: 8000 | CS48: 44 | CT48: LABOUR CHARGE | CX48: 8000 | DB48: 8000 | DF48: 8000 | DG48: =DF48-CP48 | DH48: 44 | DI48: LABOUR CHARGE | DM48: 8000 | DQ48: 8000 | DU48: 8000 | DX48: 44 | DY48: LABOUR CHARGE | EC48: 8000 | EG48: 8000 | EK48: 8000 | EN48: 44 | EO48: LABOUR CHARGE | ES48: 8000 | EW48: 8000 | FA48: 8000
B49: Total Amount | F49: =SUM(F5:F48) | J49: =SUM(J5:J48) | N49: =SUM(N5:N48) | AH49: Total Amount | AL49: =SUM(AL5:AL48) | AP49: =SUM(AP5:AP48) | AT49: =SUM(AT5:AT48) | AX49: Total Amount | BB49: =SUM(BB5:BB48) | BF49: =SUM(BF5:BF48) | BJ49: =SUM(BJ5:BJ48) | BN49: Total Amount | BR49: =SUM(BR5:BR48) | BV49: =SUM(BV5:BV48) | BZ49: =SUM(BZ5:BZ48) | CD49: Total Amount | CH49: =SUM(CH5:CH48) | CL49: =SUM(CL5:CL48) | CP49: =SUM(CP5:CP48) | CT49: Total Amount | CX49: =SUM(CX5:CX48) | DB49: =SUM(DB5:DB48) | DF49: =SUM(DF5:DF48) | DG49: =DF49-CP49 | DI49: Total Amount | DM49: =SUM(DM5:DM48) | DQ49: =SUM(DQ5:DQ48) | DU49: =SUM(DU5:DU48) | DY49: Total Amount | EC49: =SUM(EC5:EC48) | EG49: =SUM(EG5:EG48) | EK49: =SUM(EK5:EK48) | EO49: Total Amount | ES49: =SUM(ES5:ES48) | EW49: =SUM(EW5:EW48) | FA49: =SUM(FA5:FA48)
E52: 1.8 | F52: =F49*$E$52 | J52: =J49*$E$52 | N52: =N49*$E$52 | V52: =V48*$E$52 | Z52: =Z48*$E$52 | AD52: =AD48*$E$52 | AL52: =AL49*$E$52 | AP52: =AP49*$E$52 | AT52: =AT49*$E$52 | BB52: =BB49*$E$52 | BF52: =BF49*$E$52 | BJ52: =BJ49*$E$52 | BR52: =BR49*$E$52 | BV52: =BV49*$E$52 | BZ52: =BZ49*$E$52 | CH52: =CH49*$E$52 | CL52: =CL49*$E$52 | CP52: =CP49*$E$52 | CX52: =CX49*$E$52 | DB52: =DB49*$E$52 | DF52: =DF49*$E$52 | DM52: =DM49*$E$52 | DQ52: =DQ49*$E$52 | DU52: =DU49*$E$52 | EC52: =EC49*$E$52 | EG52: =EG49*$E$52 | EK52: =EK49*$E$52 | ES52: =ES49*$E$52 | EW52: =EW49*$E$52 | FA52: =FA49*$E$52
V53: =V52/V48 | Z53: =Z52/Z48 | AD53: =AD52/AD48

Sheet Rad Heat (TATA)
A1: PRICE LIST OF RAD-HEAT GAS HEATING ELEMENTS (W.E.F Aug'22)
H2: Mtr | J2: MS | K2: SS | L2: MS | M2: SS | N2: MS | O2: SS
A3: MODEL | B3: OUTPUT | C3: NOMINAL GAS PER BURNER M³/HR | E3: PRICE WITH SS TUBING | G3: Dia | H3: Tube length | I3: Elbow | J3: Tube Cost | L3: Elbow Cost | N3: total Cost
C4: LPG | D4: NG | Q4: =Rates!A19 | R4: =Rates!B19 | S4: =Rates!C19
A5: ARE-13 | B5: 9 KW | C5: 0.43 | D5: 1.11 | E5: =E15+E19+(O5*4) | G5: 60 | H5: 6 | I5: 8 | J5: =H5*Rates!$C$23 | K5: =H5*Rates!C30*Rates!G30 | M5: =I5*Rates!C36 | N5: =J5+L5 | O5: =K5+M5 | Q5: =Rates!A20 | R5: =Rates!B20 | S5: =Rates!C20
A6: ARE-22 | B6: 17 KW | C6: 0.75 | D6: 2 | E6: =E16+E19+(O6*4) | G6: 76 | H6: 8 | I6: 8 | J6: =H6*Rates!$C$23 | K6: =H6*Rates!C31*Rates!G31 | M6: =I6*Rates!C37 | N6: =J6+L6 | O6: =K6+M6 | Q6: =Rates!A21 | R6: =Rates!B21 | S6: =Rates!C21
A7: ARE-35 | B7: 30 KW | C7: 1.39 | D7: 3.53 | E7: =E17+E20+(O7*4) | G7: 100 | H7: 10.5 | I7: 8 | J7: =H7*Rates!$C$23 | K7: =H7*Rates!C32*Rates!G32 | M7: =I7*Rates!C38 | N7: =J7+L7 | O7: =K7+M7 | Q7: =Rates!A22 | R7: =Rates!B22 | S7: =Rates!C22
A8: ARE-50 | B8: 40 KW | C8: 1.91 | D8: 4.67 | E8: =E18+E20+(O8*4) | G8: 100 | H8: 12 | I8: 8 | J8: =H8*Rates!$C$23 | K8: =H8*Rates!C32*Rates!G32 | M8: =I8*Rates!C38 | N8: =J8+L8 | O8: =K8+M8 | Q8: =Rates!A23 | R8: =Rates!B23 | S8: =Rates!C23
Q9: =Rates!A24 | R9: =Rates!B24 | S9: =Rates!C24
A10: SPARES PRICE FOR AMBIRAD | Q10: =Rates!A25 | R10: =Rates!B25 | S10: =Rates!C25
Q11: =Rates!A26 | R11: =Rates!B26 | S11: =Rates!C26
A12: ITEM | D12: PRICE (Rs.) | J12: 154400 | L12: 159040 | N12: =J12/L12 | Q12: =Rates!A27 | R12: =Rates!B27 | S12: =Rates!C27
A13: SEQUENCE CONTROLLER | E13: 19500 | J13: 188300 | L13: 193950 | N13: =J13/L13 | Q13: =Rates!A28 | R13: =Rates!B28 | S13: =Rates!C28
A14: VACUUM SWITCH | E14: 6500 | J14: 240200 | L14: 247410 | N14: =J14/L14 | Q14: =Rates!A29 | R14: =Rates!B29 | S14: =Rates!C29 | W14: =Rates!G29
A15: ARE-13 Burner Alone | E15: 84500 | J15: 280600 | L15: 289020 | N15: =J15/L15 | Q15: =Rates!A30 | R15: =Rates!B30 | S15: =Rates!C30 | W15: =Rates!G30
A16: ARE-22 Burner Alone | E16: 95000 | Q16: 29 | R16: =Rates!B31 | S16: =Rates!C31 | W16: =Rates!G31
A17: ARE-35 Burner Alone | E17: 101000 | Q17: 30 | R17: =Rates!B32 | S17: =Rates!C32 | W17: =Rates!G32
A18: ARE-50 Burner Alone | E18: 132000 | Q18: 31 | R18: =Rates!B33 | S18: =Rates!C33
A19: ID FAN (ARE 13 & ARE 22) | E19: 31000 | Q19: 32 | R19: =Rates!B34 | S19: =Rates!C34
A20: ID FAN (ARE 35) | E20: 36000 | Q20: 33 | R20: =Rates!B35 | S20: =Rates!C35
A21: ID FAN (HEAVY DUTY) | E21: 48000 | Q21: 34 | R21: =Rates!B36 | S21: =Rates!C36
A22: ID FAN (TYPE O FAN) | E22: 124000 | Q22: 35 | R22: =Rates!B37 | S22: =Rates!C37
A23: SOLENOID VALVE UNIT | E23: 27000 | Q23: 36 | R23: =Rates!B38 | S23: =Rates!C38
A24: ELECTRODE ASSEMBLY | E24: 3500
A25: NOISE FILTER | E25: 2100
A26: INPUT SOCKET | E26: 1400
A27: POWER CABLE | E27: 400
A28: INDICATOR | E28: 300
A29: HT CABLE | E29: 2500
A30: SENSOR CABLE | E30: 1000
A31: WIRING KIT | E31: 10500

Sheet GAIL GAS Burner
B3: A. GAIL GAS BURNER (FOR FURNACES)
B5: Burner Size | C5: Burner | D5: C.I. Burner Plate | E5: Burner Block | F5: Hose | G5: Butterfly Valve | H5: Ball Valve | I5: Burner SET
B6: ENCON-500 KW | C6: 26000 | D6: 7100 | E6: 6700 | F6: 2400 | G6: 3300 | H6: 3900 | I6: 49400
B7: ENCON-1000 KW | C7: 37500 | D7: 8100 | E7: 12700 | F7: 3100 | G7: 3300 | H7: 7800 | I7: 72500
B8: ENCON-2000 KW | C8: 48500 | D8: 8100 | E8: 15600 | F8: 4200 | G8: 9500 | H8: 7800 | I8: 93700
B11: B. PILOT BURNER
B13: ENCON-PB-LPG- 10KW | C13: 11000
B14: ENCON-PB (NG/LPG) - 100 KW | C14: 20000
B15: ENCON-PB-COG- 100KW | C15: 20000
B16: Electrode for LPG pilot burner | C16: 1700
B17: Electrode for COG pilot burner | C17: 3300
B18: Burner Control Unit | C18: 10000
B19: Ignition Transformer | C19: 5500
B20: UV Sensor with Air Jacket | C20: 13000
B23: ALL BURNER BLOCKS ARE MADE OF WHYTE HEAT -K

Sheet Rad Heat
A1: PRICE LIST OF RAD-HEAT GAS HEATING ELEMENTS (W.E.F Aug'22)
H2: Mtr | J2: MS | K2: SS | L2: MS | M2: SS | N2: MS | O2: SS
A3: MODEL | B3: OUTPUT | C3: NOMINAL GAS PER BURNER M³/HR | E3: PRICE WITH SS TUBING | G3: Dia | H3: Tube length | I3: Elbow | J3: Tube Cost | L3: Elbow Cost | N3: total Cost
C4: LPG | D4: NG | Q4: =Rates!A19 | R4: =Rates!B19 | S4: =Rates!C19
A5: ARE-13 | B5: 9 KW | C5: 0.43 | D5: 1.11 | E5: =ROUND(E15+E19+(O5*4),-3) | G5: 60 | H5: 6 | I5: 8 | J5: =H5*Rates!$C$23 | K5: =H5*Rates!C30*Rates!G30 | M5: =I5*Rates!C36 | N5: =J5+L5 | O5: =K5+M5 | Q5: =Rates!A20 | R5: =Rates!B20 | S5: =Rates!C20
A6: ARE-22 | B6: 17 KW | C6: 0.75 | D6: 2 | E6: =ROUND(E16+E19+(O6*4),-3) | G6: 76 | H6: 8 | I6: 8 | J6: =H6*Rates!$C$23 | K6: =H6*Rates!C31*Rates!G31 | M6: =I6*Rates!C37 | N6: =J6+L6 | O6: =K6+M6 | Q6: =Rates!A21 | R6: =Rates!B21 | S6: =Rates!C21
A7: ARE-35 | B7: 30 KW | C7: 1.39 | D7: 3.53 | E7: =ROUND(E17+E20+(O7*3.5),-3) | G7: 100 | H7: 10.5 | I7: 8 | J7: =H7*Rates!$C$23 | K7: =H7*Rates!C32*Rates!G32 | M7: =I7*Rates!C38 | N7: =J7+L7 | O7: =K7+M7 | Q7: =Rates!A22 | R7: =Rates!B22 | S7: =Rates!C22
A8: ARE-50 | B8: 40 KW | C8: 1.91 | D8: 4.67 | E8: =ROUND(E18+E20+(O8*4),-3) | G8: 100 | H8: 12 | I8: 8 | J8: =H8*Rates!$C$23 | K8: =H8*Rates!C32*Rates!G32 | M8: =I8*Rates!C38 | N8: =J8+L8 | O8: =K8+M8 | Q8: =Rates!A23 | R8: =Rates!B23 | S8: =Rates!C23
Q9: =Rates!A24 | R9: =Rates!B24 | S9: =Rates!C24
A10: SPARES PRICE FOR AMBIRAD | Q10: =Rates!A25 | R10: =Rates!B25 | S10: =Rates!C25
Q11: =Rates!A26 | R11: =Rates!B26 | S11: =Rates!C26
A12: ITEM | D12: PRICE (Rs.) | Q12: =Rates!A27 | R12: =Rates!B27 | S12: =Rates!C27
A13: SEQUENCE CONTROLLER | E13: 18600 | H13: 131100 | I13: 154400 | J13: =I13/H13 | Q13: =Rates!A28 | R13: =Rates!B28 | S13: =Rates!C28
A14: VACUUM SWITCH | E14: 6200 | H14: 160900 | I14: 188300 | J14: =I14/H14 | Q14: =Rates!A29 | R14: =Rates!B29 | S14: =Rates!C29 | W14: =Rates!G29
A15: ARE-13 Burner Alone | E15: 82000 | H15: 205300 | I15: 240200 | J15: =I15/H15 | Q15: =Rates!A30 | R15: =Rates!B30 | S15: =Rates!C30 | W15: =Rates!G30
A16: ARE-22 Burner Alone | E16: 92000 | H16: 239800 | I16: 280600 | J16: =I16/H16 | Q16: 29 | R16: =Rates!B31 | S16: =Rates!C31 | W16: =Rates!G31
A17: ARE-35 Burner Alone | E17: 98100 | Q17: 30 | R17: =Rates!B32 | S17: =Rates!C32 | W17: =Rates!G32
A18: ARE-50 Burner Alone | E18: 128000 | Q18: 31 | R18: =Rates!B33 | S18: =Rates!C33
A19: ID FAN (ARE 13 & ARE 22) | E19: 30000 | Q19: 32 | R19: =Rates!B34 | S19: =Rates!C34
A20: ID FAN (ARE 35) | E20: 35000 | Q20: 33 | R20: =Rates!B35 | S20: =Rates!C35
A21: ID FAN (HEAVY DUTY) | E21: 47000 | Q21: 34 | R21: =Rates!B36 | S21: =Rates!C36
A22: ID FAN (TYPE O FAN) | E22: 121000 | Q22: 35 | R22: =Rates!B37 | S22: =Rates!C37
A23: SOLENOID VALVE UNIT | E23: 26000 | Q23: 36 | R23: =Rates!B38 | S23: =Rates!C38
A24: ELECTRODE ASSEMBLY | E24: 3500
A25: NOISE FILTER | E25: 2000
A26: INPUT SOCKET | E26: 1300
A27: POWER CABLE | E27: 300
A28: INDICATOR | E28: 200
A29: HT CABLE | E29: 2500
A30: SENSOR CABLE | E30: 1000
A31: WIRING KIT | E31: 10000

Sheet BURNER
A2: PRICE FOR VARIOUS SIZES OF ENCON `FILM’ BURNER & ACCESSORIES (W.E.F JUL'22)
A4: Burner Size | B4: Burner Alone | C4: Micro Valve | D4: C.I.Burner Plate | E4: High Al. whyteHeat K Burner Block | F4: Flexible Hoses Set | G4: `Y’ type Strainer | H4: Butterfly Valve | I4: Burner Set
A5: ENCON 2A | B5: =SUM(' Oil Burner'!H4:H8)*2.5 | C5: =' Oil Burner'!Q13*2 | D5: =' Oil Burner'!H16*1.8 | E5: =' Oil Burner'!H17*2 | F5: =SUM(' Oil Burner'!H11:H12)*2 | G5: =Rates!K24*2.5 | H5: =' Oil Burner'!H9*2 | I5: =SUM(B5:H5)
A6: ENCON 3A | B6: 14000 | C6: =C5 | D6: 6518 | E6: =E5 | F6: =F5 | G6: =G5 | H6: =H5 | I6: =SUM(B6:H6)
A7: ENCON 4A | B7: =SUM(' Oil Burner'!Q4:Q8)*2.5 | C7: =C6 | D7: =' Oil Burner'!Q16*1.8 | E7: =' Oil Burner'!Q17*2 | F7: =F6 | G7: =G6 | H7: =' Oil Burner'!Q9*2 | I7: =SUM(B7:H7)
A8: ENCON 5A | B8: =SUM(' Oil Burner'!Z4:Z8)*2.5 | C8: =C7 | D8: =' Oil Burner'!Z16*1.8 | E8: =' Oil Burner'!Z17*2.2 | F8: =SUM(' Oil Burner'!Z11:Z12)*2 | G8: =G7 | H8: =' Oil Burner'!Z9*2 | I8: =SUM(B8:H8)
A9: ENCON 6A | B9: =B8 | C9: =C8 | D9: =D8 | E9: =E8 | F9: =F8 | G9: =G8 | H9: =H8 | I9: =SUM(B9:H9)
A10: ENCON 7A | B10: =SUM(' Oil Burner'!AI4:AI13)*2.5 | C10: =Rates!K13*2 | D10: =' Oil Burner'!AI20*1.8 | E10: =' Oil Burner'!AI19*2 | F10: =SUM(' Oil Burner'!AI15:AI16)*2 | G10: =G9 | H10: =' Oil Burner'!AI17*2 | I10: =SUM(B10:H10)
A12: PRICE LIST FOR SPARES OF IIP ENCON OIL FILM BURNERS (W.E.F JUL'22)
A14: Burner Size | B14: S.G. Assembly | C14: Air Resistor
A15: ENCON-2A | B15: =' Oil Burner'!H8*3 | C15: 2900
A16: ENCON-3A | B16: =BURNER!B15+250 | C16: 2900
A17: ENCON-4A | B17: =' Oil Burner'!Q8*3.93 | C17: 3600
A18: ENCON-5A | B18: =' Oil Burner'!Z8*3.4 | C18: 6600
A19: ENCON-6A | B19: =B18+200 | C19: =C18
A20: ENCON-7A | B20: =SUM(' Oil Burner'!AI13*2) | C20: 8100
A22: PRICE FOR VARIOUS SIZES OF ENCON DUAL FUEL BURNER & ACCESSORIES (W.E.F JUL'22)
A25: Burner Size | B25: Burner Alone | C25: Micro Valve | D25: C.I.Burner Plate | E25: High Al. whyteHeat K Burner Block | F25: Flexible Hoses Set | G25: Ball Valve | H25: `Y’ type Strainer | I25: Butterfly Valve | J25: Burner Set
A26: ENCON 2A | B26: =B5+B15 | C26: =C5 | D26: =D5 | E26: =E5 | F26: =F5*3/2-5 | G26: =C54 | H26: =G5 | I26: =H5 | J26: =SUM(B26:I26) | L26: 36000 | M26: =J26/L26
A27: ENCON 3A | B27: =B6+B16 | C27: =C26 | D27: =D6 | E27: =E26 | F27: =F26 | G27: =C55 | H27: =G6 | I27: =H6 | J27: =SUM(B27:I27) | L27: 37800 | M27: =J27/L27
A28: ENCON 4A | B28: =B7+B17 | C28: =C27 | D28: =D7 | E28: =E7 | F28: =F27 | G28: =C56 | H28: =G7 | I28: =H7 | J28: =SUM(B28:I28) | L28: 46100 | M28: =J28/L28
A29: ENCON 5A | B29: =B8+B18 | C29: =C28 | D29: =D8 | E29: 11850 | F29: =F8*3/2 | G29: =C57 | H29: =G8 | I29: =H8 | J29: =SUM(B29:I29) | L29: 66000 | M29: =J29/L29
A30: ENCON 6A | B30: =B9+B19 | C30: =C29 | D30: =D9 | E30: =E29 | F30: =F29 | G30: =C58 | H30: =G9 | I30: =H9 | J30: =SUM(B30:I30) | L30: 70400 | M30: =J30/L30
A31: ENCON 7A | B31: =B10+B20 | C31: =C30 | D31: =D10 | E31: =E10 | F31: =F10*3/2 | G31: =C59 | H31: =G10 | I31: =H10 | J31: =SUM(B31:I31) | L31: 138300 | M31: =J31/L31
A33: PRICE LIST FOR HIGH VELOCITY OIL BURNERS (W.E.F JUL'22)
A35: Burner Size | C35: Burner Alone | D35: Burner Block | E35: Micro Valve | F35: Flexible Hoses Set | G35: `Y’ type Strainer | H35: Butterfly Valve | I35: Burner Set
A36: ENCON HV-3A | C36: =B6 | D36: 44000 | E36: =C5 | F36: =SUM('HV Oil Burner'!H7:H8)*2 | G36: =H27 | H36: =H6 | I36: =SUM(C36:H36)
A37: ENCON HV-4A | C37: =B7 | D37: 59000 | E37: =C6 | F37: =SUM('HV Oil Burner'!Q7:Q8)*2 | G37: =H28 | H37: =H7 | I37: =SUM(C37:H37)
A38: ENCON HV-5A | C38: =B8 | D38: 71500 | E38: =C7 | F38: =F37 | G38: =H29 | H38: =H8 | I38: =SUM(C38:H38)
A39: ENCON HV-6A | C39: =B9 | D39: 161000 | E39: =C8 | F39: =SUM('HV Oil Burner'!Z7:Z9)*2 | G39: =H30 | H39: =H9 | I39: =SUM(C39:H39)
A40: ENCON HV-7A | C40: =B10 | D40: 201300 | E40: =C10 | F40: =SUM('HV Oil Burner'!AI14:AI15)*2 | G40: =H31 | H40: =H10 | I40: =SUM(C40:H40)
A42: PRICE LIST FOR HIGH VELOCITY GAS BURNERS (W.E.F JUL'22)
A44: Burner Size | C44: Burner Alone | D44: Burner Block | E44: Ball Valve | F44: Flexible Hoses Set | G44: Butterfly Valve | H44: Burner Set
A45: ENCON HV-3A | C45: =B55 | D45: =D36 | E45: =C55 | F45: =F55 | G45: =H36 | H45: =SUM(C45:G45)
A46: ENCON HV-4A | C46: =B56 | D46: =D37 | E46: =C56 | F46: =F56 | G46: =H37 | H46: =SUM(C46:G46)
A47: ENCON HV-5A | C47: =B57 | D47: =D38 | E47: =C57 | F47: =F57 | G47: =H38 | H47: =SUM(C47:G47)
A48: ENCON HV-6A | C48: =B58 | D48: =D39 | E48: =C58 | F48: =F58 | G48: =H39 | H48: =SUM(C48:G48)
A49: ENCON HV-7A | C49: =B59 | D49: =D40 | E49: =C59 | F49: =F59 | G49: =H40 | H49: =SUM(C49:G49)
A51: PRICE FOR VARIOUS SIZES OF ENCON `GAS’ BURNER & ACCESSORIES (W.E.F JUL'22)
A53: Burner Size | B53: Burner Alone | C53: Ball Valve | D53: C.I.Burner Plate | E53: High Al. whyteHeat K Burner Block | F53: Flexible Hoses Set | G53: Butterfly Valve | H53: Burner Set
A54: ENCON 2A | B54: =B5 | C54: =2*Rates!K28*78% | D54: =D5 | E54: =E5 | F54: =F5 | G54: =H5 | H54: =SUM(B54:G54)
A55: ENCON 3A | B55: =B6 | C55: =C54 | D55: =D6 | E55: =E6 | F55: =F6 | G55: =H6 | H55: =SUM(B55:G55)
A56: ENCON 4A | B56: =B7 | C56: =2*Rates!K26*78% | D56: =D7 | E56: =E7 | F56: =F7 | G56: =H7 | H56: =SUM(B56:G56)
A57: ENCON 5A | B57: =B8 | C57: =2*Rates!K29*78% | D57: =D8 | E57: =E8 | F57: =F8 | G57: =H8 | H57: =SUM(B57:G57)
A58: ENCON 6A | B58: =B9 | C58: =2*Rates!K30*78% | D58: =D9 | E58: =E9 | F58: =F9 | G58: =H9 | H58: =SUM(B58:G58)
A59: ENCON 7A | B59: =B10 | C59: =C58 | D59: =D10 | E59: =E10 | F59: =F10 | G59: =H10 | H59: =SUM(B59:G59)
A62: PRICE LIST FOR PILOT BURNER BURNERS
A64: ENCON-PB-LPG -10 KW | C64: 11000
A65: ENCON( NG/LPG) -100 KW | C65: 21000
A66: ENCON PB COG 100 KW | C66: 32000
A67: Electrode for LPG pilot burner | C67: 1650
A68: Electrode for COG pilot burner | C68: 3300
A69: Burner Control Unit | C69: 10000
A70: Ignition tranformer | C70: 5500
A71: UV Sesnor with air jacket | C71: 13000
A74: PRICE LIST FOR GAS Burner (W.E.F JUL'22)
A76: GAIL design (Hole Type) | B76: Burner Alone (SS Pipe) | C76: C.I.Burner Plate | D76: High Al. Burner Block | E76: Hose | F76: Butterfly Valve | G76: Ball Valve | H76: Burner Assly
A77: 500 KW | B77: 26000 | C77: =D7 | D77: =E7 | E77: =F7 | F77: =H7 | G77: =C56 | H77: =SUM(B77:G77)
A78: 1000 KW | B78: 37500 | C78: =D9 | D78: =E9 | E78: =F8 | F78: =I30 | G78: =C58 | H78: =SUM(B78:G78)
A79: 2000 KW | B79: 48500 | C79: =D59 | D79: =E10 | E79: =F9 | F79: 9500 | G79: =C59 | H79: =SUM(B79:G79)
A81: Ada (Casting Type) | B81: Burner Alone | C81: C.I.Burner Plate | D81: High Al. Burner Block | E81: Hose | F81: Butterfly Valve | G81: Ball Valve | H81: Burner Assly
A82: 1000 KW | B82: 13540 | C82: =D9 | D82: =E8 | E82: =F8 | F82: 3000 | G82: =3728*0.55*2 | H82: =SUM(B82:G82)

Sheet Horizontal
A1: S.NO. | B1: 10 TON HORIZONTAL LADLE PREHEATER | C1: QTY | D1: AMOUNT(Rs.) | F1: S.NO. | G1: 15 TON HORIZONTAL LADLE PREHEATER | H1: QTY | I1: AMOUNT(Rs.) | K1: S.NO. | L1: 20 TON HORIZONTAL LADLE PREHEATER | M1: QTY | N1: AMOUNT(Rs.)
A2: 1 | B2: MS Structure | C2: 1096 Kgs. | D2: =ROUND(1096*Rates!C12*2.1,-2) | F2: 1 | G2: MS Structure | H2: 1236 Kgs. | I2: =ROUND(2.1*1236*Rates!C12,-2) | K2: 1 | L2: MS Structure | M2: 1416 Kgs. | N2: =ROUND(1416*2.1*Rates!C12,-2)
A3: 2 | B3: Combustion Equipment: | F3: 2 | G3: Combustion Equipment: | K3: 2 | L3: Combustion Equipment:
B4: a. Encon Film Burner -3A | C4: 3A | D4: =BURNER!I6 | G4: a. Encon Film Burner (4A) – 1Set. | H4: 1 | I4: =BURNER!I7 | L4: a. Encon Film Burner (4A) – 1Set. | M4: 1 | N4: =BURNER!I7
B5: b. Blower 5/40" | C5: 5/40" | D5: =Blower!G17 | G5: b. Blower 10/40” – 1 No. | H5: 1 | I5: =(Blower!J19*1.8)+(Blower!K18*1.5) | L5: b. Blower 15/40” – 1 No. | M5: 1 | N5: =(Blower!J20*1.8)+(Blower!K19*1.5)
B6: c. H & P Unit 3kW-1No,(HPD-3) | C6: HPD-3 | D6: =ROUND(HPU!F49*1.8,-2) | G6: c. H & P Unit 6 kW – 1No .(HPD-6) | H6: 1 | I6: =ROUND(HPU!V48*1.8,-2) | L6: c. H & P Unit 6 kW – 1No .(HPD-6) | M6: 1 | N6: =ROUND(HPU!V48*1.8,-2)
A7: 3 | B7: Ceramic fiber | C7: 9 Rolls | D7: =ROUND(2.1*Rates!C29*9,-2) | F7: 3 | G7: Ceramic fiber | H7: 11 Rolls | I7: =ROUND(2.1*11*Rates!C29,-2) | K7: 3 | L7: Ceramic fiber | M7: 13 Rolls | N7: =2.1*13*Rates!C29
A8: 4 | B8: Control Panel | C8: 1Set | D8: =2.1*60000 | F8: 4 | G8: Control Panel | H8: 1Set | I8: =2.1*60000 | K8: 4 | L8: Control Panel | M8: 1Set | N8: =2.1*60000
A9: 5 | B9: Pipeline and Fittings, Nut, Bolts, paint | D9: =2.1*22000 | F9: 5 | G9: Pipeline and Fittings, Nut, Bolts, paint | I9: =2.1*24000 | K9: 5 | L9: Pipeline and Fittings, Nut, Bolts, paint | N9: =2.1*55000
A10: 6 | B10: Trolley Drive Mechanism | D10: =1.8*69000 | F10: 6 | G10: Trolley Drive Mechanism | I10: =1.8*70500 | K10: 6 | L10: Trolley Drive Mechanism | N10: =1.8*72000
C11: TOTAL | D11: =SUM(D2:D10) | H11: TOTAL | I11: =SUM(I2:I10) | M11: TOTAL | N11: =SUM(N2:N10)
A13: S.NO. | B13: 30 TON HORIZONTAL LADLE PREHEATER | C13: QTY | D13: AMOUNT(Rs.) | F13: S.NO. | G13: 35-40 TON HORIZONTAL LADLE PREHEATER | H13: QTY | I13: AMOUNT(Rs.) | K13: S.NO. | L13: 60 TON HORIZONTAL LADLE PREHEATER | M13: QTY | N13: AMOUNT(Rs.)
A14: 1 | B14: MS Structure | C14: 1450 Kgs. | D14: =2.1*1450*Rates!C12 | F14: 1 | G14: MS Structure | H14: 1500 Kgs. | I14: =2.1*1500*Rates!C12 | K14: 1 | L14: MS Structure | M14: 1683 Kgs. | N14: =ROUND(2.1*1683*Rates!C12,-2)
A15: 2 | B15: Combustion Equipment: | F15: 2 | G15: Combustion Equipment: | K15: 2 | L15: Combustion Equipment:
B16: a. Encon Film Burner (5A) – 1Set. | C16: 1 | D16: =BURNER!I8 | G16: a. Encon Film Burner (5A) – 1Set. | H16: 1 | I16: =BURNER!I8 | L16: a. Encon Film Burner (5A) – 1Set. | M16: 1 | N16: =BURNER!I8
B17: b. Blower20/40” – 1 No. | C17: 1 | D17: =(Blower!J21*1.8)+(Blower!K20*1.5) | G17: b. Blower 20/40” – 1 No. | H17: 1 | I17: =Blower!J21*1.8+Blower!K20*1.5 | L17: b. Blower30/40” – 1 No. | M17: 1 | N17: =Blower!J23*1.5+Blower!K22*1.5
B18: c. H & P Unit 12 kW – 1No .(HPD-12) | C18: 1 | D18: =ROUND(HPU!BB49*1.8,-2) | G18: c. H & P Unit 12 kW – 1No .(HPD-12) | H18: 1 | I18: =ROUND(HPU!BB49*1.8,-2) | L18: c. H & P Unit 20 kW – 1No .(HPD-20) | M18: 1 | N18: =ROUND(HPU!CH49*1.8,-2)
A19: 3 | B19: Ceramic fiber | C19: 14 Rolls | D19: =2.1*14*Rates!C29 | F19: 3 | G19: Ceramic fiber | H19: 15 Rolls | I19: =ROUND(2.1*15*Rates!C29,-2) | K19: 3 | L19: Ceramic fiber | M19: 19Rolls | N19: =1.8*19*Rates!C29
A20: 4 | B20: Control Panel | C20: 1Set | D20: =2.1*75000 | F20: 4 | G20: Control Panel | H20: 1Set | I20: =2.1*75000 | K20: 4 | L20: Trolley Drive System | N20: =2.1*106000
A21: 5 | B21: Pipeline and Fittings, Nut, Bolts, paint | D21: =2.1*65000 | F21: 5 | G21: Pipeline and Fittings, Nut, Bolts, paint | I21: =2.1*78000 | K21: 5 | L21: Control Panel | M21: 1Set | N21: =1.8*75000
A22: 6 | B22: Trolley Drive Mechanism | D22: =1.8*77500 | F22: 6 | G22: Trolley Drive Mechanism | I22: =1.8*80000 | K22: 6 | L22: Pipeline and Fittings, Nut, Bolts, paint | N22: =2.1*80000
C23: TOTAL | D23: =SUM(D14:D22) | H23: TOTAL | I23: =SUM(I14:I22) | K23: Total | N23: =SUM(N14:N22)
A25: Note:
A26: 1. LPG Pilot for the above system will cost Rs.1,00,000.00 extra | J26: Change colored cell manually in this sheet
A29: Prices | C29: Prices quoted are ex-works, Faridabad.
A30: Packing & Forwarding | C30: 4% & 2% respectively
A31: Taxes & Duties | C31: As applicable shall be charged extra. At present Excise Duty is 14 % Education Cess 2% and Secondary Higher Education cess @ 1% . CST @ 2% against Form C otherwise 12.5%.
A32: Terms of Payment | C32: 50% Advance alongwith purchase order. 50% payment with taxes and duties against despatch.
A33: Validity | C33: 45 Days.

Sheet Vertical
A2: S.NO. | B2: DESCRIPTION( Vertical 10 ton lps) | C2: QTY | D2: AMOUNT(Rs.) | F2: S.NO. | G2: DESCRIPTION( Vertical 12-14 ton lps) | H2: QTY | I2: AMOUNT(Rs.) | K2: S.NO. | L2: DESCRIPTION( Vertical 15 ton lps) | M2: QTY | N2: AMOUNT(Rs.)
A3: 1 | B3: MS Structure | C3: 1096 Kgs. | D3: =1096*Rates!C13*2.1 | F3: 1 | G3: MS Structure | H3: 1130 Kgs. | I3: =2.1*1130*Rates!C12 | K3: 1 | L3: MS Structure | M3: 1215Kgs. | N3: =2.1*1215*Rates!C12
A4: 2 | B4: Combustion Equipment: | F4: 2 | G4: Combustion Equipment: | K4: 2 | L4: Combustion Equipment:
B5: a. Encon Film Burner -3A | C5: 3A | D5: =BURNER!I6 | G5: a. Encon Film Burner (4A) – 1Set. | H5: 1 | I5: =BURNER!I7 | L5: a. Encon Film Burner (4A) – 1Set. | M5: 1 | N5: =BURNER!I7
B6: b. Blower 5/40" | C6: 5/40" | D6: =Blower!G17 | G6: b. Blower 7.5/40” – 1 No. | H6: 1 | I6: =Blower!J18*1.8+Blower!K17*1.5 | L6: b. Blower 10/40” – 1 No. | M6: 1 | N6: =Blower!J19*1.8+Blower!K18*1.8
B7: c. H & P Unit 3kW-1No,(HPD-3) | C7: HPD-3 | D7: =HPU!F49*1.8 | G7: c. H & P Unit 6 kW – 1No .(HPD-6) | H7: 1 | I7: =HPU!V48*1.8 | L7: c. H & P Unit 6 kW – 1No .(HPD-6) | M7: 1 | N7: =HPU!V48*1.8
A8: 3 | B8: Ceramic fiber | C8: 9 Rolls | D8: =2.1*9*Rates!C29 | F8: 3 | G8: Ceramic fiber | H8: 8 Rolls | I8: =2.1*8*Rates!C29 | K8: 3 | L8: Ceramic fiber | M8: 9 Rolls | N8: =2.1*9*Rates!C29
A9: 4 | B9: Control Panel | C9: 1Set | D9: =2.1*50000 | F9: 4 | G9: Control Panel | H9: 1Set | I9: =2.1*50000 | K9: 4 | L9: Control Panel | M9: 1Set | N9: =2.1*55000
A10: 5 | B10: Swirling mech, Pipeline and Fittings, Nut, Bolts, paint | D10: =2.1*59490 | F10: 5 | G10: Swirling mech, Pipeline and Fittings, Nut, Bolts, paint | I10: =2.1*66213 | K10: 5 | L10: Swirling mech, Pipeline and Fittings, Nut, Bolts, paint | N10: =2.1*70000
C11: TOTAL | D11: =SUM(D3:D10) | H11: TOTAL | I11: =SUM(I3:I10) | M11: TOTAL | N11: =SUM(N3:N10)
A13: S.NO. | B13: DESCRIPTION( Vertical 16-20 ton lps) | C13: QTY | D13: AMOUNT(Rs.) | F13: S.NO. | G13: DESCRIPTION( Vertical 30 ton lps) | H13: QTY | I13: AMOUNT(Rs.) | K13: S.NO. | L13: DESCRIPTION( Vertical 30 to 40 ton lps) | M13: QTY | N13: AMOUNT(Rs.)
A14: 1 | B14: MS Structure | C14: 1300Kgs. | D14: =2.1*1300*Rates!C12 | F14: 1 | G14: MS Structure | H14: 1354 Kgs. | I14: =2.1*1354*Rates!C12 | K14: 1 | L14: MS Structure | M14: 1773 Kgs. | N14: =2.1*1773*Rates!C12
A15: 2 | B15: Combustion Equipment: | F15: 2 | G15: Combustion Equipment: | K15: 2 | L15: Combustion Equipment:
B16: a. Encon Film Burner (4A) – 1Set. | C16: 1 | D16: =BURNER!I7 | G16: a. Encon Film Burner (5A) – 1Set. | H16: 1 | I16: =BURNER!I8 | L16: a. Encon Film Burner (5A) – 1Set. | M16: 1 | N16: =BURNER!I8
B17: b. Blower 15/40” – 1 No. | C17: 1 | D17: =Blower!J20*1.8+Blower!K19*1.5 | G17: b. Blower20/40” – 1 No. | H17: 1 | I17: =Blower!J21*1.8+Blower!K20*1.5 | L17: b. Blower 20/40” – 1 No. | M17: 1 | N17: =Blower!J21*1.8+Blower!K20*1.5
B18: c. H & P Unit 6 kW – 1No .(HPD-6) | C18: 1 | D18: =HPU!V48*1.8 | G18: c. H & P Unit 12 kW – 1No .(HPD-12) | H18: 1 | I18: =HPU!BB49*1.8 | L18: c. H & P Unit 12 kW – 1No .(HPD-12) | M18: 1 | N18: =HPU!BB49*1.8
A19: 3 | B19: Ceramic fiber | C19: 10 Rolls | D19: =2.1*10*Rates!C29 | F19: 3 | G19: Ceramic fiber | H19: 11Rolls | I19: =2.1*11*Rates!C29 | K19: 3 | L19: Ceramic fiber | M19: 13Rolls | N19: =2.1*13*Rates!C29
A20: 4 | B20: Control Panel | C20: 1Set | D20: =2.1*55000 | F20: 4 | G20: Control Panel | H20: 1Set | I20: =2.1*70000 | K20: 4 | L20: Control Panel | M20: 1Set | N20: =2.1*70000
A21: 5 | B21: Swirling mech, Pipeline and Fittings, Nut, Bolts, paint | D21: =2.1*75415 | F21: 5 | G21: Swirling mech, Pipeline and Fittings, Nut, Bolts, paint | I21: =2.1*80000 | K21: 5 | L21: Swirling mech, Pipeline and Fittings, Nut, Bolts, paint | N21: =2.1*85000
C22: TOTAL | D22: =SUM(D14:D21) | H22: TOTAL | I22: =SUM(I14:I21) | M22: TOTAL | N22: =SUM(N14:N21)
A24: S.NO. | B24: DESCRIPTION( Vertical 50 to 60 ton lps) | C24: QTY | D24: AMOUNT(Rs.)
A25: 1 | B25: MS Structure | C25: 1800 Kgs. | D25: =2.1*1800*45
A26: 2 | B26: Combustion Equipment: | H26: Change colored cell manually in this sheet
B27: a. Encon Film Burner (5A) – 1Set. | C27: 1 | D27: =BURNER!I8
B28: b. Blower30/40” – 1 No. | C28: 1 | D28: =Blower!J23*1.8+Blower!K22*1.5
B29: c. H & P Unit 20 kW – 1No .(HPD-20) | C29: 1 | D29: =HPU!CH49*1.8
A30: 3 | B30: Ceramic fiber | C30: 19Rolls | D30: =2.1*19*Rates!C29
A31: 4 | B31: Control Panel | C31: 1Set | D31: =2.1*70000
A32: 5 | B32: Swirling mech, Pipeline and Fittings, Nut, Bolts, paint | D32: =2.1*90000
C33: TOTAL | D33: =SUM(D25:D32)
A36: Note:
A37: 1. LPG Pilot for the above system will cost Rs.1,00,000.00 extra
A38: 2. System will hydraulic system for lowering and lifting will cost Rs.1,50,000.00 extra
A40: Prices | C40: Prices quoted are ex-works, Faridabad.
A41: Packing & Forwarding | C41: 4% & 2% respectively
A42: Taxes & Duties | C42: As applicable shall be charged extra. At present Excise Duty is 14 % Education Cess 2% and Secondary Higher Education cess @ 1% . CST @ 2% against Form C otherwise 12.5%.
A43: Terms of Payment | C43: 50% Advance alongwith purchase order. 50% payment with taxes and duties against despatch.
A44: Validity | C44: 45 Days.
